Workbook

Sheet Resumo
A1: Distribuição de Prospects por Vendedor
A3: Critério de distribuição: round-robin (intercalado) para balancear UF e setor entre os 4 vendedores.
A5: Vendedor | B5: Qtd. Empresas | C5: Faturamento Total Presumido (R$) | D5: Total Funcionários
A6: Vendedor 1 | B6: =COUNTA(sandra!A5:A100) -> 9 | C6: =SUM(sandra!E5:E100) -> 8314794066 | D6: =SUM(sandra!G5:G100) -> 1161
A7: Vendedor 2 | B7: =COUNTA(adriana!A5:A100) -> 9 | C7: =SUM(adriana!E5:E100) -> 6953179766 | D7: =SUM(adriana!G5:G100) -> 2896
A8: Vendedor 3 | B8: =COUNTA(gislaine!A5:A100) -> 9 | C8: =SUM(gislaine!E5:E100) -> 6518176209 | D8: =SUM(gislaine!G5:G100) -> 3137
A9: Vendedor 4 | B9: =COUNTA(eduardo!A5:A100) -> 8 | C9: =SUM(eduardo!E5:E100) -> 5828208079 | D9: =SUM(eduardo!G5:G100) -> 1905
A10: TOTAL | B10: =SUM(B6:B9) -> 35 | C10: =SUM(C6:C9) -> 27614358120 | D10: =SUM(D6:D9) -> 9099
A13: Distribuição por UF
A14: UF | B14: Vendedor 1 | C14: Vendedor 2 | D14: Vendedor 3 | E14: Vendedor 4 | F14: Total
A15: BA | B15: 1 | C15: 0 | D15: 0 | E15: 0 | F15: =SUM(B15:E15) -> 1
A16: GO | B16: 1 | C16: 0 | D16: 0 | E16: 0 | F16: =SUM(B16:E16) -> 1
A17: MA | B17: 0 | C17: 0 | D17: 1 | E17: 0 | F17: =SUM(B17:E17) -> 1
A18: MG | B18: 0 | C18: 0 | D18: 1 | E18: 1 | F18: =SUM(B18:E18) -> 2
A19: PR | B19: 0 | C19: 1 | D19: 2 | E19: 0 | F19: =SUM(B19:E19) -> 3
A20: RJ | B20: 0 | C20: 1 | D20: 0 | E20: 1 | F20: =SUM(B20:E20) -> 2
A21: RN | B21: 0 | C21: 0 | D21: 0 | E21: 1 | F21: =SUM(B21:E21) -> 1
A22: RS | B22: 1 | C22: 4 | D22: 1 | E22: 1 | F22: =SUM(B22:E22) -> 7
A23: SC | B23: 3 | C23: 0 | D23: 2 | E23: 2 | F23: =SUM(B23:E23) -> 7
A24: SP | B24: 3 | C24: 3 | D24: 2 | E24: 2 | F24: =SUM(B24:E24) -> 10
A26: Dica: cada aba já vem com filtro automático, cabeçalho congelado e as 3 primeiras colunas fixadas para facilitar a navegação.

Sheet sandra
A1: Carteira de Prospects — Vendedor 1
A2: Total de empresas: 9 | Porte: GRANDE | Fonte: Base de prospecção
A4: CNPJ | B4: Razão Social | C4: Nome Fantasia | D4: Porte | E4: Faturamento Presumido (R$) | F4: Capital Social (R$) | G4: Qtd. Funcionários | H4: Score | I4: Classificação de Risco | J4: Situação Cadastral | K4: CNAE | L4: Atividade Principal | M4: Data Abertura | N4: Qtd. Filiais | O4: Logradouro | P4: Nº | Q4: Complemento | R4: Bairro | S4: Cidade | T4: UF | U4: CEP | V4: DDD 1 | W4: Telefone 1 | X4: Tipo 1 | Y4: DDD 2 | Z4: Telefone 2 | AA4: Tipo 2 | AB4: DDD 3 | AC4: Telefone 3 | AD4: Tipo 3 | AE4: DDD 4 | AF4: Telefone 4 | AG4: Tipo 4 | AH4: E-mail 1 | AI4: E-mail 2 | AJ4: E-mail 3 | AK4: Sócio 1 | AL4: Cargo Sócio 1 | AM4: DDD Sócio 1 | AN4: Tel. Sócio 1 | AO4: Sócio 2 | AP4: Cargo Sócio 2 | AQ4: DDD Sócio 2 | AR4: Tel. Sócio 2 | AS4: Sócio 3 | AT4: Cargo Sócio 3 | AU4: DDD Sócio 3 | AV4: Tel. Sócio 3 | AW4: CNAEs Secundários | AX4: Inscrição Estadual | AY4: Flag DAU
A5: 04.700.714/0001-63 | B5: APM TERMINALS ITAJAI S.A. | D5: GRANDE | E5: 2688665738 | F5: 408321804 | G5: 56 | H5: 784 | I5: RISCO MUITO BAIXO | J5: ATIVA | K5: 5231102 | L5: Atividades do Operador Portuário | M5: 10/8/2001 | N5: 1 | O5: PEDRO FERREIRA | P5: 333 | Q5: SALA 1302 EDIF ABSOLUTE B HOTEL | R5: CENTRO | S5: ITAJAI | T5: SC | U5: 88301030 | V5: 47 | W5: 988692484 | X5: Celular | Y5: 47 | Z5: 988051681 | AA5: Celular | AB5: 47 | AC5: 991599797 | AD5: Celular | AE5: 47 | AF5: 33419900 | AG5: Fixo | AH5: INVOICE.BRAZIL@APMTERMINALS.COM | AK5: JACKELINE DAROS ABREU | AL5: DIRETOR | AM5: 47 | AN5: 999228111 | AO5: DANIEL ROSE | AP5: PRESIDENTE | AQ5: 47 | AR5: 996525784 | AS5: FRANCIELI BRIEDIS | AT5: DIRETOR | AU5: 47 | AV5: 999257252 | AW5: 5211799-Depósitos de mercadorias para terceiros, exceto armazéns gerais e guarda-móveis\7739099-Aluguel de outras máquinas e equipamentos comerciais e industriais não especificados anteriormente, sem operador | AX5: 254306527 | AY5: N
A6: 07.030.611/0001-21 | B6: PORTINVEST PARTICIPACOES S.A. | D6: GRANDE | E6: 991219896 | F6: 264138460 | H6: 838 | I6: RISCO MUITO BAIXO | J6: ATIVA | K6: 5231102 | L6: Atividades do Operador Portuário | M6: 9/23/2004 | N6: 0 | O6: DONA FRANCISCA | P6: 8300 | Q6: BLOCO L SALA 15 UNIDADE EBANO COND PERINI BUSINES PARK | R6: ZONA INDUSTRIAL NORTE | S6: JOINVILLE | T6: SC | U6: 89219600 | V6: 47 | W6: 999691349 | X6: Celular | Y6: 47 | Z6: 38032224 | AA6: Fixo | AH6: DIRETORIA@ITAPOASA.COM | AI6: IVETE.DUCATI@BATTISTELLA.COM.BR | AK6: JOSE ANTONIO DA ROSA NETO | AL6: DIRETOR | AM6: 11 | AN6: 969187224 | AO6: MAURICIO VALENTE BATTISTELLA | AP6: DIRETOR | AQ6: 11 | AR6: 992201612 | AW6: 5231101-Administração da infraestrutura portuária\ | AY6: N
A7: 40.561.649/0001-04 | B7: TERMINAL PORTUARIO COTEGIPE S.A | C7: PORTO COTEGIPE | D7: GRANDE | E7: 899143689 | F7: 110882968 | G7: 188 | H7: 920 | I7: RISCO MUITO BAIXO | J7: ATIVA | K7: 5231102 | L7: Atividades do Operador Portuário | M7: 9/26/1991 | N7: 0 | O7: PONTA DO FERNANDINHO | P7: 3142 | R7: SAO TOME | S7: SALVADOR | T7: BA | U7: 40800168 | V7: 71 | W7: 33112203 | X7: Fixo | AH7: SIMONE.CARMO@DIBRA.COM.BR | AK7: FRANCISCO CLAUDIO SARAIVA LEAO DIAS BRANCO | AL7: ADMINISTRADOR | AM7: 88 | AN7: 997143353 | AO7: JORGE HUMBERTO PESSOA LOPES | AP7: DIRETOR | AQ7: 71 | AR7: 999178496 | AS7: FRANCISCO IVENS DE SA DIAS BRANCO JUNIOR | AT7: DIRETOR | AU7: 35 | AV7: 997571928 | AW7: 5211701-Armazéns gerais - emissão de warrant\5231101-Administração da infraestrutura portuária\6462000-Holdings de instituições não financeiras\ | AX7: 027.106.815 | AY7: N
A8: 02.703.755/0001-88 | B8: ADONAI QUIMICA S/A | D8: GRANDE | E8: 768457597 | F8: 150000000 | H8: 920 | I8: RISCO MUITO BAIXO | J8: ATIVA | K8: 5211701 | L8: Armazéns gerais - emissão de warrant | M8: 8/1/1998 | N8: 2 | O8: GOMES DE CARVALHO | P8: 1306 | Q8: ANDAR 8 SALA 85 | R8: VILA OLIMPIA | S8: SAO PAULO | T8: SP | U8: 4547005 | V8: 11 | W8: 30488822 | X8: Fixo | AH8: ALEX.PELEGRINI@ADONAIQUIMICA.COM.BR | AI8: ALLAN.DIAS@ADONAIQUIMICA.COM.BR | AJ8: EDUARDO@ADONAIQUIMICA.COM.BR | AK8: LEANDRO LUIZ CHIACHIO | AL8: DIRETOR | AM8: 13 | AN8: 981110043 | AO8: AMERICO RELVAS DA ROCHA | AP8: PRESIDENTE | AQ8: 11 | AR8: 930265174 | AS8: LUIS GUSTAVO BATISTA | AT8: DIRETOR | AU8: 13 | AV8: 997141463 | AX8: 148.300.992.110 | AY8: N
A9: 58.138.058/0001-86 | B9: EUDMARCO S.A. SERVICOS E COMERCIO INTERNACIONAL | D9: GRANDE | E9: 723719465 | F9: 27532515 | H9: 913 | I9: RISCO MUITO BAIXO | J9: ATIVA | K9: 5211701 | L9: Armazéns gerais - emissão de warrant | M9: 9/1/1966 | N9: 2 | O9: GOMES DE CARVALHO | P9: 1306 | Q9: CONJ 82 SALA 03 | R9: VILA OLIMPIA | S9: SAO PAULO | T9: SP | U9: 4547005 | V9: 11 | W9: 30488729 | X9: Fixo | AH9: EDUARDO.MORAES@EUDMARCO.COM.BR | AI9: LCARVALHO@EUDMARCOAG.COM.BR | AJ9: ANTONIA.OLIVEIRA@EUDMARCO.COM.BR | AK9: AMERICO RELVAS DA ROCHA | AL9: DIRETOR | AM9: 11 | AN9: 930265174 | AO9: LUIS GUSTAVO BATISTA | AP9: DIRETOR | AQ9: 13 | AR9: 997141463 | AS9: LUIS ANTONIO FLORIANO | AT9: PRESIDENTE | AU9: 98 | AV9: 984951792 | AW9: 4930201-Transporte rodoviário de carga, exceto produtos perigosos e mudanças, municipal\4930202-Transporte rodoviário de carga, exceto produtos perigosos e mudanças, intermunicipal, interestadual e internacional\4930203-Transporte rodoviário de produtos perigosos\5250802-Atividades de despachantes aduaneiros | AX9: 108.360.070.110 | AY9: S
A10: 62.576.327/0001-63 | B10: FUPRESA S.A. | D10: GRANDE | E10: 614390284 | F10: 39028200 | G10: 1 | H10: 847 | I10: RISCO MUITO BAIXO | J10: ATIVA | K10: 2451200 | L10: Fundição de ferro e aço | M10: 12/16/1969 | N10: 1 | O10: ENGENHEIRO ERMENIO DE OLIVEIRA PENTEADO | P10: SN | Q10: KM 47 6 | R10: CALDEIRA | S10: INDAIATUBA | T10: SP | U10: 13347600 | V10: 11 | W10: 999009799 | X10: Celular | Y10: 19 | Z10: 38859606 | AA10: Fixo | AH10: CONTABILIDADE@FUPRESA.COM.BR | AI10: ANDRE@FUPRESA.COM.BR | AJ10: ARMANDO.NETO@FUPRESA.COM.BR | AK10: PAULO ROBERTO RODRIGUES BUTORI | AL10: DIRETOR | AM10: 11 | AN10: 983329949 | AO10: ANTONIO CARLOS ALVES BEVILACQUA | AP10: DIRETOR | AX10: 112.289.553.110 | AY10: N
A11: 02.680.379/0001-53 | B11: PORTO SECO CENTRO OESTE S/A | C11: EADI ANAPOLIS | D11: GRANDE | E11: 565608816 | F11: 21500000 | G11: 246 | H11: 523 | I11: RISCO BAIXO | J11: ATIVA | K11: 5231102 | L11: Atividades do Operador Portuário | M11: 2/7/1980 | N11: 2 | O11: VP 5E | P11: SN | Q11: QD 09 MOD 07 | R11: DISTRITO AGROINDUSTRIAL DE ANAPOLIS | S11: ANAPOLIS | T11: GO | U11: 75132125 | V11: 62 | W11: 991472245 | X11: Celular | Y11: 62 | Z11: 998212843 | AA11: Celular | AB11: 62 | AC11: 998239489 | AD11: Celular | AE11: 62 | AF11: 33106100 | AG11: Fixo | AH11: PORTO@PORTOCENTROOESTE.COM.BR | AI11: PORTO.COMPRAS@PORTOCENTROOESTE.COM.BR | AK11: SAID VIEIRA BORGES | AL11: PRESIDENTE | AM11: 62 | AN11: 999289888 | AO11: EVERALDO FIATKOSKI JUNIOR | AP11: DIRETOR | AQ11: 62 | AR11: 984368000 | AS11: ROBERTO RASSI | AT11: DIRETOR | AW11: 5120000-Transporte aéreo de carga\5211701-Armazéns gerais - emissão de warrant\5211799-Depósitos de mercadorias para terceiros, exceto armazéns gerais e guarda-móveis\5212500-Carga e descarga\5222200-Terminais rodoviários e ferroviários\5231101-Administração da infraestrutura portuária\5240101-Operação dos aeroportos e campos de aterrissagem\5250802-Atividades de despachantes aduaneiros\5250803-Agenciamento de cargas, exceto para o transporte marítimo\5250804-Organização logística do transporte de carga\5250805-Operador de transporte multimodal - OTM\8299799-Outras atividades de serviços prestados principalmente às empresas não especificadas anteriormente | AX11: 10.044.749-0 | AY11: N
A12: 01.115.535/0001-70 | B12: TESC - TERMINAL SANTA CATARINA S/A | D12: GRANDE | E12: 547227865 | F12: 52495102 | G12: 77 | H12: 805 | I12: RISCO MUITO BAIXO | J12: ATIVA | K12: 5231102 | L12: Atividades do Operador Portuário | M12: 3/25/1996 | N12: 0 | O12: ENGENHEIRO LEITE RIBEIRO | P12: 99 | R12: CENTRO | S12: SAO FRANCISCO DO SUL | T12: SC | U12: 89240000 | V12: 47 | W12: 34712112 | X12: Fixo | AH12: CONTABILIDADE@TERMINALSC.COM.BR | AK12: MARIO JOSE NASCIMENTO VALENTIM | AL12: CONSELHEIRO DE ADMINISTRACAO | AM12: 21 | AN12: 999532341 | AO12: LETICIA BRESSAN | AP12: CONSELHEIRO DE ADMINISTRACAO | AQ12: 11 | AR12: 999314149 | AS12: RAPHAEL BLANC COSTA SCHUWARTZ VIEIRA | AT12: CONSELHEIRO DE ADMINISTRACAO | AW12: 5211701-Armazéns gerais - emissão de warrant\5231101-Administração da infraestrutura portuária | AX12: 256080267 | AY12: N
A13: 95.426.862/0001-97 | B13: EXCELSIOR ALIMENTOS SA. | D13: GRANDE | E13: 516360716 | F13: 64161000 | G13: 593 | H13: 822 | I13: RISCO MUITO BAIXO | J13: ATIVA | K13: 1013901 | L13: Fabricação de produtos de carne | M13: 9/5/1966 | N13: 4 | O13: BARAO DO ARROIO GRANDE | P13: 192 | R13: ARROIO GRANDE | S13: SANTA CRUZ DO SUL | T13: RS | U13: 96830504 | V13: 51 | W13: 999307079 | X13: Celular | Y13: 51 | Z13: 997778348 | AA13: Celular | AB13: 51 | AC13: 996468841 | AD13: Celular | AE13: 51 | AF13: 21068800 | AG13: Fixo | AH13: FISCAL@EXCELSIOR.IND.BR | AK13: JOANITA MARIA MAESTRI KAROLESKI | AL13: CONSELHEIRO DE ADMINISTRACAO | AM13: 47 | AN13: 999737388 | AO13: LUIZ CARLOS MOTTA NUNES | AP13: DIRETOR | AQ13: 51 | AR13: 999533758 | AS13: GILBERTO TOMAZONI | AT13: CONSELHEIRO DE ADMINISTRACAO | AU13: 47 | AV13: 991301452 | AW13: 0154700-Criação de suínos\1013902-Preparação de subprodutos do abate\1043100-Fabricação de margarina e outras gorduras vegetais e de óleos não comestíveis de animais\1052000-Fabricação de laticínios\1094500-Fabricação de massas alimentícias\1096100-Fabricação de alimentos e pratos prontos\1099699-Fabricação de outros produtos alimentícios não especificados anteriormente\4631100-Comércio atacadista de leite e laticínios\4634601-Comércio atacadista de carnes bovinas e suínas e derivados\4634602-Comércio atacadista de aves abatidas e derivados\4634699-Comércio atacadista de carnes e derivados de outros animais\4637105-Comércio atacadista de massas alimentícias\4637199-Comércio atacadista especializado em outros produtos alimentícios não especificados anteriormente\4639701-Comércio atacadista de produtos alimentícios em geral\4639702-Comércio atacadista de produtos alimentícios em geral, com atividade de fracionamento e acondicionamento associada\4930201-Transporte rodoviário de carga, exceto produtos perigosos e mudanças, municipal\6821801-Corretagem na compra e venda e avaliação de imóveis\ | AX13: 108/0000191 | AY13: N

Sheet adriana
A1: Carteira de Prospects — Vendedor 2
A2: Total de empresas: 9 | Porte: GRANDE | Fonte: Base de prospecção
A4: CNPJ | B4: Razão Social | C4: Nome Fantasia | D4: Porte | E4: Faturamento Presumido (R$) | F4: Capital Social (R$) | G4: Qtd. Funcionários | H4: Score | I4: Classificação de Risco | J4: Situação Cadastral | K4: CNAE | L4: Atividade Principal | M4: Data Abertura | N4: Qtd. Filiais | O4: Logradouro | P4: Nº | Q4: Complemento | R4: Bairro | S4: Cidade | T4: UF | U4: CEP | V4: DDD 1 | W4: Telefone 1 | X4: Tipo 1 | Y4: DDD 2 | Z4: Telefone 2 | AA4: Tipo 2 | AB4: DDD 3 | AC4: Telefone 3 | AD4: Tipo 3 | AE4: DDD 4 | AF4: Telefone 4 | AG4: Tipo 4 | AH4: E-mail 1 | AI4: E-mail 2 | AJ4: E-mail 3 | AK4: Sócio 1 | AL4: Cargo Sócio 1 | AM4: DDD Sócio 1 | AN4: Tel. Sócio 1 | AO4: Sócio 2 | AP4: Cargo Sócio 2 | AQ4: DDD Sócio 2 | AR4: Tel. Sócio 2 | AS4: Sócio 3 | AT4: Cargo Sócio 3 | AU4: DDD Sócio 3 | AV4: Tel. Sócio 3 | AW4: CNAEs Secundários | AX4: Inscrição Estadual | AY4: Flag DAU
A5: 88.416.482/0001-06 | B5: METASA SA INDUSTRIA METALURGICA | D5: GRANDE | E5: 1480697425 | F5: 142646285 | G5: 728 | H5: 879 | I5: RISCO MUITO BAIXO | J5: ATIVA | K5: 2511000 | L5: Fabricação de estruturas metálicas | M5: 1/13/1976 | N5: 2 | O5: LOC RODOVIA RS | P5: 324 | Q5: KM 82 SN | R5: SEDE | S5: MARAU | T5: RS | U5: 99150000 | V5: 54 | W5: 996343123 | X5: Celular | Y5: 11 | Z5: 976216176 | AA5: Celular | AB5: 54 | AC5: 33427400 | AD5: Fixo | AH5: RAFAEL.SORANCO@METASA.COM.BR | AK5: ANTONIO ROSO | AL5: DIRETOR | AM5: 54 | AN5: 991045075 | AO5: FELIPE FUGA ROSO | AP5: DIRETOR | AQ5: 54 | AR5: 984387994 | AS5: VINICIUS FUGA ROSO | AT5: CONSELHEIRO DE ADMINISTRACAO | AU5: 54 | AV5: 991245792 | AW5: 2449199-Metalurgia de outros metais não ferrosos e suas ligas não especificados anteriormente\2869100-Fabricação de máquinas e equipamentos para uso industrial específico não especificados anteriormente, peças e acessórios\3011301-Construção de embarcações de grande porte\3011302-Construção de embarcações para uso comercial e para usos especiais, exceto de grande porte\3317101-Manutenção e reparação de embarcações e estruturas flutuantes\3321000-Instalação de máquinas e equipamentos industriais\4292802-Obras de montagem industrial\4299599-Outras obras de engenharia civil não especificadas anteriormente\4313400-Obras de terraplenagem\4321500-Instalação e manutenção elétrica\4322301-Instalações hidráulicas, sanitárias e de gás\4618499-Outros representantes comerciais e agentes do comércio especializado em produtos não especificados anteriormente\4685100-Comércio atacadista de produtos siderúrgicos e metalúrgicos, exceto para construção\4789099-Comércio varejista de outros produtos não especificados anteriormente\4930203-Transporte rodoviário de produtos perigosos\5212500-Carga e descarga\5231103-Gestão de terminais aquaviários\7112000-Serviços de engenharia\7119799-Atividades técnicas relacionadas à engenharia e arquitetura não especificadas anteriormente\7732201-Aluguel de máquinas e equipamentos para construção sem operador, exceto andaimes | AX5: 075/0011955 | AY5: N
A6: 02.873.539/0001-80 | B6: SOLSTAD SHIPPING LTDA. | D6: GRANDE | E6: 963560005 | F6: 147884146 | G6: 463 | H6: 717 | I6: RISCO MUITO BAIXO | J6: ATIVA | K6: 5030101 | L6: Navegação de apoio marítimo | M6: 10/16/1998 | N6: 2 | O6: ABILIO MOREIRA DE MIRANDA | P6: 606 | R6: IMBETIBA | S6: MACAE | T6: RJ | U6: 27915250 | V6: 21 | W6: 998303129 | X6: Celular | Y6: 21 | Z6: 999958267 | AA6: Celular | AB6: 21 | AC6: 998390019 | AD6: Celular | AE6: 22 | AF6: 21051900 | AG6: Fixo | AH6: COMMERCIAL.RIO@FARSTAD.COM | AI6: ANDRE.MEDEIROS@FARSTAD.COM | AJ6: PURCHASE.MACAE@FARSTAD.COM | AK6: FELIPE RODRIGUES ALVES MEIRA | AL6: SOCIO ADMINISTRADOR | AM6: 21 | AN6: 980373637 | AO6: CAROLINE DIAS COSTA RODRIGUES | AP6: ADMINISTRADOR | AQ6: 21 | AR6: 982094999 | AS6: SOLSTAD BRASIL HOLDING AS | AT6: SOCIO PESSOA JURIDICA DOMICILIADO NO EXTERIOR | AW6: 0910600-Atividades de apoio à extração de petróleo e gás natural\5030102-Navegação de apoio portuário | AX6: 76.099.960 | AY6: S
A7: 92.721.232/0001-57 | B7: BANRISUL - ARMAZENS GERAIS S/A | D7: GRANDE | E7: 847221694 | F7: 53100000 | G7: 70 | H7: 847 | I7: RISCO MUITO BAIXO | J7: ATIVA | K7: 5211701 | L7: Armazéns gerais - emissão de warrant | M7: 11/12/1953 | N7: 0 | O7: GETULIO VARGAS | P7: 8201 | R7: SAO JOSE | S7: CANOAS | T7: RS | U7: 92420024 | V7: 51 | W7: 997909104 | X7: Celular | Y7: 51 | Z7: 980308494 | AA7: Celular | AB7: 51 | AC7: 997127857 | AD7: Celular | AE7: 51 | AF7: 34257021 | AG7: Fixo | AH7: SECRETARIA@BAGERGS.COM.BR | AK7: CRISTINA BACHETTINI DUARTE | AL7: CONSELHEIRO DE ADMINISTRACAO | AM7: 53 | AN7: 981040002 | AO7: IBANEZ FERREIRA FILTER | AP7: DIRETOR | AQ7: 51 | AR7: 995160033 | AS7: FERNANDO ZINGANO | AT7: CONSELHEIRO DE ADMINISTRACAO | AU7: 51 | AV7: 999993903 | AX7: 024/0165853 | AY7: N
A8: 92.017.110/0001-84 | B8: BERTOL SA IND COM E EXP | D8: GRANDE | E8: 766355199 | F8: 42811631 | G8: 13 | H8: 728 | I8: RISCO MUITO BAIXO | J8: ATIVA | K8: 4930202 | L8: Transporte rodoviário de carga, exceto produtos perigosos e mudanças, intermunicipal, interestadual e internacional | M8: 5/4/1944 | N8: 1 | O8: FAGUNDES DOS REIS | P8: 428 | Q8: SALA 502 | R8: CENTRO | S8: PASSO FUNDO | T8: RS | U8: 99010070 | V8: 51 | W8: 980535885 | X8: Celular | Y8: 51 | Z8: 995701980 | AA8: Celular | AB8: 51 | AC8: 997975986 | AD8: Celular | AE8: 54 | AF8: 21031722 | AG8: Fixo | AH8: CONTABILIDADE@BERTOL.COM.BR | AI8: DOMINGOS@BERTOL.COM.BR | AK8: LIANE BERTOL | AL8: CONSELHEIRO DE ADMINISTRACAO | AM8: 54 | AN8: 999827743 | AO8: IVO BERTOL | AP8: PRESIDENTE | AQ8: 54 | AR8: 999988321 | AS8: IVO BERTOL JUNIOR | AT8: CONSELHEIRO DE ADMINISTRACAO | AU8: 54 | AV8: 999350333 | AW8: 0115600-Cultivo de soja\0210101-Cultivo de eucalipto\4622200-Comércio atacadista de soja\ | AX8: 091/1045716 | AY8: N
A9: 85.041.333/0001-11 | B9: PORTO PONTA DO FELIX S/A | D9: GRANDE | E9: 670021325 | F9: 140012637 | G9: 312 | H9: 741 | I9: RISCO MUITO BAIXO | J9: ATIVA | K9: 5231102 | L9: Atividades do Operador Portuário | M9: 5/15/1992 | N9: 2 | O9: ENGENHEIRO LUIZ AUGUSTO LEAO FONSECA | P9: 1520 | R9: ITAPEMA DE BAIXO | S9: ANTONINA | T9: PR | U9: 83370000 | V9: 41 | W9: 40404474 | X9: Fixo | AH9: RONALDO.CORREA@TPPF.COM.BR | AI9: TPPF@TPPF.COM.BR | AJ9: PONTADOFELIX@PONTADOFELIX.COM.BR | AK9: NIKITA GUSKOV | AL9: CONSELHEIRO DE ADMINISTRACAO | AO9: MARCO ANTONIO GHIDINI | AP9: PRESIDENTE | AQ9: 41 | AR9: 999995465 | AS9: LUIZ ALBERTO BONI | AT9: CONSELHEIRO DE ADMINISTRACAO | AU9: 47 | AV9: 996256688 | AW9: 4291000-Obras portuárias, marítimas e fluviais\5030101-Navegação de apoio marítimo\5030102-Navegação de apoio portuário\5211799-Depósitos de mercadorias para terceiros, exceto armazéns gerais e guarda-móveis\5212500-Carga e descarga\5231101-Administração da infraestrutura portuária\6462000-Holdings de instituições não financeiras\7119702-Atividades de estudos geológicos\8292000-Envasamento e empacotamento sob contrato\ | AX9: 90170765-04 | AY9: N
A10: 89.423.040/0001-50 | B10: CERCENA S/A - INDUSTRIA METALURGICA | D10: GRANDE | E10: 611877120 | F10: 12000000 | G10: 338 | H10: 908 | I10: RISCO MUITO BAIXO | J10: ATIVA | K10: 2451200 | L10: Fundição de ferro e aço | M10: 5/15/1972 | N10: 0 | O10: SALOMAO IOSCHPE | P10: 361 | Q10: CX P 101 | R10: INDUSTRIAL | S10: ERECHIM | T10: RS | U10: 99706399 | V10: 54 | W10: 21071300 | X10: Fixo | Y10: 54 | Z10: 991334199 | AA10: Celular | AB10: 54 | AC10: 991364048 | AD10: Celular | AE10: 54 | AF10: 991351415 | AG10: Celular | AH10: CONTROLADORIA@CERCENA.COM.BR | AI10: RODRIGO.RAFAEL@CERCENA.COM.BR | AJ10: FERNANDO@CERCENA.COM.BR | AK10: JUAREZ JOSE CERCENA | AL10: PRESIDENTE | AM10: 54 | AN10: 999822829 | AO10: MARGARETE IGNEZ CERCENA | AP10: DIRETOR | AQ10: 54 | AR10: 984444079 | AS10: RENATA ZANARDO CERCENA | AT10: DIRETOR | AU10: 54 | AV10: 992439993 | AW10: 2539001-Serviços de usinagem, torneiria e solda\2941700-Fabricação de peças e acessórios para o sistema motor de veículos automotores\2942500-Fabricação de peças e acessórios para os sistemas de marcha e transmissão de veículos automotores\2943300-Fabricação de peças e acessórios para o sistema de freios de veículos automotores\2944100-Fabricação de peças e acessórios para o sistema de direção e suspensão de veículos automotores\2949299-Fabricação de outras peças e acessórios para veículos automotores não especificadas anteriormente\3314713-Manutenção e reparação de máquinas-ferramenta\4614100-Representantes comerciais e agentes do comércio de máquinas, equipamentos, embarcações e aeronaves\4619200-Representantes comerciais e agentes do comércio de mercadorias em geral não especializado\4685100-Comércio atacadista de produtos siderúrgicos e metalúrgicos, exceto para construção\7120100-Testes e análises técnicas\7210000-Pesquisa e desenvolvimento experimental em ciências físicas e naturais | AX10: 039/0001260 | AY10: N
A11: 04.244.527/0001-12 | B11: TERMINAL XXXIX DE SANTOS S.A | D11: GRANDE | E11: 564742678 | F11: 100000000 | G11: 324 | H11: 862 | I11: RISCO MUITO BAIXO | J11: ATIVA | K11: 5231102 | L11: Atividades do Operador Portuário | M11: 1/9/2001 | N11: 0 | O11: GOVERNADOR MARIO COVAS JUNIOR | Q11: ARMZXXXIX | R11: ESTUARIO | S11: SANTOS | T11: SP | U11: 11020300 | V11: 13 | W11: 974160015 | X11: Celular | Y11: 13 | Z11: 974173035 | AA11: Celular | AB11: 13 | AC11: 974040729 | AD11: Celular | AE11: 13 | AF11: 32785007 | AG11: Fixo | AH11: TERMINAL39@TERMINAL39.COM.BR | AK11: JOAO MARCELO ALVES DA SILVA | AL11: DIRETOR | AM11: 21 | AN11: 996373939 | AO11: CRISTIANO GONCALVES FARIA | AP11: DIRETOR | AQ11: 64 | AR11: 992039517 | AW11: 5211799-Depósitos de mercadorias para terceiros, exceto armazéns gerais e guarda-móveis\5231101-Administração da infraestrutura portuária | AX11: 633.566.880.117 | AY11: N
A12: 43.244.631/0001-69 | B12: TRANSPORTADORA AMERICANA S.A. | C12: T.A. | D12: GRANDE | E12: 541430250 | F12: 465143877 | G12: 72 | H12: 675 | I12: RISCO BAIXO | J12: ATIVA | K12: 4930202 | L12: Transporte rodoviário de carga, exceto produtos perigosos e mudanças, intermunicipal, interestadual e internacional | M12: 7/29/1966 | N12: 14 | O12: RIO NEGRO | P12: 500 | Q12: ANDAR 6 TORRE 1 SALA 603 | R12: ALPHAVILLE CENTRO INDUSTRIAL E EMPRESARIAL/ALPHAVILLE. | S12: BARUERI | T12: SP | U12: 06454000 | V12: 19 | W12: 991953958 | X12: Celular | Y12: 19 | Z12: 991953931 | AA12: Celular | AB12: 11 | AC12: 43918824 | AD12: Fixo | AH12: FISCAL@MOVE3.COM.BR | AI12: CONTATO@TANET.COM.BR | AJ12: ORIDES.SANTOS@TANET.COM.BR | AK12: LEOPOLDO DE BRUGGEN E SILVA | AL12: DIRETOR | AM12: 19 | AN12: 999762227 | AO12: DIEGO OLIVEIRA DA RESSURREICAO | AP12: DIRETOR | AQ12: 11 | AR12: 933142424 | AW12: 4511102-Comércio a varejo de automóveis, camionetas e utilitários usados\4511104-Comércio por atacado de caminhões novos e usados\4930201-Transporte rodoviário de carga, exceto produtos perigosos e mudanças, municipal\4930203-Transporte rodoviário de produtos perigosos\5212500-Carga e descarga\5232000-Atividades de agenciamento marítimo\5250803-Agenciamento de cargas, exceto para o transporte marítimo\8599604-Treinamento em desenvolvimento profissional e gerencial | AX12: 165.003.886.115 | AY12: S
A13: 65.790.610/0001-81 | B13: ABATEDOURO DE AVES CALIFORNIA LTDA | C13: GONZALEZ | D13: GRANDE | E13: 507274070 | F13: 79874298 | G13: 576 | H13: 209 | I13: RISCO ALTO | J13: ATIVA | K13: 1012101 | L13: Abate de aves | M13: 4/17/1991 | N13: 4 | O13: LOC E VICINAL RICIERI COLA | Q13: KM 1 LOC E VICINAL RICIERI COL | R13: ZONA RURAL | S13: PIRANGI | T13: SP | U13: 15820000 | V13: 17 | W13: 996240121 | X13: Celular | Y13: 17 | Z13: 996232749 | AA13: Celular | AB13: 17 | AC13: 997041370 | AD13: Celular | AE13: 17 | AF13: 33869800 | AG13: Fixo | AH13: CONTABIL@FRANGOGONZALEZ.COM.BR | AI13: COMPRAS@FRANGOGONZALEZ.COM.BR | AJ13: FRANGOGONZALEZ@FRANGOGONZALEZ.COM.BR | AK13: VGN PARTICIPACOES LTDA | AL13: SOCIO | AM13: 17 | AN13: 33869800 | AO13: TRES IRMAS PARTICIPACOES LTDA | AP13: SOCIO | AQ13: 11 | AR13: 55097151 | AS13: GONZALEZ ADMINISTRACAO E PARTICIPACOES LTDA | AT13: SOCIO | AU13: 17 | AV13: 33869800 | AW13: 0139306-Cultivo de seringueira\0155501-Criação de frangos para corte\0155502-Produção de pintos de um dia\0155503-Criação de outros galináceos, exceto para corte\0155505-Produção de ovos\1013901-Fabricação de produtos de carne\1013902-Preparação de subprodutos do abate\1066000-Fabricação de alimentos para animais\1099604-Fabricação de gelo comum\4634603-Comércio atacadista de pescados e frutos do mar\4637199-Comércio atacadista especializado em outros produtos alimentícios não especificados anteriormente\4722901-Comércio varejista de carnes - açougues\4930202-Transporte rodoviário de carga, exceto produtos perigosos e mudanças, intermunicipal, interestadual e internacional\ | AX13: 539.005.639.117 | AY13: N

Sheet gislaine
A1: Carteira de Prospects — Vendedor 3
A2: Total de empresas: 9 | Porte: GRANDE | Fonte: Base de prospecção
A4: CNPJ | B4: Razão Social | C4: Nome Fantasia | D4: Porte | E4: Faturamento Presumido (R$) | F4: Capital Social (R$) | G4: Qtd. Funcionários | H4: Score | I4: Classificação de Risco | J4: Situação Cadastral | K4: CNAE | L4: Atividade Principal | M4: Data Abertura | N4: Qtd. Filiais | O4: Logradouro | P4: Nº | Q4: Complemento | R4: Bairro | S4: Cidade | T4: UF | U4: CEP | V4: DDD 1 | W4: Telefone 1 | X4: Tipo 1 | Y4: DDD 2 | Z4: Telefone 2 | AA4: Tipo 2 | AB4: DDD 3 | AC4: Telefone 3 | AD4: Tipo 3 | AE4: DDD 4 | AF4: Telefone 4 | AG4: Tipo 4 | AH4: E-mail 1 | AI4: E-mail 2 | AJ4: E-mail 3 | AK4: Sócio 1 | AL4: Cargo Sócio 1 | AM4: DDD Sócio 1 | AN4: Tel. Sócio 1 | AO4: Sócio 2 | AP4: Cargo Sócio 2 | AQ4: DDD Sócio 2 | AR4: Tel. Sócio 2 | AS4: Sócio 3 | AT4: Cargo Sócio 3 | AU4: DDD Sócio 3 | AV4: Tel. Sócio 3 | AW4: CNAEs Secundários | AX4: Inscrição Estadual | AY4: Flag DAU
A5: 83.188.110/0001-56 | B5: FRICASA ALIMENTOS S/A | C5: FRICASA | D5: GRANDE | E5: 1126541549 | F5: 123638427 | G5: 674 | H5: 822 | I5: RISCO MUITO BAIXO | J5: ATIVA | K5: 1013901 | L5: Fabricação de produtos de carne | M5: 8/26/1966 | N5: 3 | O5: SENADOR IVO D AQUINO | P5: 1330 | R5: INDUSTRIAL 1 | S5: CANOINHAS | T5: SC | U5: 89462488 | V5: 47 | W5: 999780975 | X5: Celular | Y5: 31 | Z5: 33483552 | AA5: Fixo | AB5: 47 | AC5: 999781382 | AD5: Celular | AE5: 47 | AF5: 999781268 | AG5: Celular | AH5: FISCAL@FRICASA.COM.BR | AI5: ALEXFERNANDES@FRICASA.COM.BR | AJ5: ANASCHETTINI@FRICASA.COM.BR | AK5: LUIZ CARLOS MENDES COSTA | AL5: PRESIDENTE | AM5: 31 | AN5: 975129723 | AO5: LUCIANO SALLES | AP5: DIRETOR | AQ5: 28 | AR5: 999113320 | AS5: ANTONIO DOS SANTOS COSTA FILHO | AT5: DIRETOR | AU5: 27 | AV5: 998870227 | AW5: 0151201-Criação de bovinos para corte\0151202-Criação de bovinos para leite\0153902-Criação de ovinos, inclusive para produção de lã\0154700-Criação de suínos\0155501-Criação de frangos para corte\0155502-Produção de pintos de um dia\0155503-Criação de outros galináceos, exceto para corte\0155504-Criação de aves, exceto galináceos\0155505-Produção de ovos\1011201-Frigorífico - abate de bovinos\1011203-Frigorífico - abate de ovinos e caprinos\1012101-Abate de aves\1012103-Frigorífico - abate de suínos\1013902-Preparação de subprodutos do abate\1066000-Fabricação de alimentos para animais\1510600-Curtimento e outras preparações de couro\4631100-Comércio atacadista de leite e laticínios\4634601-Comércio atacadista de carnes bovinas e suínas e derivados\4634602-Comércio atacadista de aves abatidas e derivados\4634603-Comércio atacadista de pescados e frutos do mar\4634699-Comércio atacadista de carnes e derivados de outros animais\4635402-Comércio atacadista de cerveja, chope e refrigerante\4635499-Comércio atacadista de bebidas não especificadas anteriormente\4637105-Comércio atacadista de massas alimentícias\4637199-Comércio atacadista especializado em outros produtos alimentícios não especificados anteriormente\4639702-Comércio atacadista de produtos alimentícios em geral, com atividade de fracionamento e acondicionamento associada\4689399-Comércio atacadista especializado em outros produtos intermediários não especificados anteriormente\4691500-Comércio atacadista de mercadorias em geral, com predominância de produtos alimentícios\4721103-Comércio varejista de laticínios e frios\4722901-Comércio varejista de carnes - açougues\4729699-Comércio varejista de produtos alimentícios em geral ou especializado em produtos alimentícios não especificados anteriormente\4771704-Comércio varejista de medicamentos veterinários\4789004-Comércio varejista de animais vivos e de artigos e alimentos para animais de estimação\6462000-Holdings de instituições não financeiras | AX5: 250006545 | AY5: N
A6: 02.725.300/0001-63 | B6: PASA - PARANA OPERACOES PORTUARIAS S/A | C6: PASA | D6: GRANDE | E6: 940057392 | F6: 181981670 | G6: 316 | H6: 797 | I6: RISCO MUITO BAIXO | J6: ATIVA | K6: 5211701 | L6: Armazéns gerais - emissão de warrant | M6: 8/4/1998 | N6: 4 | O6: BENTO ROCHA | P6: 67 | Q6: ARMZ PASA | R6: DOM PEDRO II | S6: PARANAGUA | T6: PR | U6: 83221565 | V6: 41 | W6: 999845842 | X6: Celular | Y6: 41 | Z6: 984285303 | AA6: Celular | AB6: 41 | AC6: 984285777 | AD6: Celular | AE6: 41 | AF6: 34205700 | AG6: Fixo | AH6: PASAPARANAGUA@PASAPARANAGUA.COM.BR | AI6: OSVALDO.SILVA@PASAPARANAGUA.COM.BR | AK6: PAULO MENEGUETTI | AL6: PRESIDENTE | AM6: 44 | AN6: 999821982 | AO6: PERSIO SOUZA DE ASSIS | AP6: DIRETOR | AQ6: 41 | AR6: 999118382 | AS6: SIDNEY SAMUEL MENEGUETTI | AT6: DIRETOR | AU6: 44 | AV6: 991460647 | AW6: 5222200-Terminais rodoviários e ferroviários\5223100-Estacionamento de veículos\5231101-Administração da infraestrutura portuária\5231102-Atividades do Operador Portuário\5250802-Atividades de despachantes aduaneiros\8299799-Outras atividades de serviços prestados principalmente às empresas não especificadas anteriormente | AX6: 90232683-93 | AY6: N
A7: 60.713.823/0001-96 | B7: SWIFT ARMOUR S A INDUSTRIA E COMERCIO | D7: GRANDE | E7: 829129596 | F7: 122400000 | G7: 2 | H7: 895 | I7: RISCO MUITO BAIXO | J7: ATIVA | K7: 1013901 | L7: Fabricação de produtos de carne | M7: 8/31/1966 | N7: 2 | O7: BRIGADEIRO FARIA LIMA, 2391 | P7: 2391 | Q7: ANDAR 12 CONJ 121 SALA 09 | R7: JARDIM PAULISTANO | S7: SAO PAULO | T7: SP | U7: 1452905 | V7: 11 | W7: 30343008 | X7: Fixo | AH7: SWIFT.SASAIC@GMAIL.COM | AI7: SWIFTBORDON@GLOBO.COM | AK7: FLORISVALDO CAETANO DE OLIVEIRA | AL7: PRESIDENTE | AM7: 11 | AN7: 994571681 | AX7: 100.158.750.114 | AY7: N
A8: 04.784.802/0001-90 | B8: COMPANHIA OPERADORA PORTUARIA DO ITAQUI | C8: COPI | D8: GRANDE | E8: 750561604 | F8: 167742344 | G8: 257 | H8: 883 | I8: RISCO MUITO BAIXO | J8: ATIVA | K8: 5231102 | L8: Atividades do Operador Portuário | M8: 10/31/2001 | N8: 3 | O8: DO ITAQUI | Q8: BAIA DE SAO MARCOS | R8: ITAQUI | S8: SAO LUIS | T8: MA | U8: 65085370 | V8: 98 | W8: 984059839 | X8: Celular | Y8: 98 | Z8: 981144834 | AA8: Celular | AB8: 98 | AC8: 32616539 | AD8: Fixo | AH8: FINANCEIRO@COPI-PORTODOITAQUI.COM.BR | AK8: PEDRO ALCEU FELDMANN | AL8: CONSELHEIRO DE ADMINISTRACAO | AM8: 65 | AN8: 998012007 | AO8: VALMOR FELIPETTO | AP8: CONSELHEIRO DE ADMINISTRACAO | AQ8: 41 | AR8: 991096280 | AS8: DARLAN FABIO DE DAVID | AT8: PRESIDENTE | AU8: 48 | AV8: 988262773 | AW8: 5211701-Armazéns gerais - emissão de warrant\5231101-Administração da infraestrutura portuária\6463800-Outras sociedades de participação, exceto holdings\7739099-Aluguel de outras máquinas e equipamentos comerciais e industriais não especificados anteriormente, sem operador | AX8: 12.539316-4 | AY8: N
A9: 75.294.801/0001-06 | B9: MARTINI MEAT S/A ARMAZENS GERAIS | C9: EMERGENT COLD LATAM | D9: GRANDE | E9: 668149961 | F9: 1122449574 | G9: 229 | H9: 618 | I9: RISCO BAIXO | J9: ATIVA | K9: 5211701 | L9: Armazéns gerais - emissão de warrant | M9: 7/14/1970 | N9: 15 | O9: BR-277 | P9: 5709 | R9: COLONIA SANTA RITA | S9: PARANAGUA | T9: PR | U9: 83209715 | V9: 42 | W9: 998540039 | X9: Celular | Y9: 41 | Z9: 34202000 | AA9: Fixo | AH9: FISCAL@EMERGENTCOLD.COM | AI9: FISCAL@MARTINIMEAT.COM.BR | AJ9: COMPRAS@MARTINIMEAT.COM.BR | AK9: EVANDRO CALANCA DA SILVA | AL9: DIRETOR | AM9: 11 | AN9: 945585809 | AO9: DAVID ALAN PALFENIER | AP9: PRESIDENTE | AQ9: 11 | AR9: 982791817 | AS9: RICARDO LUIZ AGUIAR JACOB | AT9: DIRETOR | AU9: 11 | AV9: 991299240 | AW9: 4930201-Transporte rodoviário de carga, exceto produtos perigosos e mudanças, municipal\4930202-Transporte rodoviário de carga, exceto produtos perigosos e mudanças, intermunicipal, interestadual e internacional\5212500-Carga e descarga\5231102-Atividades do Operador Portuário\5232000-Atividades de agenciamento marítimo\5250801-Comissaria de despachos\5250802-Atividades de despachantes aduaneiros\5250803-Agenciamento de cargas, exceto para o transporte marítimo\5250804-Organização logística do transporte de carga\5250805-Operador de transporte multimodal - OTM | AX9: 11802869-49 | AY9: N
A10: 07.032.076/0001-48 | B10: FUNDIMISA - FUNDICAO E USINAGEM LTDA. | D10: GRANDE | E10: 601943935 | F10: 151300000 | G10: 932 | H10: 998 | I10: RISCO MUITO BAIXO | J10: ATIVA | K10: 2451200 | L10: Fundição de ferro e aço | M10: 10/6/2004 | N10: 0 | O10: GIRUA | P10: 50 | R10: ALIANCA | S10: SANTO ANGELO | T10: RS | U10: 98805540 | V10: 55 | W10: 33139000 | X10: Fixo | AH10: LEONARDO@FUNDIMISA.COM.BR | AI10: ANDRE@FUNDIMISA.COM.BR | AJ10: BETHINA@FUNDIMISA.COM.BR | AK10: PAULO ROBERTO VELLINHO ELY | AL10: SOCIO-ADMINISTRADOR | AM10: 55 | AN10: 999823029 | AO10: JAQUELINE MARIA MULLER ELY | AP10: SOCIO-ADMINISTRADOR | AQ10: 55 | AR10: 999400878 | AW10: 2424502-Produção de relaminados, trefilados e perfilados de aço, exceto arames\2539001-Serviços de usinagem, torneiria e solda\2539002-Serviços de tratamento e revestimento em metais\2593400-Fabricação de artigos de metal para uso doméstico e pessoal\2599301-Serviços de confecção de armações metálicas para a construção\2599302-Serviço de corte e dobra de metais\2599399-Fabricação de outros produtos de metal não especificados anteriormente\2833000-Fabricação de máquinas e equipamentos para a agricultura e pecuária, peças e acessórios, exceto para irrigação\2941700-Fabricação de peças e acessórios para o sistema motor de veículos automotores\2942500-Fabricação de peças e acessórios para os sistemas de marcha e transmissão de veículos automotores\2943300-Fabricação de peças e acessórios para o sistema de freios de veículos automotores\2944100-Fabricação de peças e acessórios para o sistema de direção e suspensão de veículos automotores\4663000-Comércio atacadista de máquinas e equipamentos para uso industrial, partes e peças\4687703-Comércio atacadista de resíduos e sucatas metálicos\4759899-Comércio varejista de outros artigos de uso doméstico não especificados anteriormente\ | AX10: 113/0136342 | AY10: N
A11: 05.527.694/0001-33 | B11: TERMINAL DE GRANEIS DO GUARUJA S.A. | D11: GRANDE | E11: 561021272 | F11: 79747000 | G11: 328 | H11: 773 | I11: RISCO MUITO BAIXO | J11: ATIVA | K11: 5231102 | L11: Atividades do Operador Portuário | M11: 2/7/2003 | N11: 0 | O11: SANTOS DUMONT | Q11: TEFER1 TECON3 | R11: JARDIM CONCEICAOZINHA (VICENTE DE CARVALHO) | S11: GUARUJA | T11: SP | U11: 11460006 | V11: 13 | W11: 997528103 | X11: Celular | Y11: 13 | Z11: 974030183 | AA11: Celular | AB11: 13 | AC11: 974076576 | AD11: Celular | AE11: 13 | AF11: 21048800 | AG11: Fixo | AH11: CONTABIL@TGG.COM.BR | AK11: GILDECIO JOSE MOREIRA FIEL | AL11: DIRETOR | AM11: 11 | AN11: 981766291 | AO11: CLAUDINEI FRANCISCO ZENATTI | AP11: DIRETOR | AQ11: 21 | AR11: 995202670 | AS11: FLORENT ALAIN HENRI DUPUI | AT11: DIRETOR | AX11: 335.195.176.119 | AY11: N
A12: 10.341.742/0001-34 | B12: POLY TERMINAIS PORTUARIOS SA | C12: POLY TERMINAIS | D12: GRANDE | E12: 540712262 | F12: 80000000 | G12: 129 | H12: 883 | I12: RISCO MUITO BAIXO | J12: ATIVA | K12: 5231102 | L12: Atividades do Operador Portuário | M12: 9/16/2008 | N12: 1 | O12: JOSE LUIZ MARCELINO | P12: 1400 | R12: MURTA | S12: ITAJAI | T12: SC | U12: 88311370 | V12: 47 | W12: 991517895 | X12: Celular | Y12: 47 | Z12: 992494637 | AA12: Celular | AB12: 47 | AC12: 991404549 | AD12: Celular | AE12: 47 | AF12: 21045788 | AG12: Fixo | AH12: COMPRAS@POLYTERMINAIS.COM.BR | AK12: ADALBERTO SEDLACEK | AL12: PRESIDENTE | AM12: 47 | AN12: 999797008 | AO12: EDISON MALLMANN | AP12: DIRETOR | AQ12: 51 | AR12: 996872300 | AS12: JULIO CESAR BOTICELLI | AT12: DIRETOR | AU12: 51 | AV12: 980579075 | AW12: 4930203-Transporte rodoviário de produtos perigosos\5211701-Armazéns gerais - emissão de warrant\5211799-Depósitos de mercadorias para terceiros, exceto armazéns gerais e guarda-móveis\5212500-Carga e descarga\5250804-Organização logística do transporte de carga\5250805-Operador de transporte multimodal - OTM | AX12: 255697546 | AY12: N
A13: 38.711.826/0001-31 | B13: LINCON INDUSTRIA E COMERCIO LTDA | D13: GRANDE | E13: 500058638 | F13: 39090000 | G13: 270 | H13: 416 | I13: RISCO MÉDIO | J13: ATIVA | K13: 1013901 | L13: Fabricação de produtos de carne | M13: 7/27/1990 | N13: 4 | O13: JOSE MARIA DE LACERDA | P13: 2058 | Q13: B | R13: CIDADE INDUSTRIAL | S13: CONTAGEM | T13: MG | U13: 32210120 | V13: 31 | W13: 33680001 | X13: Fixo | AH13: SAC@TROPEIRA.COM.BR | AI13: AGAMENON.MAGALHAES@TROPEIRA.COM.BR | AJ13: ALEXIA.NEVES@TROPEIRA.COM.BR | AK13: ANTONIO BRAGA DOS SANTOS | AL13: SOCIO | AM13: 31 | AN13: 984508811 | AO13: MARTON PARTICIPACOES S/A | AP13: SOCIO | AW13: 1013902-Preparação de subprodutos do abate\4634601-Comércio atacadista de carnes bovinas e suínas e derivados\4634602-Comércio atacadista de aves abatidas e derivados\4634603-Comércio atacadista de pescados e frutos do mar\4637199-Comércio atacadista especializado em outros produtos alimentícios não especificados anteriormente\4639701-Comércio atacadista de produtos alimentícios em geral\4721103-Comércio varejista de laticínios e frios\4722901-Comércio varejista de carnes - açougues\4722902-Peixaria\4729699-Comércio varejista de produtos alimentícios em geral ou especializado em produtos alimentícios não especificados anteriormente | AX13: 186657198.00-48 | AY13: N

Sheet eduardo
A1: Carteira de Prospects — Vendedor 4
A2: Total de empresas: 8 | Porte: GRANDE | Fonte: Base de prospecção
A4: CNPJ | B4: Razão Social | C4: Nome Fantasia | D4: Porte | E4: Faturamento Presumido (R$) | F4: Capital Social (R$) | G4: Qtd. Funcionários | H4: Score | I4: Classificação de Risco | J4: Situação Cadastral | K4: CNAE | L4: Atividade Principal | M4: Data Abertura | N4: Qtd. Filiais | O4: Logradouro | P4: Nº | Q4: Complemento | R4: Bairro | S4: Cidade | T4: UF | U4: CEP | V4: DDD 1 | W4: Telefone 1 | X4: Tipo 1 | Y4: DDD 2 | Z4: Telefone 2 | AA4: Tipo 2 | AB4: DDD 3 | AC4: Telefone 3 | AD4: Tipo 3 | AE4: DDD 4 | AF4: Telefone 4 | AG4: Tipo 4 | AH4: E-mail 1 | AI4: E-mail 2 | AJ4: E-mail 3 | AK4: Sócio 1 | AL4: Cargo Sócio 1 | AM4: DDD Sócio 1 | AN4: Tel. Sócio 1 | AO4: Sócio 2 | AP4: Cargo Sócio 2 | AQ4: DDD Sócio 2 | AR4: Tel. Sócio 2 | AS4: Sócio 3 | AT4: Cargo Sócio 3 | AU4: DDD Sócio 3 | AV4: Tel. Sócio 3 | AW4: CNAEs Secundários | AX4: Inscrição Estadual | AY4: Flag DAU
A5: 34.040.345/0001-90 | B5: COMPANHIA DOCAS DO RIO GRANDE DO NORTE - CODERN | D5: GRANDE | E5: 1084889606 | F5: 432842995 | G5: 131 | H5: 827 | I5: RISCO MUITO BAIXO | J5: ATIVA | K5: 5231102 | L5: Atividades do Operador Portuário | M5: 3/16/1970 | N5: 5 | O5: ENGENHEIRO HILDEBRANDO DE GOIS | P5: 220 | R5: RIBEIRA | S5: NATAL | T5: RN | U5: 59010700 | V5: 84 | W5: 999910660 | X5: Celular | Y5: 84 | Z5: 999910634 | AA5: Celular | AB5: 84 | AC5: 981650770 | AD5: Celular | AE5: 84 | AF5: 32023200 | AG5: Fixo | AH5: FINANCEIRO@CODERN.COM.BR | AI5: ALLIKA.LIRA@CODERN.COM.BR | AJ5: BOSCO.MACEDO@CODERN.COM.BR | AW5: 5231101-Administração da infraestrutura portuária\ | AX5: 20.061.797-4 | AY5: N
A6: 17.500.224/0001-65 | B6: USIMINAS MECANICA SA | D6: GRANDE | E6: 901412077 | F6: 132700000 | G6: 1 | H6: 781 | I6: RISCO MUITO BAIXO | J6: ATIVA | K6: 2511000 | L6: Fabricação de estruturas metálicas | M6: 12/13/1971 | N6: 12 | O6: DO CONTORNO | P6: 6594 | Q6: SALA 801 C | R6: LOURDES | S6: BELO HORIZONTE | T6: MG | U6: 30110044 | V6: 31 | W6: 34999019 | X6: Fixo | AK6: FERNANDO MAZZONI PENA | AL6: DIRETOR | AM6: 31 | AN6: 999883228 | AO6: ADRIANE VIEIRA OLIVEIRA ALBUQUERQUE | AP6: DIRETOR | AQ6: 31 | AR6: 984546799 | AW6: 2513600-Fabricação de obras de caldeiraria pesada\2599399-Fabricação de outros produtos de metal não especificados anteriormente\2949299-Fabricação de outras peças e acessórios para veículos automotores não especificadas anteriormente\3011301-Construção de embarcações de grande porte\3317101-Manutenção e reparação de embarcações e estruturas flutuantes\3321000-Instalação de máquinas e equipamentos industriais\4291000-Obras portuárias, marítimas e fluviais\4292801-Montagem de estruturas metálicas\4292802-Obras de montagem industrial\4789099-Comércio varejista de outros produtos não especificados anteriormente\7119799-Atividades técnicas relacionadas à engenharia e arquitetura não especificadas anteriormente\8630502-Atividade médica ambulatorial com recursos para realização de exames complementares\8630504-Atividade odontológica\8630506-Serviços de vacinação e imunização humana\8640202-Laboratórios clínicos\8650001-Atividades de enfermagem\8650002-Atividades de profissionais da nutrição\8650003-Atividades de psicologia e psicanálise\8650004-Atividades de fisioterapia\8650006-Atividades de fonoaudiologia\8650099-Atividades de profissionais da área de saúde não especificadas anteriormente\ | AX6: 062025169.00-90 | AY6: N
A7: 58.180.316/0001-92 | B7: SANTOS BRASIL LOGISTICA S.A. | D7: GRANDE | E7: 781418720 | F7: 133955365 | G7: 234 | H7: 963 | I7: RISCO MUITO BAIXO | J7: ATIVA | K7: 4930202 | L7: Transporte rodoviário de carga, exceto produtos perigosos e mudanças, intermunicipal, interestadual e internacional | M7: 10/17/1966 | N7: 7 | O7: ANCHIETA | P7: 820 | R7: ALEMOA | S7: SANTOS | T7: SP | U7: 11095000 | V7: 11 | W7: 32793279 | X7: Fixo | AH7: PRISCILA.FARES@SANTOSBRASILLOG.COM.BR | AI7: COMPRAS@SANTOSBRASIL.COM.BR | AJ7: ADRIANA.AUGUSTO@SANTOSBRASIL.COM.BR | AK7: RICARDO DOS SANTOS BUTERI | AL7: DIRETOR | AM7: 11 | AN7: 990031551 | AO7: ANTONIO CARLOS DUARTE SEPULVEDA | AP7: PRESIDENTE | AQ7: 13 | AR7: 997302878 | AS7: DANIEL PEDREIRA DOREA | AT7: DIRETOR | AU7: 11 | AV7: 997430956 | AW7: 4930203-Transporte rodoviário de produtos perigosos\4930204-Transporte rodoviário de mudanças\5212500-Carga e descarga\5250801-Comissaria de despachos\5250803-Agenciamento de cargas, exceto para o transporte marítimo\5250804-Organização logística do transporte de carga\5250805-Operador de transporte multimodal - OTM\ | AX7: 633.064.086.111 | AY7: N
A8: 52.045.697/0001-10 | B8: SASAZAKI INDUSTRIA E COMERCIO S.A. | D8: GRANDE | E8: 735745332 | F8: 58673120 | G8: 190 | H8: 532 | I8: RISCO BAIXO | J8: ATIVA | K8: 2512800 | L8: Fabricação de esquadrias de metal | M8: 8/3/1966 | N8: 0 | O8: EUGENIO CONEGLIAN 1060 | P8: 1060 | R8: DISTRITO INDUSTRIAL | S8: MARILIA | T8: SP | U8: 17512900 | V8: 11 | W8: 959090534 | X8: Celular | Y8: 14 | Z8: 996780894 | AA8: Celular | AB8: 14 | AC8: 996779164 | AD8: Celular | AE8: 14 | AF8: 34029922 | AG8: Fixo | AH8: GREICE@SASAZAKI.COM.BR | AI8: BARBARA@SASAZAKI.COM.BR | AJ8: ALEX.SANTIAGO@SASAZAKI.COM.BR | AK8: LEONARDO KOZO SASAZAKI | AL8: SOCIO ADMINISTRADOR | AM8: 14 | AN8: 997845050 | AO8: GERALDO GONCALVES | AP8: PRESIDENTE | AQ8: 15 | AR8: 997442852 | AW8: 2599302-Serviço de corte e dobra de metais\4330402-Instalação de portas, janelas, tetos, divisórias e armários embutidos de qualquer material\4399199-Serviços especializados para construção não especificados anteriormente\4612500-Representantes comerciais e agentes do comércio de combustíveis, minerais, produtos siderúrgicos e químicos\4679604-Comércio atacadista especializado de materiais de construção não especificados anteriormente\4744005-Comércio varejista de materiais de construção não especificados anteriormente\4930202-Transporte rodoviário de carga, exceto produtos perigosos e mudanças, intermunicipal, interestadual e internacional\ | AX8: 438.010.070.113 | AY8: S
A9: 06.989.608/0001-77 | B9: BARRA DO RIO TERMINAL PORTUARIO S.A | C9: BARRA DO RIO TERMINAL PORTUARIO S.A | D9: GRANDE | E9: 666661395 | F9: 138869000 | G9: 83 | H9: 618 | I9: RISCO BAIXO | J9: ATIVA | K9: 5231102 | L9: Atividades do Operador Portuário | M9: 8/20/2004 | N9: 0 | O9: ARNOLDO LOPES GONZAGA | P9: 507 | R9: BARRA DO RIO | S9: ITAJAI | T9: SC | U9: 88305570 | V9: 47 | W9: 991142493 | X9: Celular | Y9: 47 | Z9: 992894531 | AA9: Celular | AB9: 47 | AC9: 992939737 | AD9: Celular | AE9: 47 | AF9: 33411051 | AG9: Fixo | AH9: JZUNINO@ESTINAVELOG.COM.BR | AK9: RICARDO TOMBINI | AL9: DIRETOR | AO9: RICARDO RAMOS MORAES | AP9: DIRETOR | AQ9: 47 | AR9: 991166116 | AS9: ANGELO COSER NETO | AT9: DIRETOR | AU9: 11 | AV9: 958382446 | AW9: 3317101-Manutenção e reparação de embarcações e estruturas flutuantes\4671100-Comércio atacadista de madeira e produtos derivados\4930201-Transporte rodoviário de carga, exceto produtos perigosos e mudanças, municipal\4930202-Transporte rodoviário de carga, exceto produtos perigosos e mudanças, intermunicipal, interestadual e internacional\5211701-Armazéns gerais - emissão de warrant\5211799-Depósitos de mercadorias para terceiros, exceto armazéns gerais e guarda-móveis\5212500-Carga e descarga\5231101-Administração da infraestrutura portuária\5232000-Atividades de agenciamento marítimo\5239799-Atividades auxiliares dos transportes aquaviários não especificadas anteriormente\5250801-Comissaria de despachos\7739099-Aluguel de outras máquinas e equipamentos comerciais e industriais não especificados anteriormente, sem operador | AX9: 255109660 | AY9: N
A10: 80.718.984/0001-80 | B10: ALUMASA INDUSTRIA DE PLASTICO E ALUMINIO LTDA | D10: GRANDE | E10: 580869389 | F10: 60000000 | G10: 935 | H10: 924 | I10: RISCO MUITO BAIXO | J10: ATIVA | K10: 2512800 | L10: Fabricação de esquadrias de metal | M10: 6/20/1988 | N10: 1 | O10: SC 445 | Q10: KM 25 B | S10: URUSSANGA | T10: SC | U10: 88840000 | V10: 48 | W10: 34412256 | X10: Fixo | AH10: CONTABILIDADE@ALUMASA.COM.BR | AI10: JURANDI@ALUMASA.COM.BR | AJ10: CRISTIANO.RALDI@ALUMASA.COM.BR | AK10: RENATO FONTANELLA | AL10: SOCIO ADMINISTRADOR | AO10: REINALDO FONTANELLA | AP10: SOCIO | AQ10: 48 | AR10: 998290628 | AS10: RODRIGO FONTANELLA | AT10: SOCIO ADMINISTRADOR | AU10: 48 | AV10: 999841297 | AW10: 2229301-Fabricação de artefatos de material plástico para uso pessoal e doméstico\2441501-Produção de alumínio e suas ligas em formas primárias\2441502-Produção de laminados de alumínio\2599399-Fabricação de outros produtos de metal não especificados anteriormente\4330402-Instalação de portas, janelas, tetos, divisórias e armários embutidos de qualquer material\4649499-Comércio atacadista de outros equipamentos e artigos de uso pessoal e doméstico não especificados anteriormente\4679699-Comércio atacadista de materiais de construção em geral\ | AX10: 251694208 | AY10: N
A11: 01.785.688/0001-25 | B11: TERMINAL GRANELEIRO S/A | C11: TERGRASA | D11: GRANDE | E11: 554976874 | F11: 56797402 | G11: 331 | H11: 913 | I11: RISCO MUITO BAIXO | J11: ATIVA | K11: 5211701 | L11: Armazéns gerais - emissão de warrant | M11: 4/3/1997 | N11: 0 | O11: ALMIRANTE MAXIMIANO FONSECA | P11: 5481 | Q11: 4 SECCAO DA BARRA | R11: ZONA PORTUARIA | S11: RIO GRANDE | T11: RS | U11: 96204040 | V11: 53 | W11: 30368650 | X11: Fixo | AH11: FISCAL@CCGL.COM.BR | AK11: NEI CESAR MANICA | AL11: CONSELHEIRO DE ADMINISTRACAO | AM11: 51 | AN11: 981069551 | AO11: DARCI PEDRO HARTMANN | AP11: DIRETOR | AQ11: 55 | AR11: 981250055 | AS11: CAIO CEZAR FERNANDEZ VIANNA | AT11: PRESIDENTE | AU11: 48 | AV11: 988427210 | AW11: 5211799-Depósitos de mercadorias para terceiros, exceto armazéns gerais e guarda-móveis\5231102-Atividades do Operador Portuário | AX11: 100/0186900 | AY11: N
A12: 42.598.920/0001-01 | B12: NORSULMAX NAVEGACAO SA | C12: NORAP | D12: GRANDE | E12: 522234686 | F12: 98877651 | H12: 805 | I12: RISCO MUITO BAIXO | J12: ATIVA | K12: 5011401 | L12: Transporte marítimo de cabotagem - Carga | M12: 4/18/1977 | N12: 0 | O12: PRESIDENTE WILSON, 231 | P12: 00231 | Q12: SAL 304 | R12: CENTRO | S12: RIO DE JANEIRO | T12: RJ | U12: 20030905 | V12: 21 | W12: 21390515 | X12: Fixo | AK12: ANGELO BARONCINI | AL12: PRESIDENTE | AM12: 21 | AN12: 998573143 | AO12: FABIANO BODANEZI LORENZI | AP12: DIRETOR | AQ12: 67 | AR12: 993386179 | AS12: RODRIGO PIRES CUESTA | AT12: DIRETOR | AU12: 21 | AV12: 995731493 | AW12: 5012201-Transporte marítimo de longo curso - Carga\ | AX12: 81.416.885 | AY12: N
