Workbook

Sheet Resumo
A1: Distribuição de Prospects por Vendedor
A3: Critério de distribuição: round-robin (intercalado) para balancear UF e setor entre os 4 vendedores.
A5: Vendedor | B5: Qtd. Empresas | C5: Faturamento Total Presumido (R$) | D5: Total Funcionários
A6: Vendedor 1 | B6: =COUNTA(SANDRA!A5:A100) -> 47 | C6: =SUM(SANDRA!E5:E100) -> 10545619542 | D6: =SUM(SANDRA!G5:G100) -> 11240
A7: Vendedor 2 | B7: =COUNTA(ADRIANA!A5:A100) -> 47 | C7: =SUM(ADRIANA!E5:E100) -> 10435272362 | D7: =SUM(ADRIANA!G5:G100) -> 11477
A8: Vendedor 3 | B8: =COUNTA(GISLAINE!A5:A100) -> 47 | C8: =SUM(GISLAINE!E5:E100) -> 10368800237 | D8: =SUM(GISLAINE!G5:G100) -> 12736
A9: Vendedor 4 | B9: =COUNTA(EDUARDO!A5:A100) -> 46 | C9: =SUM(EDUARDO!E5:E100) -> 10152317542 | D9: =SUM(EDUARDO!G5:G100) -> 14094
A10: TOTAL | B10: =SUM(B6:B9) -> 187 | C10: =SUM(C6:C9) -> 41502009683 | D10: =SUM(D6:D9) -> 49547
A13: Distribuição por UF
A14: UF | B14: Vendedor 1 | C14: Vendedor 2 | D14: Vendedor 3 | E14: Vendedor 4 | F14: Total
A15: AC | B15: 0 | C15: 1 | D15: 0 | E15: 0 | F15: =SUM(B15:E15) -> 1
A16: AM | B16: 0 | C16: 0 | D16: 0 | E16: 2 | F16: =SUM(B16:E16) -> 2
A17: BA | B17: 3 | C17: 0 | D17: 1 | E17: 0 | F17: =SUM(B17:E17) -> 4
A18: CE | B18: 1 | C18: 0 | D18: 2 | E18: 0 | F18: =SUM(B18:E18) -> 3
A19: DF | B19: 1 | C19: 0 | D19: 0 | E19: 0 | F19: =SUM(B19:E19) -> 1
A20: ES | B20: 1 | C20: 2 | D20: 4 | E20: 1 | F20: =SUM(B20:E20) -> 8
A21: GO | B21: 2 | C21: 0 | D21: 1 | E21: 1 | F21: =SUM(B21:E21) -> 4
A22: MG | B22: 10 | C22: 5 | D22: 4 | E22: 6 | F22: =SUM(B22:E22) -> 25
A23: MS | B23: 0 | C23: 1 | D23: 0 | E23: 0 | F23: =SUM(B23:E23) -> 1
A24: MT | B24: 0 | C24: 1 | D24: 1 | E24: 0 | F24: =SUM(B24:E24) -> 2
A25: PE | B25: 0 | C25: 0 | D25: 0 | E25: 1 | F25: =SUM(B25:E25) -> 1
A26: PI | B26: 0 | C26: 0 | D26: 0 | E26: 1 | F26: =SUM(B26:E26) -> 1
... A32: SP | B32: 16 | C32: 16 | D32: 19 | E32: 17 | F32: =SUM(B32:E32) -> 68
A34: Dica: cada aba já vem com filtro automático, cabeçalho congelado e as 3 primeiras colunas fixadas para facilitar a navegação.

Sheet SANDRA
A1: Carteira de Prospects — Vendedor 1
A2: Total de empresas: 47 | Porte: GRANDE | Fonte: Base de prospecção
A4: CNPJ | B4: Razão Social | C4: Nome Fantasia | D4: Porte | E4: Faturamento Presumido (R$) | F4: Capital Social (R$) | G4: Qtd. Funcionários | H4: Score | I4: Classificação de Risco | J4: Situação Cadastral | K4: CNAE | L4: Atividade Principal | M4: Data Abertura | N4: Qtd. Filiais | O4: Logradouro | P4: Nº | Q4: Complemento | R4: Bairro | S4: Cidade | T4: UF | U4: CEP | V4: DDD 1 | W4: Telefone 1 | X4: Tipo 1 | Y4: DDD 2 | Z4: Telefone 2 | AA4: Tipo 2 | AB4: DDD 3 | AC4: Telefone 3 | AD4: Tipo 3 | AE4: DDD 4 | AF4: Telefone 4 | AG4: Tipo 4 | AH4: E-mail 1 | AI4: E-mail 2 | AJ4: E-mail 3 | AK4: Sócio 1 | AL4: Cargo Sócio 1 | AM4: DDD Sócio 1 | AN4: Tel. Sócio 1 | AO4: Sócio 2 | AP4: Cargo Sócio 2 | AQ4: DDD Sócio 2 | AR4: Tel. Sócio 2 | AS4: Sócio 3 | AT4: Cargo Sócio 3 | AU4: DDD Sócio 3 | AV4: Tel. Sócio 3 | AW4: CNAEs Secundários | AX4: Inscrição Estadual | AY4: Flag DAU
A5: 59.105.262/0001-63 | B5: TRANSAUTO TRANSPORTES ESPECIALIZADOS DE AUTOMOVEIS S A | D5: GRANDE | E5: 472761491 | F5: 100000000 | G5: 70 | H5: 914 | I5: RISCO MUITO BAIXO | J5: ATIVA | K5: 4930202 | L5: Transporte rodoviário de carga, exceto produtos perigosos e mudanças, intermunicipal, interestadual e internacional | M5: 7/20/1966 | N5: 12 | O5: SENADOR VERGUEIRO | P5: 4600 | R5: RUDGE RAMOS | S5: SAO BERNARDO DO CAMPO | T5: SP | U5: 9604000 | V5: 11 | W5: 930660337 | X5: Celular | Y5: 11 | Z5: 956962202 | AA5: Celular | AB5: 11 | AC5: 963888459 | AD5: Celular | AE5: 11 | AF5: 43663400 | AG5: Fixo | AH5: CONTAB@TRANSAUTO.COM.BR | AI5: ADRIANA@TRANSAUTO.COM.BR | AJ5: ALEXANDRE@TRANSAUTO.COM.BR | AK5: ANA LUIZA MENEZES DE GOES | AL5: DIRETOR | AM5: 11 | AN5: 992041313 | AO5: ERYX DE OLIVEIRA | AP5: DIRETOR | AQ5: 11 | AR5: 991834832 | AW5: 4520007-Serviços de instalação, manutenção e reparação de acessórios para veículos automotores\4930201-Transporte rodoviário de carga, exceto produtos perigosos e mudanças, municipal\5229002-Serviços de reboque de veículos\ | AX5: 635.031.050.113 | AY5: N
A6: 01.934.441/0001-23 | B6: TRANSPORTES SARZEDO LTDA | D6: GRANDE | E6: 455830534 | F6: 30500000 | G6: 2069 | H6: 940 | I6: RISCO MUITO BAIXO | J6: ATIVA | K6: 4930201 | L6: Transporte rodoviário de carga, exceto produtos perigosos e mudanças, municipal | M6: 6/24/1997 | N6: 1 | O6: CAMPOS ELISIOS | P6: 371 | R6: BRASILIA | S6: SARZEDO | T6: MG | U6: 32450000 | V6: 31 | W6: 971857584 | X6: Celular | Y6: 31 | Z6: 998885048 | AA6: Celular | AB6: 31 | AC6: 971108927 | AD6: Celular | AE6: 31 | AF6: 35778749 | AG6: Fixo | AH6: CACAMBAS.ATERRO@TSLSOLUCOES.COM.BR | AK6: JOSE DONIZETE DE SOUZA MAIA | AL6: SOCIO ADMINISTRADOR | AM6: 31 | AN6: 999672488 | AO6: JOAO PAULO MOREIRA DE SOUSA | AP6: ADMINISTRADOR | AQ6: 31 | AR6: 998885048 | AS6: EDUARDO MENDES DE SOUSA MAIA | AT6: ADMINISTRADOR | AU6: 31 | AV6: 991587550 | AW6: 3811400-Coleta de resíduos não perigosos\4313400-Obras de terraplenagem\4319300-Serviços de preparação do terreno não especificados anteriormente\4929902-Transporte rodoviário coletivo de passageiros, sob regime de fretamento, intermunicipal, interestadual e internacional\4930202-Transporte rodoviário de carga, exceto produtos perigosos e mudanças, intermunicipal, interestadual e internacional\4930203-Transporte rodoviário de produtos perigosos\5212500-Carga e descarga\7739099-Aluguel de outras máquinas e equipamentos comerciais e industriais não especificados anteriormente, sem operador\7820500-Locação de mão de obra temporária\8129000-Atividades de limpeza não especificadas anteriormente | AX6: 850041085.00-38 | AY6: N
A7: 11.727.497/0001-60 | B7: NATURAVES INDUSTRIA E COMERCIO DE ALIMENTOS LTDA | D7: GRANDE | E7: 419981320 | F7: 54362847 | G7: 607 | H7: 606 | I7: RISCO BAIXO | J7: ATIVA | K7: 1012101 | L7: Abate de aves | M7: 3/16/2010 | N7: 1 | O7: RUY BARBOSA 479 | Q7: FAZENDA RESPLENDOR | R7: CENTRO | S7: EUNAPOLIS | T7: BA | U7: 45820970 | V7: 73 | W7: 999551456 | X7: Celular | Y7: 73 | Z7: 998681454 | AA7: Celular | AB7: 73 | AC7: 998712612 | AD7: Celular | AE7: 73 | AF7: 31662450 | AG7: Fixo | AH7: FISCAL2@NATURAVES.COM.BR | AK7: JUSCIMAR MODENEZI DE ALMEIDA | AL7: ADMINISTRADOR | AM7: 73 | AN7: 999851115 | AO7: CLEOMAR MODENEZI DE ALMEIDA | AP7: ADMINISTRADOR | AQ7: 73 | AR7: 981591409 | AS7: CESCONETTO E FILHOS PARTICIPACOES SOCIETARIAS LTDA | AT7: SOCIO | AU7: 73 | AV7: 31662450 | AW7: 0111302-Cultivo de milho\0155501-Criação de frangos para corte\0155502-Produção de pintos de um dia\1013901-Fabricação de produtos de carne\1013902-Preparação de subprodutos do abate\1066000-Fabricação de alimentos para animais\4623109-Comércio atacadista de alimentos para animais\4634602-Comércio atacadista de aves abatidas e derivados\4639701-Comércio atacadista de produtos alimentícios em geral\4930202-Transporte rodoviário de carga, exceto produtos perigosos e mudanças, intermunicipal, interestadual e internacional\5620101-Fornecimento de alimentos preparados preponderantemente para empresas\ | AX7: 086.309.978 | AY7: N
A8: 02.326.750/0001-83 | B8: INTERCAST S/A | D8: GRANDE | E8: 408374455 | F8: 14350450 | G8: 416 | H8: 900 | I8: RISCO MUITO BAIXO | J8: ATIVA | K8: 2451200 | L8: Fundição de ferro e aço | M8: 1/21/1998 | N8: 0 | O8: MG-050 | P8: KM 92 | R8: DISTRITO INDUSTRIAL | S8: ITAUNA | T8: MG | U8: 35681750 | V8: 37 | W8: 998566598 | X8: Celular | Y8: 37 | Z8: 998248452 | AA8: Celular | AB8: 37 | AC8: 998765162 | AD8: Celular | AE8: 37 | AF8: 32497040 | AG8: Fixo | AH8: FERNANDA@INTERCAST.COM.BR | AI8: INTERCAST@INTERCAST.COM.BR | AJ8: LILIAN@INTERCAST.COM.BR | AK8: CASSIO MOREIRA MACHADO | AL8: PRESIDENTE | AM8: 37 | AN8: 991214401 | AO8: SAMUEL NOGUEIRA RABELO DE MELO | AP8: DIRETOR | AW8: 2543800-Fabricação de ferramentas\3319800-Manutenção e reparação de equipamentos e produtos não especificados anteriormente\4663000-Comércio atacadista de máquinas e equipamentos para uso industrial, partes e peças\ | AX8: 338726365.00-33 | AY8: N
A9: 19.749.936/0001-48 | B9: GSL METALURGICA S/A | D9: GRANDE | E9: 391025934 | F9: 15000000 | G9: 316 | H9: 917 | I9: RISCO MUITO BAIXO | J9: ATIVA | K9: 2511000 | L9: Fabricação de estruturas metálicas | M9: 8/11/1977 | N9: 2 | O9: ENGENHEIRO SERGIO MACULAN | P9: 120 | R9: DISTRITO INDUSTRIAL SIMAO DA CUNHA | S9: SABARA | T9: MG | U9: 34735022 | V9: 31 | W9: 995330574 | X9: Celular | Y9: 31 | Z9: 971358821 | AA9: Celular | AB9: 31 | AC9: 999589015 | AD9: Celular | AE9: 31 | AF9: 36793100 | AG9: Fixo | AH9: GSL@GSL.COM.BR | AI9: COMPRAS2@GSL.COM.BR | AJ9: QUALIDADE@GSL.COM.BR | AK9: FABIANO DE SOUZA BATISTA | AL9: CONSELHEIRO DE ADMINISTRACAO | AM9: 31 | AN9: 984043997 | AO9: DANIEL CARVALHO MARTINS | AP9: DIRETOR | AQ9: 31 | AR9: 992750300 | AS9: JANINE CARVALHO MARTINS | AT9: CONSELHEIRO DE ADMINISTRACAO | AU9: 81 | AV9: 991417313 | AW9: 2539002-Serviços de tratamento e revestimento em metais\4292801-Montagem de estruturas metálicas\7112000-Serviços de engenharia\ | AX9: 578260161.00-70 | AY9: N
A10: 09.078.935/0001-65 | B10: STARNAV SERVICOS MARITIMOS LTDA. | D10: GRANDE | E10: 384199059 | F10: 247393395 | G10: 651 | H10: 464 | I10: RISCO MÉDIO | J10: ATIVA | K10: 5030101 | L10: Navegação de apoio marítimo | M10: 9/25/2007 | N10: 5 | O10: CESAR AUGUSTO DALSOQUIO | P10: 4500 | Q10: SALAA | R10: SALSEIROS | S10: ITAJAI | T10: SC | U10: 88311500 | V10: 22 | W10: 996161482 | X10: Celular | Y10: 22 | Z10: 996161655 | AA10: Celular | AB10: 22 | AC10: 999211094 | AD10: Celular | AE10: 47 | AF10: 21038561 | AG10: Fixo | AH10: WKBRA@DETROIT.CL | AK10: DETROIT UK INTERNATIONAL LLP | AL10: SOCIO PESSOA JURIDICA DOMICILIADO NO EXTERIOR | AO10: JULIANO ZIMMERMANN DE FREITAS | AP10: ADMINISTRADOR | AQ10: 47 | AR10: 999279442 | AW10: 4669999-Comércio atacadista de outras máquinas e equipamentos não especificados anteriormente, partes e peças\5011401-Transporte marítimo de cabotagem - Carga\5011402-Transporte marítimo de cabotagem - Passageiros\5012201-Transporte marítimo de longo curso - Carga\5012202-Transporte marítimo de longo curso - Passageiros\5021102-Transporte por navegação interior de carga, intermunicipal, interestadual e internacional, exceto travessia\5022002-Transporte por navegação interior de passageiros em linhas regulares, intermunicipal, interestadual e internacional, exceto travessia\5030102-Navegação de apoio portuário\5030103-Serviço de rebocadores e empurradores\6462000-Holdings de instituições não financeiras\6463800-Outras sociedades de participação, exceto holdings\7719501-Locação de embarcações sem tripulação, exceto para finsrecreativos | AX10: 255858620 | AY10: N
A11: 04.731.861/0001-09 | B11: INTERALLI GRAOS TERMINAIS S.A | D11: GRANDE | E11: 368955710 | F11: 60116176 | G11: 188 | H11: 930 | I11: RISCO MUITO BAIXO | J11: ATIVA | K11: 5231102 | L11: Atividades do Operador Portuário | M11: 10/22/2001 | N11: 4 | O11: PORTUARIA | R11: DOM PEDRO II | S11: PARANAGUA | T11: PR | U11: 83221570 | V11: 31 | W11: 984631182 | X11: Celular | Y11: 41 | Z11: 32210707 | AA11: Fixo | AH11: CONTADOR1@INTERALLI.COM.BR | AI11: ANGELA@INTERALLI.COM.BR | AJ11: ANDERSON@INTERALLI.COM.BR | AK11: CRISTIANO SLAVIERO FUMAGALLI | AL11: DIRETOR | AM11: 43 | AN11: 999579325 | AO11: FELIPE SLAVIERO FUMAGALLI | AP11: DIRETOR | AQ11: 43 | AR11: 999741354 | AS11: FABRICIO SLAVIERO FUMAGALLI | AT11: DIRETOR | AU11: 66 | AV11: 999540930 | AW11: 5211701-Armazéns gerais - emissão de warrant\5232000-Atividades de agenciamento marítimo\5250801-Comissaria de despachos\5250803-Agenciamento de cargas, exceto para o transporte marítimo | AX11: 90529181-51 | AY11: N
A12: 17.578.354/0001-10 | B12: ITESAPAR FUNDICAO LTDA | C12: ITESAPAR FUNDICAO | D12: GRANDE | E12: 357152613 | F12: 20000000 | G12: 26 | H12: 206 | I12: RISCO ALTO | J12: ATIVA | K12: 2452100 | L12: Fundição de metais não ferrosos e suas ligas | M12: 2/7/2013 | N12: 0 | O12: PE ANCHIETA | P12: 112 | Q12: LT 12 LT 12 112 | R12: VL VIDA | S12: PALMEIRA | T12: PR | U12: 84130000 | V12: 42 | W12: 32528536 | X12: Fixo | AH12: CONTABIL@ITESAPAR.COM.BR | AI12: DIRETORIA@ITESA.COM.BR | AJ12: ADIR.SANTOS@ITESAPAR.COM.BR | AK12: MARCELO RIBEIRO | AL12: SOCIO-ADMINISTRADOR | AM12: 11 | AN12: 959501724 | AW12: 2539001-Serviços de usinagem, torneiria e solda\7739001-Aluguel de máquinas e equipamentos para extração de minérios e petróleo, sem operador | AX12: 90621463-60 | AY12: S
A13: 04.535.453/0001-73 | B13: BRASCERAS S.A. INDUSTRIA E COMERCIO | C13: GEQUIMICA INDUSTRIA E COMERCIO | D13: GRANDE | E13: 333829029 | F13: 32449000 | G13: 32 | H13: 967 | I13: RISCO MUITO BAIXO | J13: ATIVA | K13: 1921700 | L13: Fabricação de produtos do refino de petróleo | M13: 6/21/2001 | N13: 3 | O13: COPACABANA | P13: 190 | Q13: SALA 801 E 802 | R13: DEZOITO DO FORTE EMPRESARIAL/ALPHAVILLE. | S13: BARUERI | T13: SP | U13: 6472001 | V13: 11 | W13: 41338111 | X13: Fixo | AH13: ANDREIA.ZEBELLINI@GEQUIMICA.COM.BR | AI13: CLELIO@GEQUIMICA.COM.BR | AJ13: ADILSON.XAVIER@GEQUIMICA.COM.BR | AK13: KLEBER REIMBERG GUTSCHOW | AL13: PRESIDENTE | AM13: 11 | AN13: 983549171 | AO13: GISELE CIRILO SILVESTRE | AP13: DIRETOR | AQ13: 11 | AR13: 999562014 | AW13: 2099199-Fabricação de outros produtos químicos não especificados anteriormente\4612500-Representantes comerciais e agentes do comércio de combustíveis, minerais, produtos siderúrgicos e químicos\4684299-Comércio atacadista de outros produtos químicos e petroquímicos não especificados anteriormente\4693100-Comércio atacadista de mercadorias em geral, sem predominância de alimentos ou de insumos agropecuários\4930201-Transporte rodoviário de carga, exceto produtos perigosos e mudanças, municipal\4930202-Transporte rodoviário de carga, exceto produtos perigosos e mudanças, intermunicipal, interestadual e internacional\5250803-Agenciamento de cargas, exceto para o transporte marítimo\7719599-Locação de outros meios de transporte não especificados anteriormente, sem condutor\8211300-Serviços combinados de escritório e apoio administrativo\ | AX13: 90247455-27 | AY13: N
A14: 60.319.985/0001-44 | B14: JOMED TRANSPORTES E LOGISTICA S/A | D14: GRANDE | E14: 327762506 | F14: 13153280 | G14: 235 | H14: 864 | I14: RISCO MUITO BAIXO | J14: ATIVA | K14: 4930202 | L14: Transporte rodoviário de carga, exceto produtos perigosos e mudanças, intermunicipal, interestadual e internacional | M14: 3/31/1989 | N14: 9 | O14: SISA | P14: 261 | R14: CIDADE INDUSTRIAL SATELITE DE SAO PAULO | S14: GUARULHOS | T14: SP | U14: 7221030 | V14: 27 | W14: 974001210 | X14: Celular | Y14: 11 | Z14: 971965330 | AA14: Celular | AB14: 11 | AC14: 49668215 | AD14: Fixo | AH14: SIDNEI.ALVES@JOMEDLOG.COM.BR | AI14: COMERCIAL@JOMEDLOG.COM.BR | AK14: ODAIR BRAGA GARRIDO | AL14: TITULAR PESSOA FISICA RESIDENTE OU DOMICILIADO NO BRASIL | AM14: 11 | AN14: 940321440 | AO14: JOCELIA DE JESUS CAMPOS | AP14: DIRETOR | AQ14: 27 | AR14: 997236372 | AW14: 4930201-Transporte rodoviário de carga, exceto produtos perigosos e mudanças, municipal\4930203-Transporte rodoviário de produtos perigosos\5211701-Armazéns gerais - emissão de warrant\5211799-Depósitos de mercadorias para terceiros, exceto armazéns gerais e guarda-móveis\5212500-Carga e descarga\5250805-Operador de transporte multimodal - OTM\5320201-Serviços de malote não realizados pelo Correio Nacional\5320202-Serviços de entrega rápida\7719599-Locação de outros meios de transporte não especificados anteriormente, sem condutor\ | AX14: 796.529.849.112 | AY14: N
A15: 02.462.805/0001-82 | B15: FM LOGISTIC DO BRASIL OPERACOES DE LOGISTICA LTDA. | D15: GRANDE | E15: 303447574 | F15: 87004818 | G15: 22 | H15: 290 | I15: RISCO ALTO | J15: ATIVA | K15: 5211701 | L15: Armazéns gerais - emissão de warrant | M15: 3/6/1998 | N15: 9 | O15: ANHANGUERA | Q15: KM26 421 PREDIO 1 SALA1 | R15: JARDIM JARAGUA | S15: SAO PAULO | T15: SP | U15: 5275000 | V15: 31 | W15: 984358933 | X15: Celular | Y15: 31 | Z15: 984358691 | AA15: Celular | AB15: 31 | AC15: 984346784 | AD15: Celular | AE15: 11 | AF15: 21099400 | AG15: Fixo | AH15: CPFISCAL@FMLOGISTIC.COM.BR | AK15: FM LOGISTIC SERVICES | AL15: SOCIO PESSOA JURIDICA DOMICILIADO NO EXTERIOR | AO15: FM LOGISTIC CORPORATE | AP15: SOCIO PESSOA JURIDICA DOMICILIADO NO EXTERIOR | AS15: RONALDO FERNANDES DA SILVA | AT15: ADMINISTRADOR | AU15: 19 | AV15: 981377125 | AW15: 4930202-Transporte rodoviário de carga, exceto produtos perigosos e mudanças, intermunicipal, interestadual e internacional\8292000-Envasamento e empacotamento sob contrato | AX15: 142.238.168.114 | AY15: N
A16: 39.397.682/0001-53 | B16: BUSATO - TRANSPORTES E LOCACOES LTDA | D16: GRANDE | E16: 287327513 | F16: 300000 | G16: 619 | H16: 861 | I16: RISCO MUITO BAIXO | J16: ATIVA | K16: 4930202 | L16: Transporte rodoviário de carga, exceto produtos perigosos e mudanças, intermunicipal, interestadual e internacional | M16: 2/3/1993 | N16: 1 | O16: GAIVOTA | P16: 1640 | R16: NOVO HORIZONTE | S16: SERRA | T16: ES | U16: 29163322 | V16: 31 | W16: 997681925 | X16: Celular | Y16: 27 | Z16: 996168132 | AA16: Celular | AB16: 27 | AC16: 992551869 | AD16: Celular | AE16: 27 | AF16: 32162008 | AG16: Fixo | AH16: COMERCIAL@BUSATOTRANSPORTES.COM.BR | AI16: BUSATO.CONSTRUTORA@TERRA.COM.BR | AK16: GENEZIO BUSATO | AL16: SOCIO | AM16: 27 | AN16: 998314777 | AO16: EDNO BUSATO | AP16: SOCIO | AQ16: 27 | AR16: 999714900 | AS16: FERNANDO BUSATO | AT16: SOCIO ADMINISTRADOR | AU16: 27 | AV16: 996908044 | AW16: 3600602-Distribuição de água por caminhões\3811400-Coleta de resíduos não perigosos\3812200-Coleta de resíduos perigosos\4311801-Demolição de edifícios e outras estruturas\4399104-Serviços de operação e fornecimento de equipamentos para transporte e elevação de cargas e pessoas para uso em obras\4921301-Transporte rodoviário coletivo de passageiros, com itinerário fixo, municipal\4923002-Serviço de transporte de passageiros - locação de automóveis com motorista\4930201-Transporte rodoviário de carga, exceto produtos perigosos e mudanças, municipal\5212500-Carga e descarga\7711000-Locação de automóveis sem condutor\7719599-Locação de outros meios de transporte não especificados anteriormente, sem condutor\7732201-Aluguel de máquinas e equipamentos para construção sem operador, exceto andaimes\7739099-Aluguel de outras máquinas e equipamentos comerciais e industriais não especificados anteriormente, sem operador\ | AX16: 081.595.82-4 | AY16: N
A17: 13.892.216/0001-50 | B17: TORRES EOLICAS DO NORDESTE S/A | D17: GRANDE | E17: 282758528 | F17: 40255019 | H17: 947 | I17: RISCO MUITO BAIXO | J17: ATIVA | K17: 2511000 | L17: Fabricação de estruturas metálicas | M17: 6/28/2011 | N17: 1 | O17: DO CONTORNO | P17: 8269 | Q17: SALA 009 | R17: GUTIERREZ | S17: BELO HORIZONTE | T17: MG | U17: 30110059 | V17: 74 | W17: 999940869 | X17: Celular | Y17: 74 | Z17: 999712151 | AA17: Celular | AB17: 74 | AC17: 999752038 | AD17: Celular | AE17: 31 | AF17: 32906655 | AG17: Fixo | AH17: ILDA.AZEVEDO@AGNET.COM.BR | AK17: ANDRE DE RESENDE RODRIGUES | AL17: DIRETOR | AM17: 51 | AN17: 993246161 | AO17: JOSE ALBERTO TEIXEIRA DA SILVA | AP17: DIRETOR | AQ17: 12 | AR17: 996668080 | AS17: ARTHUR ARAUJO DE SOUZA | AT17: DIRETOR | AU17: 75 | AV17: 982144171 | AW17: 3319800-Manutenção e reparação de equipamentos e produtos não especificados anteriormente\4221902-Construção de estações e redes de distribuição de energia elétrica\5211799-Depósitos de mercadorias para terceiros, exceto armazéns gerais e guarda-móveis\7112000-Serviços de engenharia | AX17: 002161980.00-63 | AY17: N
A18: 49.316.524/0001-85 | B18: ROSARIAL ALIMENTOS S/A | C18: ROSARIAL ALIMENTOS | D18: GRANDE | E18: 275281111 | F18: 2060460 | G18: 61 | H18: 912 | I18: RISCO MUITO BAIXO | J18: ATIVA | K18: 1013901 | L18: Fabricação de produtos de carne | M18: 4/22/1970 | N18: 3 | O18: ESTM IBIUNA RIO DE UNA | P18: 777 | Q18: CXPST 16 | R18: RIO DE UNA | S18: IBIUNA | T18: SP | U18: 18150000 | V18: 15 | W18: 991255155 | X18: Celular | Y18: 15 | Z18: 991347427 | AA18: Celular | AB18: 15 | AC18: 996051756 | AD18: Celular | AE18: 15 | AF18: 32489791 | AG18: Fixo | AH18: EVANDRO@ROSARIAL.COM.BR | AI18: MARCO@ROSARIAL.COM.BR | AK18: MARCO AURELIO ROSSIT SILVA | AL18: PRESIDENTE | AM18: 15 | AN18: 991343638 | AO18: EVANDRO JESUS RIBEIRO | AP18: DIRETOR | AQ18: 15 | AR18: 991356968 | AW18: 4930201-Transporte rodoviário de carga, exceto produtos perigosos e mudanças, municipal\4930202-Transporte rodoviário de carga, exceto produtos perigosos e mudanças, intermunicipal, interestadual e internacional | AX18: 345.002.200.110 | AY18: S
A19: 04.754.815/0001-17 | B19: UP OFFSHORE APOIO MARITIMO LTDA | D19: MÉDIA | E19: 273016956 | F19: 212328705 | G19: 94 | H19: 645 | I19: RISCO BAIXO | J19: ATIVA | K19: 5030101 | L19: Navegação de apoio marítimo | M19: 9/12/2001 | N19: 1 | O19: DA GLORIA | P19: 344 | Q19: SALA401 PARTE SALA402 PARTE SALA403 PARTE SALA404 PARTE | R19: GLORIA | S19: RIO DE JANEIRO | T19: RJ | U19: 20241180 | V19: 21 | W19: 997735764 | X19: Celular | Y19: 21 | Z19: 967135148 | AA19: Celular | AB19: 21 | AC19: 971133230 | AD19: Celular | AE19: 21 | AF19: 21124500 | AG19: Fixo | AH19: MADAMES@SEACORMARINE.COM | AI19: ASETHI@UPOFFSHORE.COM.BR | AJ19: TI@UPOFFSHORE.COM.BR | AK19: OCEANPACT SERVICOS MARITIMOS S.A. | AL19: SOCIO | AM19: 21 | AN19: 30326700 | AO19: FLAVIO NOGUEIRA PINHEIRO DE ANDRADE | AP19: ADMINISTRADOR | AQ19: 85 | AR19: 997672472 | AS19: EDUARDO DE TOLEDO | AT19: ADMINISTRADOR | AU19: 11 | AV19: 999524185 | AW19: 0910600-Atividades de apoio à extração de petróleo e gás natural\4619200-Representantes comerciais e agentes do comércio de mercadorias em geral não especializado\5030102-Navegação de apoio portuário\5030103-Serviço de rebocadores e empurradores\5099899-Outros transportes aquaviários não especificados anteriormente\5232000-Atividades de agenciamento marítimo\6463800-Outras sociedades de participação, exceto holdings\7719501-Locação de embarcações sem tripulação, exceto para finsrecreativos | AX19: 77.344.993 | AY19: N
A20: 00.450.577/0001-03 | B20: CPC CONSTRUCOES E PROCESSOS CIENTIFICOS LTDA | D20: MÉDIA | E20: 265543364 | F20: 32000000 | G20: 329 | H20: 465 | I20: RISCO MÉDIO | J20: ATIVA | K20: 2511000 | L20: Fabricação de estruturas metálicas | M20: 7/6/1976 | N20: 2 | O20: SAAN QUADRA 2 | P20: 310 | Q20: ST ABAS NORTE | R20: ZONA INDUSTRIAL | S20: BRASILIA | T20: DF | U20: 70632200 | V20: 61 | W20: 993963184 | X20: Celular | Y20: 61 | Z20: 995568250 | AA20: Celular | AB20: 61 | AC20: 992554754 | AD20: Celular | AE20: 61 | AF20: 33610030 | AG20: Fixo | AH20: ANTONIO@CPCESTRUTURAS.COM.BR | AI20: ARMANDO@CPCESTRUTURAS.COM.BR | AJ20: CARLOS@CPCESTRUTURAS.COM.BR | AK20: RENATO MAIA PUPO | AL20: ADMINISTRADOR | AM20: 24 | AN20: 998593982 | AO20: RMP CONSTRUCOES E ENGENHARIA LTDA | AP20: SOCIO | AQ20: 61 | AR20: 35415643 | AW20: 2513600-Fabricação de obras de caldeiraria pesada\2521700-Fabricação de tanques, reservatórios metálicos e caldeiras para aquecimento central\2539001-Serviços de usinagem, torneiria e solda\2539002-Serviços de tratamento e revestimento em metais\2599302-Serviço de corte e dobra de metais\4110700-Incorporação de empreendimentos imobiliários\4120400-Construção de edifícios\4292801-Montagem de estruturas metálicas\4292802-Obras de montagem industrial\4329199-Outras obras de instalações em construções não especificadas anteriormente\6462000-Holdings de instituições não financeiras\6810201-Compra e venda de imóveis próprios\6810202-Aluguel de imóveis próprios\7112000-Serviços de engenharia | AX20: 0731759600176 | AY20: S
A21: 01.855.226/0001-37 | B21: SOLFACIL DISTRIBUIDORA INDUSTRIAL LTDA | C21: SOLFACIL DISTRIBUIDORA | D21: MÉDIA | E21: 260868277 | F21: 91045494 | G21: 109 | H21: 591 | I21: RISCO BAIXO | J21: ATIVA | K21: 2511000 | L21: Fabricação de estruturas metálicas | M21: 4/22/1997 | N21: 4 | O21: JOSE ALVES DOS SANTOS PASSOS | P21: 3064 | Q21: O GALP | R21: SAO MARTINHO | S21: TUBARAO | T21: SC | U21: 88708701 | V21: 48 | W21: 999913028 | X21: Celular | Y21: 48 | Z21: 998580002 | AA21: Celular | AB21: 48 | AC21: 984050627 | AD21: Celular | AE21: 48 | AF21: 36280258 | AG21: Fixo | AH21: CONTABILIDADE@SOLARINOVE.COM.BR | AI21: TURBOFERRO@TURBOFERRO.COM.BR | AJ21: BRAINER@TURBOFERRO.COM.BR | AK21: FABIO AUGUSTO BREDDA CARRARA | AL21: ADMINISTRADOR | AM21: 11 | AN21: 998009692 | AO21: GUILLAUME CHRISTIAN EMMANUEL TIRET | AP21: ADMINISTRADOR | AQ21: 11 | AR21: 944592654 | AS21: SOLFACIL PARTICIPACOES LTDA | AT21: SOCIO | AU21: 11 | AV21: 973987407 | AW21: 2542000-Fabricação de artigos de serralheria, exceto esquadrias\2610800-Fabricação de componentes eletrônicos\2710401-Fabricação de geradores de corrente contínua e alternada, peças e acessórios\2731700-Fabricação de aparelhos e equipamentos para distribuição e controle de energia elétrica\3329599-Instalação de outros equipamentos não especificados anteriormente\4292801-Montagem de estruturas metálicas\4669999-Comércio atacadista de outras máquinas e equipamentos não especificados anteriormente, partes e peças\4689399-Comércio atacadista especializado em outros produtos intermediários não especificados anteriormente\4742300-Comércio varejista de material elétrico\4930201-Transporte rodoviário de carga, exceto produtos perigosos e mudanças, municipal\4930202-Transporte rodoviário de carga, exceto produtos perigosos e mudanças, intermunicipal, interestadual e internacional\5211701-Armazéns gerais - emissão de warrant\5250801-Comissaria de despachos\5250803-Agenciamento de cargas, exceto para o transporte marítimo\5250804-Organização logística do transporte de carga\8211300-Serviços combinados de escritório e apoio administrativo | AX21: 253422817 | AY21: N
A22: 05.104.067/0001-90 | B22: GALAXIA MARITIMA S.A. | C22: GLX | D22: GRANDE | E22: 250330401 | F22: 7765000 | G22: 83 | H22: 542 | I22: RISCO BAIXO | J22: ATIVA | K22: 5030101 | L22: Navegação de apoio marítimo | M22: 5/22/2002 | N22: 1 | O22: ACAPULCO | P22: 24 | R22: CAVALEIROS | S22: MACAE | T22: RJ | U22: 27920150 | V22: 21 | W22: 984917897 | X22: Celular | Y22: 21 | Z22: 971785237 | AA22: Celular | AB22: 21 | AC22: 38048100 | AD22: Fixo | AH22: J.ALEXANDRE@GALAXIAMARITIMA.COM.BR | AI22: BIANCA.MARQUES@GALAXIAMARITIMA.COM.BR | AJ22: DAVID.ALVARENGA@GALAXIAMARITIMA.COM.BR | AK22: GERSON WAGNER PINHEIRO DE MORAES | AL22: DIRETOR | AM22: 21 | AN22: 996680563 | AO22: ANTONIO EDUARDO DE BARROS PINHEIRO | AP22: DIRETOR | AS22: THIAGO PALMIERI | AT22: DIRETOR | AU22: 21 | AV22: 974453613 | AW22: 5011401-Transporte marítimo de cabotagem - Carga\5012201-Transporte marítimo de longo curso - Carga\5030102-Navegação de apoio portuário\5232000-Atividades de agenciamento marítimo | AX22: 77.420.452 | AY22: S
A23: 58.673.450/0001-25 | B23: TAIPASTUR TRANSPORTES TURISTICOS LTDA | D23: GRANDE | E23: 226346985 | F23: 7340000 | G23: 239 | H23: 961 | I23: RISCO MUITO BAIXO | J23: ATIVA | K23: 4930202 | L23: Transporte rodoviário de carga, exceto produtos perigosos e mudanças, intermunicipal, interestadual e internacional | M23: 3/3/1988 | N23: 8 | O23: DEPUTADO CANTIDIO SAMPAIO | P23: 6557 | R23: VILA SOUZA | S23: SAO PAULO | T23: SP | U23: 2860001 | V23: 11 | W23: 21523500 | X23: Fixo | Y23: 11 | Z23: 993475924 | AA23: Celular | AB23: 11 | AC23: 989284271 | AD23: Celular | AE23: 11 | AF23: 989291421 | AG23: Celular | AH23: CONTABILIDADE@PICCOLOTUR.COM.BR | AK23: FERNANDO RUAS PICCOLO | AL23: SOCIO ADMINISTRADOR | AM23: 11 | AN23: 999435015 | AO23: EVANIR ROBERTO PICCOLO | AP23: SOCIO ADMINISTRADOR | AQ23: 31 | AR23: 995686556 | AW23: 4923002-Serviço de transporte de passageiros - locação de automóveis com motorista\4929901-Transporte rodoviário coletivo de passageiros, sob regime de fretamento, municipal\4929902-Transporte rodoviário coletivo de passageiros, sob regime de fretamento, intermunicipal, interestadual e internacional\4929904-Organização de excursões em veículos rodoviários próprios, intermunicipal, interestadual e internacional\4929999-Outros transportes rodoviários de passageiros não especificados anteriormente\4930201-Transporte rodoviário de carga, exceto produtos perigosos e mudanças, municipal\4930203-Transporte rodoviário de produtos perigosos\6462000-Holdings de instituições não financeiras\6463800-Outras sociedades de participação, exceto holdings\7711000-Locação de automóveis sem condutor\7719599-Locação de outros meios de transporte não especificados anteriormente, sem condutor\7739099-Aluguel de outras máquinas e equipamentos comerciais e industriais não especificados anteriormente, sem operador\7820500-Locação de mão de obra temporária\ | AX23: 112.326.797.110 | AY23: N
A24: 81.804.684/0001-86 | B24: TRANSPORTES E ARMAZENAGEM ZILLI LTDA | C24: TRANSZILLI EXPRESSO E LOGISTICA | D24: GRANDE | E24: 222712859 | F24: 139000000 | G24: 10 | H24: 913 | I24: RISCO MUITO BAIXO | J24: ATIVA | K24: 4930202 | L24: Transporte rodoviário de carga, exceto produtos perigosos e mudanças, intermunicipal, interestadual e internacional | M24: 4/17/1990 | N24: 26 | O24: BR-153 | P24: SN | Q24: QUADRAAREA LOTE 0002 SALA 1 | R24: PARQUE INDUSTRIAL ARAGUAIA | S24: APARECIDA DE GOIANIA | T24: GO | U24: 74981331 | V24: 62 | W24: 999943525 | X24: Celular | Y24: 62 | Z24: 30859900 | AA24: Fixo | AK24: OSVALDO ANTONIO PAGNUNSSAT ZILLI | AL24: SOCIO ADMINISTRADOR | AM24: 62 | AN24: 984259022 | AO24: VALDIRENE MARIA BEVILAQUA ZILLI | AP24: SOCIO | AQ24: 62 | AR24: 982386633 | AW24: 4511101-Comércio a varejo de automóveis, camionetas e utilitários novos\4511102-Comércio a varejo de automóveis, camionetas e utilitários usados\4511103-Comércio por atacado de automóveis, camionetas e utilitários novos e usados\4511104-Comércio por atacado de caminhões novos e usados\4511105-Comércio por atacado de reboques e semireboques novos e usados\4511106-Comércio por atacado de ônibus e micro-ônibus novos e usados\4512902-Comércio sob consignação de veículos automotores\4661300-Comércio atacadista de máquinas, aparelhos e equipamentos para uso agropecuário, partes e peças\4930201-Transporte rodoviário de carga, exceto produtos perigosos e mudanças, municipal\5211701-Armazéns gerais - emissão de warrant\5211799-Depósitos de mercadorias para terceiros, exceto armazéns gerais e guarda-móveis\5212500-Carga e descarga\5223100-Estacionamento de veículos\5250804-Organização logística do transporte de carga | AX24: 252000137 | AY24: N
A25: 75.813.923/0001-61 | B25: MAGNABOSCO COMERCIO E TRANSPORTES LTDA | C25: TRANS MAGNABOSCO | D25: GRANDE | E25: 211674558 | F25: 158716438 | G25: 498 | H25: 666 | I25: RISCO BAIXO | J25: ATIVA | K25: 4930202 | L25: Transporte rodoviário de carga, exceto produtos perigosos e mudanças, intermunicipal, interestadual e internacional | M25: 3/10/1981 | N25: 10 | O25: SEVERIANO GUERREIRO | P25: 1238 | Q25: R SEVERIANO GUER | R25: CIDADE JARDIM | S25: CATANDUVAS | T25: SC | U25: 89670000 | V25: 49 | W25: 999600033 | X25: Celular | Y25: 49 | Z25: 991611039 | AA25: Celular | AB25: 49 | AC25: 991013927 | AD25: Celular | AE25: 49 | AF25: 35251194 | AG25: Fixo | AH25: CONTASAPAGAR@TRANSMAGNABOSCO.COM.BR | AI25: ALVARO@TRANSMAGNABOSCO.COM.BR | AJ25: ANA@TRANSMAGNABOSCO.COM.BR | AK25: CLODOMAR LUIZ MAGNABOSCO | AL25: ADMINISTRADOR | AM25: 49 | AN25: 999548274 | AO25: MAGNABOSCO PARTICIPACOES LTDA | AP25: SOCIO | AQ25: 49 | AR25: 35251194 | AS25: GUILHERME BORDIN MAGNABOSCO | AT25: ADMINISTRADOR | AU25: 43 | AV25: 998251964 | AW25: 2930101-Fabricação de cabines, carrocerias e reboques para caminhões\4520005-Serviços de lavagem, lubrificação e polimento de veículos automotores\4731800-Comércio varejista de combustíveis para veículos automotores\4929902-Transporte rodoviário coletivo de passageiros, sob regime de fretamento, intermunicipal, interestadual e internacional\4930201-Transporte rodoviário de carga, exceto produtos perigosos e mudanças, municipal\4930203-Transporte rodoviário de produtos perigosos\5212500-Carga e descarga\ | AX25: 250807190 | AY25: N
A26: 03.052.564/0001-66 | B26: TRANS KOTHE TRANSPORTES RODOVIARIOS S/A | C26: KOTHE TRANSPORTES E LOGISTICA | D26: GRANDE | E26: 204078377 | F26: 217622008 | G26: 189 | H26: 913 | I26: RISCO MUITO BAIXO | J26: ATIVA | K26: 4930202 | L26: Transporte rodoviário de carga, exceto produtos perigosos e mudanças, intermunicipal, interestadual e internacional | M26: 3/23/1999 | N26: 22 | O26: JOSE CAPRETZ | P26: 320 | R26: LOTEAMENTO PARQUE INDUSTRIAL | S26: JUNDIAI | T26: SP | U26: 13213095 | V26: 94 | W26: 981691441 | X26: Celular | Y26: 98 | Z26: 981197210 | AA26: Celular | AB26: 94 | AC26: 981694004 | AD26: Celular | AE26: 11 | AF26: 45252629 | AG26: Fixo | AH26: ADILSONTONIELO@KOTHE.COM.BR | AI26: ADIR@KOTHE.COM.BR | AJ26: ADRIANO.GRANDO@KOTHE.COM.BR | AK26: ARLETE KOTHE | AL26: DIRETOR | AM26: 63 | AN26: 992380170 | AO26: ADIR PEDRO KOTHE | AP26: PRESIDENTE | AQ26: 63 | AR26: 992368300 | AS26: ADEMIR KOTHE | AT26: PRESIDENTE | AU26: 11 | AV26: 994612991 | AW26: 4930201-Transporte rodoviário de carga, exceto produtos perigosos e mudanças, municipal\4930203-Transporte rodoviário de produtos perigosos\5211799-Depósitos de mercadorias para terceiros, exceto armazéns gerais e guarda-móveis\5250804-Organização logística do transporte de carga\6463800-Outras sociedades de participação, exceto holdings\ | AX26: 407.578.172.117 | AY26: N
A27: 75.862.821/0001-36 | B27: RODALOG SOLUCOES EM LOGISTICA E TRANSPORTE LTDA | C27: RODALOG | D27: GRANDE | E27: 200838976 | F27: 4000000 | G27: 59 | H27: 492 | I27: RISCO MÉDIO | J27: ATIVA | K27: 4930202 | L27: Transporte rodoviário de carga, exceto produtos perigosos e mudanças, intermunicipal, interestadual e internacional | M27: 3/24/1982 | N27: 10 | O27: ARY SCHOSSLAND | P27: 49 | R27: ANITA GARIBALDI | S27: JOINVILLE | T27: SC | U27: 89202066 | V27: 48 | W27: 991880471 | X27: Celular | Y27: 47 | Z27: 992120267 | AA27: Celular | AB27: 47 | AC27: 992774566 | AD27: Celular | AE27: 47 | AF27: 32786750 | AG27: Fixo | AH27: TRIBUTARIO@RODALOG.COM.BR | AI27: AVILA@RODALOG.COM.BR | AJ27: DEISI.CATARINA@RODALOG.COM.BR | AK27: AUSTERITA PARTICIPACOES LTDA | AL27: SOCIO | AM27: 47 | AN27: 999892622 | AO27: STEFAN RODRIGO SOARES E BOGO | AP27: ADMINISTRADOR | AQ27: 47 | AR27: 999717870 | AW27: 4930201-Transporte rodoviário de carga, exceto produtos perigosos e mudanças, municipal\5211701-Armazéns gerais - emissão de warrant\5211799-Depósitos de mercadorias para terceiros, exceto armazéns gerais e guarda-móveis\5212500-Carga e descarga\5250803-Agenciamento de cargas, exceto para o transporte marítimo\5250804-Organização logística do transporte de carga\5320202-Serviços de entrega rápida\6462000-Holdings de instituições não financeiras\7711000-Locação de automóveis sem condutor\7820500-Locação de mão de obra temporária\7911200-Agências de viagens\8211300-Serviços combinados de escritório e apoio administrativo | AX27: 251798402 | AY27: N
A28: 07.520.001/0001-06 | B28: CARRER ALIMENTOS LTDA EM RECUPERACAO JUDICIAL | D28: GRANDE | E28: 193666534 | F28: 83000000 | G28: 103 | H28: 585 | I28: RISCO BAIXO | J28: ATIVA | K28: 1013901 | L28: Fabricação de produtos de carne | M28: 7/19/2005 | N28: 6 | O28: RSC 453 | Q28: KM 77 DO LADO DA C DE VINHOS | S28: BOA VISTA DO SUL | T28: RS | U28: 95727000 | V28: 51 | W28: 980149662 | X28: Celular | Y28: 54 | Z28: 999215082 | AA28: Celular | AB28: 54 | AC28: 34355426 | AD28: Fixo | AH28: KATIANE@AVICOLACARRER.COM.BR | AK28: HOLDINVEST FOODS S.A. EM RECUPERACAO JUDICIAL | AL28: SOCIO | AM28: 54 | AN28: 30567600 | AO28: GERALDO CARRER | AP28: SOCIO ADMINISTRADOR | AQ28: 54 | AR28: 999943760 | AS28: BRUNO KUMMEL CARRER | AT28: ADMINISTRADOR | AW28: 0155502-Produção de pintos de um dia\0155504-Criação de aves, exceto galináceos\0155505-Produção de ovos\1012101-Abate de aves\1052000-Fabricação de laticínios\1099699-Fabricação de outros produtos alimentícios não especificados anteriormente\4633802-Comércio atacadista de aves vivas e ovos\4634601-Comércio atacadista de carnes bovinas e suínas e derivados\4634602-Comércio atacadista de aves abatidas e derivados\4729699-Comércio varejista de produtos alimentícios em geral ou especializado em produtos alimentícios não especificados anteriormente\4930201-Transporte rodoviário de carga, exceto produtos perigosos e mudanças, municipal\4930202-Transporte rodoviário de carga, exceto produtos perigosos e mudanças, intermunicipal, interestadual e internacional\5211701-Armazéns gerais - emissão de warrant\6810202-Aluguel de imóveis próprios | AX28: 037/0039912 | AY28: N
A29: 22.067.862/0001-74 | B29: CESA S.A. | C29: CESA LOGISTICA | D29: GRANDE | E29: 190665833 | F29: 1000 | H29: 584 | I29: RISCO BAIXO | J29: ATIVA | K29: 4930202 | L29: Transporte rodoviário de carga, exceto produtos perigosos e mudanças, intermunicipal, interestadual e internacional | M29: 10/14/1970 | N29: 1 | O29: DO CONTORNO | P29: 3542 | Q29: SALA 503 | R29: SANTA EFIGENIA | S29: BELO HORIZONTE | T29: MG | U29: 30110018 | V29: 31 | W29: 971031917 | X29: Celular | Y29: 31 | Z29: 997946719 | AA29: Celular | AB29: 31 | AC29: 995203522 | AD29: Celular | AE29: 31 | AF29: 36633500 | AG29: Fixo | AH29: ELDER.CABRAL@CESA.COM.BR | AI29: CESAFISCAL@CESA.COM.BR | AK29: GUSTAVO DIAS | AL29: PRESIDENTE | AM29: 31 | AN29: 999796633 | AO29: MARCELO DIAS | AP29: DIRETOR | AQ29: 31 | AR29: 981159785 | AW29: 4930201-Transporte rodoviário de carga, exceto produtos perigosos e mudanças, municipal\7719599-Locação de outros meios de transporte não especificados anteriormente, sem condutor | AX29: 186030422.00-62 | AY29: S
A30: 78.807.427/0001-93 | B30: COSTA TEIXEIRA TRANSPORTES LTDA | D30: GRANDE | E30: 184223750 | F30: 60000000 | G30: 452 | H30: 449 | I30: RISCO MÉDIO | J30: ATIVA | K30: 4930202 | L30: Transporte rodoviário de carga, exceto produtos perigosos e mudanças, intermunicipal, interestadual e internacional | M30: 7/26/1985 | N30: 13 | O30: BR-376 | Q30: KM499 | R30: COLONIA DONA LUIZA | S30: PONTA GROSSA | T30: PR | U30: 84043450 | V30: 11 | W30: 998740738 | X30: Celular | Y30: 42 | Z30: 40097100 | AA30: Fixo | AH30: NOTAFISCAL@COSTATEIXEIRA.COM.BR | AI30: CLAUDIO.TEIXEIRA@COSTATEIXEIRA.COM.BR | AJ30: CLAUDIO@COSTATEIXEIRA.COM.BR | AK30: CLAUDIO JOSE COSTA TEIXEIRA | AL30: SOCIO ADMINISTRADOR | AM30: 42 | AN30: 999142042 | AO30: GILBERTO LEANDRO COSTA TEIXEIRA | AP30: SOCIO ADMINISTRADOR | AQ30: 41 | AR30: 996195199 | AS30: GILMAR TADEU COSTA TEIXEIRA | AT30: SOCIO ADMINISTRADOR | AU30: 22 | AV30: 981211052 | AW30: 4930201-Transporte rodoviário de carga, exceto produtos perigosos e mudanças, municipal\4930203-Transporte rodoviário de produtos perigosos\5211701-Armazéns gerais - emissão de warrant\5212500-Carga e descarga\5229099-Outras atividades auxiliares dos transportes terrestres não especificadas anteriormente\ | AX30: 20110644-37 | AY30: N
A31: 16.127.441/0001-99 | B31: AVIGRO AVICOLA AGROINDUSTRIAL LTDA | C31: AVIGRO | D31: MÉDIA | E31: 175923925 | F31: 4494000 | G31: 482 | H31: 532 | I31: RISCO BAIXO | J31: ATIVA | K31: 1012101 | L31: Abate de aves | M31: 6/4/1987 | N31: 0 | O31: VILA DOS COQUEIROS | P31: 520 | R31: CENTRO | S31: CONCEICAO DA FEIRA | T31: BA | U31: 44320000 | V31: 75 | W31: 998015976 | X31: Celular | Y31: 75 | Z31: 999416201 | AA31: Celular | AB31: 75 | AC31: 998785571 | AD31: Celular | AE31: 75 | AF31: 32443500 | AG31: Fixo | AH31: GERCONTROLADORIA@AVIGRO.COM.BR | AI31: MARCOS@AVIGRO.COM.BR | AJ31: CLAUDIO@AVIGRO.COM.BR | AK31: MARIA ANTONIA MASCARENHAS ALVES | AL31: SOCIO | AM31: 75 | AN31: 999942024 | AO31: OLINTO PEREIRA ALVES | AP31: SOCIO ADMINISTRADOR | AQ31: 75 | AR31: 981654048 | AS31: LOURIVAL CHAGAS DO NASCIMENTO | AT31: SOCIO | AU31: 75 | AV31: 998038656 | AW31: 0155501-Criação de frangos para corte\0155502-Produção de pintos de um dia\1066000-Fabricação de alimentos para animais\4634601-Comércio atacadista de carnes bovinas e suínas e derivados\4634602-Comércio atacadista de aves abatidas e derivados\4712100-Comércio varejista de mercadorias em geral, com predominância de produtos alimentícios - minimercados, mercearias e armazéns\4722901-Comércio varejista de carnes - açougues\4729602-Comércio varejista de mercadorias em lojas de conveniência\4729699-Comércio varejista de produtos alimentícios em geral ou especializado em produtos alimentícios não especificados anteriormente\4930202-Transporte rodoviário de carga, exceto produtos perigosos e mudanças, intermunicipal, interestadual e internacional | AX31: 026.152.167 | AY31: N
A32: 60.678.471/0001-85 | B32: LEPE INDUSTRIA E COMERCIO LTDA | D32: MÉDIA | E32: 172951394 | F32: 3100000 | G32: 411 | H32: 902 | I32: RISCO MUITO BAIXO | J32: ATIVA | K32: 2451200 | L32: Fundição de ferro e aço | M32: 10/6/1966 | N32: 0 | O32: LUIS RODRIGUES DE FREITAS | P32: 597 | R32: VILA ROSA MINELIA | S32: GUARULHOS | T32: SP | U32: 7034050 | V32: 11 | W32: 964757070 | X32: Celular | Y32: 11 | Z32: 974180268 | AA32: Celular | AB32: 11 | AC32: 942952223 | AD32: Celular | AE32: 11 | AF32: 24757091 | AG32: Fixo | AH32: CONTABIL@LEPE.COM.BR | AI32: COMPRAS@LEPE.COM.BR | AJ32: ACK@LEPE.COM.BR | AK32: ANTONIO CARLOS KOCH | AL32: SOCIO ADMINISTRADOR | AM32: 11 | AN32: 969764256 | AO32: AUGUSTO KOCH JUNIOR | AP32: SOCIO ADMINISTRADOR | AQ32: 11 | AR32: 978156406 | AS32: LUIZ CARLOS KOCH | AT32: SOCIO ADMINISTRADOR | AU32: 11 | AV32: 999826475 | AX32: 336.066.110.115 | AY32: N
A33: 03.875.931/0001-21 | B33: NEPOMUCENO CARGAS LTDA. | C33: NEPOMUCENO LOGISTICA | D33: GRANDE | E33: 162598033 | F33: 45351208 | G33: 181 | H33: 576 | I33: RISCO BAIXO | J33: ATIVA | K33: 4930202 | L33: Transporte rodoviário de carga, exceto produtos perigosos e mudanças, intermunicipal, interestadual e internacional | M33: 6/9/2000 | N33: 8 | O33: DOM GABRIEL PAULINO BUENO COUTO | P33: 500 | Q33: SALA 4 PREDIO A | R33: MEDEIROS | S33: JUNDIAI | T33: SP | U33: 13212240 | V33: 35 | W33: 36949837 | X33: Fixo | AH33: NEPOMUCENOCARGASLTDA@GMAIL.COM | AI33: CPEDROSO@EXPRESSONEPOMUCENO.COM.BR | AJ33: ADRIANOCARDOSO@EXPRESSONEPOMUCENO.COM.BR | AK33: EXPRESSO NEPOMUCENO S/A | AL33: SOCIO | AM33: 35 | AN33: 998164753 | AO33: AGNALDO DE SOUZA FILHO | AP33: ADMINISTRADOR | AQ33: 35 | AR33: 988577625 | AS33: AGNESIO CARVALHO DE SOUZA NETO | AT33: ADMINISTRADOR | AU33: 35 | AV33: 988328195 | AW33: 4520001-Serviços de manutenção e reparação mecânica de veículos automotores\4930201-Transporte rodoviário de carga, exceto produtos perigosos e mudanças, municipal\4930203-Transporte rodoviário de produtos perigosos\5211799-Depósitos de mercadorias para terceiros, exceto armazéns gerais e guarda-móveis\5212500-Carga e descarga\5250804-Organização logística do transporte de carga\5320202-Serviços de entrega rápida\6810202-Aluguel de imóveis próprios\7711000-Locação de automóveis sem condutor\7719599-Locação de outros meios de transporte não especificados anteriormente, sem condutor\7739099-Aluguel de outras máquinas e equipamentos comerciais e industriais não especificados anteriormente, sem operador\7820500-Locação de mão de obra temporária | AX33: 407.744.676.118 | AY33: N
A34: 06.292.402/0001-93 | B34: BRAMETAL MG METALURGICA LTDA | C34: BRAMETAL MG | D34: MÉDIA | E34: 161477780 | F34: 37400000 | G34: 5 | H34: 588 | I34: RISCO BAIXO | J34: ATIVA | K34: 2511000 | L34: Fabricação de estruturas metálicas | M34: 6/4/2004 | N34: 0 | O34: DO CONTORNO 2905 | P34: 2905 | Q34: ANDAR 4 | R34: SANTA EFIGENIA | S34: BELO HORIZONTE | T34: MG | U34: 30110915 | V34: 31 | W34: 971263708 | X34: Celular | Y34: 31 | Z34: 999637354 | AA34: Celular | AB34: 31 | AC34: 995190762 | AD34: Celular | AE34: 27 | AF34: 21039051 | AG34: Fixo | AH34: CONTROLADORIA@BRAMETAL.COM.BR | AI34: CINTIA@BRAMETAL.COM.BR | AJ34: ADRIANA.SMARSARO@BRAMETAL.COM.BR | AK34: HOLLMORE PARTICIPACOES E INVESTIMENTOS LTDA | AL34: SOCIO | AO34: RICARDO MINATTO BRANDAO | AP34: SOCIO | AQ34: 48 | AR34: 991716600 | AS34: ALEXANDRE QUEIROZ SCHMIDT | AT34: ADMINISTRADOR | AU34: 27 | AV34: 988004321 | AW34: 2330302-Fabricação de artefatos de cimento para uso na construção\2539001-Serviços de usinagem, torneiria e solda\2539002-Serviços de tratamento e revestimento em metais\4110700-Incorporação de empreendimentos imobiliários\4292801-Montagem de estruturas metálicas\4292802-Obras de montagem industrial\4689399-Comércio atacadista especializado em outros produtos intermediários não especificados anteriormente\4744005-Comércio varejista de materiais de construção não especificados anteriormente\4744099-Comércio varejista de materiais de construção em geral\7112000-Serviços de engenharia | AX34: 567295995.00-09 | AY34: N
A35: 04.662.776/0001-28 | B35: CAJURU INDUSTRIA E COMERCIO DE ALIMENTOS LTDA EM RECUPERACAO JUDICIAL | D35: MÉDIA | E35: 157755862 | F35: 4400000 | G35: 108 | H35: 577 | I35: RISCO BAIXO | J35: ATIVA | K35: 1013901 | L35: Fabricação de produtos de carne | M35: 9/14/2001 | N35: 0 | O35: JONAS JACOB SANTANA | P35: 85 | Q35: 16 3667 9000 PRQ INDUS | R35: DIST INDUSTRIAL I | S35: CAJURU | T35: SP | U35: 14240000 | V35: 16 | W35: 991323616 | X35: Celular | Y35: 16 | Z35: 993208861 | AA35: Celular | AB35: 16 | AC35: 991425829 | AD35: Celular | AE35: 16 | AF35: 36679000 | AG35: Fixo | AH35: GOLDMEAT@GOLDMEAT.COM.BR | AK35: JOSE PAULO CANDIDO JUNIOR | AL35: SOCIO ADMINISTRADOR | AM35: 16 | AN35: 991160012 | AO35: SILVIA MARIA LOPES DA SILVA CARDINALI CANDIDO | AP35: SOCIO ADMINISTRADOR | AQ35: 16 | AR35: 997941231 | AW35: 4619200-Representantes comerciais e agentes do comércio de mercadorias em geral não especializado\4631100-Comércio atacadista de leite e laticínios\4634601-Comércio atacadista de carnes bovinas e suínas e derivados\4634602-Comércio atacadista de aves abatidas e derivados\4634603-Comércio atacadista de pescados e frutos do mar\4637199-Comércio atacadista especializado em outros produtos alimentícios não especificados anteriormente\4642702-Comércio atacadista de roupas e acessórios para uso profissional e de segurança do trabalho\4721103-Comércio varejista de laticínios e frios | AX35: 243.065.620.112 | AY35: S
A36: 11.270.328/0001-44 | B36: BOVMEAT PROCESSADORA DE CARNES E DERIVADOS LTDA. | C36: BOVMEAT CARNES | D36: MÉDIA | E36: 152021534 | F36: 3020000 | G36: 269 | H36: 875 | I36: RISCO MUITO BAIXO | J36: ATIVA | K36: 1013901 | L36: Fabricação de produtos de carne | M36: 7/31/2009 | N36: 1 | O36: PRACA BERNARDINO DE CAMPOS 184 | Q36: GALPAOINDUSTRIAL | R36: CENTRO | S36: ITAPIRA | T36: SP | U36: 13970970 | V36: 19 | W36: 992079256 | X36: Celular | Y36: 19 | Z36: 989788982 | AA36: Celular | AB36: 19 | AC36: 992945469 | AD36: Celular | AE36: 19 | AF36: 38632354 | AG36: Fixo | AH36: ALESSANDROALMEIDA@BOVMEAT.COM.BR | AI36: ALEX@BOVMEAT.COM.BR | AJ36: DELSON@BOVMEAT.COM.BR | AK36: ALESSANDRO SAMPAIO DE ALMEIDA | AL36: SOCIO ADMINISTRADOR | AM36: 19 | AN36: 992945509 | AO36: PATRICIA PEREIRA SOARES DE ALMEIDA | AP36: SOCIO ADMINISTRADOR | AQ36: 19 | AR36: 992945509 | AW36: 4617600-Representantes comerciais e agentes do comércio de produtos alimentícios, bebidas e fumo\4631100-Comércio atacadista de leite e laticínios\4637199-Comércio atacadista especializado em outros produtos alimentícios não especificados anteriormente\4691500-Comércio atacadista de mercadorias em geral, com predominância de produtos alimentícios | AX36: 374.136.362.111 | AY36: N
A37: 36.492.502/0001-24 | B37: CHARQUE 500 INDUSTRIA E COMERCIO LTDA | D37: MÉDIA | E37: 149507150 | F37: 918000 | G37: 225 | H37: 504 | I37: RISCO BAIXO | J37: ATIVA | K37: 1013901 | L37: Fabricação de produtos de carne | M37: 4/25/1991 | N37: 2 | O37: JOAQUIM EUGENIO SANTOS | P37: 500 | R37: CENTRO | S37: MARICA | T37: RJ | U37: 24901040 | V37: 21 | W37: 990118593 | X37: Celular | Y37: 21 | Z37: 983680122 | AA37: Celular | AB37: 21 | AC37: 983680175 | AD37: Celular | AE37: 21 | AF37: 26372326 | AG37: Fixo | AH37: CLEIDI@CHARQUE500.COM.BR | AI37: CARLOS@CHARQUE500.COM.BR | AJ37: CATIA@CHARQUE500.COM.BR | AK37: WALTER ROBERTO COLAVITTI | AL37: SOCIO ADMINISTRADOR | AM37: 21 | AN37: 988302326 | AO37: CLEIDI DA SILVA ABREU | AP37: SOCIO | AQ37: 21 | AR37: 979258911 | AW37: 4639702-Comércio atacadista de produtos alimentícios em geral, com atividade de fracionamento e acondicionamento associada\4721103-Comércio varejista de laticínios e frios\4722901-Comércio varejista de carnes - açougues\4930202-Transporte rodoviário de carga, exceto produtos perigosos e mudanças, intermunicipal, interestadual e internacional\8292000-Envasamento e empacotamento sob contrato\ | AX37: 84.000.418 | AY37: S
A38: 03.836.990/0001-90 | B38: CPA ARMAZENS GERAIS LTDA | D38: MÉDIA | E38: 144050393 | F38: 75225608 | G38: 26 | H38: 775 | I38: RISCO MUITO BAIXO | J38: ATIVA | K38: 5211701 | L38: Armazéns gerais - emissão de warrant | M38: 5/25/2000 | N38: 1 | O38: CASTELO BRANCO | P38: 800 | Q38: SALA02LOTE199 A | R38: VERA CRUZ | S38: SARANDI | T38: PR | U38: 87111760 | V38: 44 | W38: 991621621 | X38: Celular | Y38: 44 | Z38: 991341846 | AA38: Celular | AB38: 44 | AC38: 991169613 | AD38: Celular | AE38: 44 | AF38: 32888001 | AG38: Fixo | AH38: GILBERTO@CPATRADING.COM.BR | AK38: PAULO MENEGUETTI | AL38: ADMINISTRADOR | AM38: 44 | AN38: 999821982 | AO38: CPA HOLDING PARTICIPACOES S.A. | AP38: SOCIO | AQ38: 44 | AR38: 32888000 | AS38: AYRTON CARLOS BERG JUNIOR | AT38: ADMINISTRADOR | AU38: 44 | AV38: 999645015 | AW38: 3315500-Manutenção e reparação de veículos ferroviários\4619200-Representantes comerciais e agentes do comércio de mercadorias em geral não especializado\5231102-Atividades do Operador Portuário\5250802-Atividades de despachantes aduaneiros\5250804-Organização logística do transporte de carga\8211300-Serviços combinados de escritório e apoio administrativo | AY38: N
A39: 60.746.518/0001-09 | B39: TRANSPORTADORA TRANSLECCHI LTDA | C39: TRANSLECCHI | D39: GRANDE | E39: 135876829 | F39: 7355820 | H39: 703 | I39: RISCO MUITO BAIXO | J39: ATIVA | K39: 4930202 | L39: Transporte rodoviário de carga, exceto produtos perigosos e mudanças, intermunicipal, interestadual e internacional | M39: 6/7/1989 | N39: 5 | O39: PAULISTA | P39: 1636 | Q39: CONJ8 PAV 13 | R39: BELA VISTA | S39: SAO PAULO | T39: SP | U39: 01310200 | V39: 11 | W39: 999771076 | X39: Celular | Y39: 11 | Z39: 47904790 | AA39: Fixo | AH39: CLAUDENIR.MENDES@TRANSLECCHI.COM.BR | AI39: WEBMASTER@TRANSLECCHI.COM.BR | AJ39: WAGNER.DIAS@TRANSLECCHI.COM.BR | AK39: ROBERTO GIUSEPPE MONGUZZI | AL39: SOCIO ADMINISTRADOR | AM39: 11 | AN39: 999771076 | AO39: ALDO ERNESTO MONGUZZI | AP39: SOCIO ADMINISTRADOR | AQ39: 62 | AR39: 995027871 | AW39: 5212500-Carga e descarga\5250804-Organização logística do transporte de carga\7739099-Aluguel de outras máquinas e equipamentos comerciais e industriais não especificados anteriormente, sem operador\ | AX39: 140.798.820.111 | AY39: N
A40: 08.247.312/0001-06 | B40: TECER - TERMINAIS PORTUARIOS CEARA LTDA | D40: MÉDIA | E40: 132943988 | F40: 1300000 | G40: 471 | H40: 533 | I40: RISCO BAIXO | J40: ATIVA | K40: 5231102 | L40: Atividades do Operador Portuário | M40: 7/26/2006 | N40: 2 | O40: S LUIS | P40: 671 | R40: CENTRO | S40: PECEM | T40: CE | U40: 62674000 | V40: 85 | W40: 981744236 | X40: Celular | Y40: 85 | Z40: 981243183 | AA40: Celular | AB40: 85 | AC40: 981769949 | AD40: Celular | AE40: 85 | AF40: 33151415 | AG40: Fixo | AH40: CONTABILIDADE@TECERTERMINAIS.COM.BR | AK40: BERTRAND ALPHONSE BORIS NETO | AL40: ADMINISTRADOR | AM40: 85 | AN40: 999812988 | AO40: TERMACO PARTICIPACOES S.A. | AP40: SOCIO | AQ40: 85 | AR40: 33885600 | AS40: TOME PARTICIPACOES LTDA (EM RECUPERACAO JUDICIAL) | AT40: SOCIO | AU40: 11 | AV40: 43556254 | AW40: 4520001-Serviços de manutenção e reparação mecânica de veículos automotores\4520002-Serviços de lanternagem ou funilaria e pintura de veículos automotores\4520005-Serviços de lavagem, lubrificação e polimento de veículos automotores\4520006-Serviços de borracharia para veículos automotores\5212500-Carga e descarga\5231101-Administração da infraestrutura portuária\5250804-Organização logística do transporte de carga\7739099-Aluguel de outras máquinas e equipamentos comerciais e industriais não especificados anteriormente, sem operador | AX40: 06.199520-7 | AY40: N
A41: 06.106.950/0001-81 | B41: YUSEN LOGISTICS DO BRASIL LTDA. | C41: YUSEN LOGISTICS DO BRASIL | D41: GRANDE | E41: 128261120 | F41: 66664900 | G41: 127 | H41: 489 | I41: RISCO MÉDIO | J41: ATIVA | K41: 5211701 | L41: Armazéns gerais - emissão de warrant | M41: 12/16/2003 | N41: 17 | O41: ANHANGUERA KM 15 | Q41: GALPAO1 PARTE E 2 | R41: VILA JAGUARA | S41: SAO PAULO | T41: SP | U41: 5113902 | V41: 11 | W41: 972679882 | X41: Celular | Y41: 11 | Z41: 974911741 | AA41: Celular | AB41: 11 | AC41: 934720135 | AD41: Celular | AE41: 11 | AF41: 39089700 | AG41: Fixo | AH41: YLBR.FISCAL@BR.YUSEN-LOGISTICS.COM | AI41: ADRIANA.ROVIGATTI@BR.YUSEN-LOGISTICS.COM | AJ41: MARGARIDA.PLACIDIO@BR.YUSEN-LOGISTICS.COM | AK41: YUSEN LOGISTICS CO., LTDA | AL41: SOCIO PESSOA JURIDICA DOMICILIADO NO EXTERIOR | AO41: EDSON TADAO CHIKU | AP41: ADMINISTRADOR | AQ41: 11 | AR41: 964458842 | AW41: 4930202-Transporte rodoviário de carga, exceto produtos perigosos e mudanças, intermunicipal, interestadual e internacional\5232000-Atividades de agenciamento marítimo\5250802-Atividades de despachantes aduaneiros\5250803-Agenciamento de cargas, exceto para o transporte marítimo\5250804-Organização logística do transporte de carga\5250805-Operador de transporte multimodal - OTM\9512600-Reparação e manutenção de equipamentos de comunicação\ | AX41: 116.765.606.111 | AY41: N
A42: 75.958.926/0001-93 | B42: GHELERE TRANSPORTES LTDA | C42: GHELERE TRANSPORTES | D42: MÉDIA | E42: 122616042 | F42: 34000000 | G42: 183 | H42: 406 | I42: RISCO MÉDIO | J42: ATIVA | K42: 4930202 | L42: Transporte rodoviário de carga, exceto produtos perigosos e mudanças, intermunicipal, interestadual e internacional | M42: 11/30/1981 | N42: 16 | O42: RURAL | Q42: KM 517 | R42: AREA RURAL DE CASCAVEL | S42: CASCAVEL | T42: PR | U42: 85820899 | V42: 45 | W42: 30992000 | X42: Fixo | AH42: NFE@GHELERE.COM.BR | AI42: EDUARDO@GHELERE.COM.BR | AJ42: JACQUELINE@GHELERE.COM.BR | AK42: MARILIANA LUCIA GHELERE | AL42: ADMINISTRADOR | AM42: 45 | AN42: 999461177 | AO42: VILMAR ATILIO GHELERE | AP42: ADMINISTRADOR | AQ42: 13 | AR42: 997813781 | AS42: EAGH ADMINISTRACAO DE BENS E PARTICIPACOES SOCIETARIAS LTDA | AT42: SOCIO | AU42: 45 | AV42: 991350169 | AW42: 2941700-Fabricação de peças e acessórios para o sistema motor de veículos automotores\4511102-Comércio a varejo de automóveis, camionetas e utilitários usados\4520001-Serviços de manutenção e reparação mecânica de veículos automotores\4530703-Comércio a varejo de peças e acessórios novos para veículos automotores\4669999-Comércio atacadista de outras máquinas e equipamentos não especificados anteriormente, partes e peças\4930201-Transporte rodoviário de carga, exceto produtos perigosos e mudanças, municipal\4930203-Transporte rodoviário de produtos perigosos\5211701-Armazéns gerais - emissão de warrant\5211799-Depósitos de mercadorias para terceiros, exceto armazéns gerais e guarda-móveis\5212500-Carga e descarga\5229099-Outras atividades auxiliares dos transportes terrestres não especificadas anteriormente\5250803-Agenciamento de cargas, exceto para o transporte marítimo\5250804-Organização logística do transporte de carga\5250805-Operador de transporte multimodal - OTM\6311900-Tratamento de dados, provedores de serviços de aplicação e serviços de hospedagem na Internet\7719599-Locação de outros meios de transporte não especificados anteriormente, sem condutor | AX42: 42002431-24 | AY42: N
A43: 26.336.941/0001-94 | B43: MVC TRANSPORTE E LOGISTICA S.A | D43: GRANDE | E43: 120004308 | F43: 1000000 | G43: 149 | H43: 899 | I43: RISCO MUITO BAIXO | J43: ATIVA | K43: 4930202 | L43: Transporte rodoviário de carga, exceto produtos perigosos e mudanças, intermunicipal, interestadual e internacional | M43: 1/9/1990 | N43: 21 | O43: AMALIA RODRIGUES DE JESUS | P43: 137 | Q43: C | R43: FELIPE CLAUDIO DE S | S43: PEDRO LEOPOLDO | T43: MG | U43: 33600000 | V43: 31 | W43: 971024813 | X43: Celular | Y43: 31 | Z43: 971024941 | AA43: Celular | AB43: 31 | AC43: 23421000 | AD43: Fixo | AH43: MVCFISCAL@MVCLOGISTICA.COM.BR | AI43: BARBARA.RODRIGUES@MVCLOGISTICA.COM.BR | AJ43: FREDERICO.RIBEIRO@MVCLOGISTICA.COM.BR | AK43: ALMIR PUJONI | AL43: DIRETOR | AM43: 31 | AN43: 995886164 | AO43: FREDERICO DIAS RIBEIRO | AP43: PRESIDENTE | AQ43: 31 | AR43: 991334628 | AW43: 4930201-Transporte rodoviário de carga, exceto produtos perigosos e mudanças, municipal\5211799-Depósitos de mercadorias para terceiros, exceto armazéns gerais e guarda-móveis\5212500-Carga e descarga\7719599-Locação de outros meios de transporte não especificados anteriormente, sem condutor | AX43: 062618321.00-98 | AY43: N
A44: 21.378.906/0001-14 | B44: PORTO SECO SUL DE MINAS LTDA | D44: MÉDIA | E44: 115838526 | F44: 19100000 | G44: 167 | H44: 697 | I44: RISCO BAIXO | J44: ATIVA | K44: 5211701 | L44: Armazéns gerais - emissão de warrant | M44: 7/26/1979 | N44: 3 | O44: CITLOG | P44: 333 | R44: AEROPORTO | S44: VARGINHA | T44: MG | U44: 37031090 | V44: 35 | W44: 998114407 | X44: Celular | Y44: 35 | Z44: 998095977 | AA44: Celular | AB44: 35 | AC44: 998527826 | AD44: Celular | AE44: 35 | AF44: 32191111 | AG44: Fixo | AH44: ERNANE@EXPRINSUL.COM.BR | AI44: LILIANA.BOTELHONOGUEIRAPAIVA@GMAIL.COM | AJ44: CLEBER@UNECOM.COM.BR | AK44: BRENO NOGUEIRA PAIVA | AL44: SOCIO ADMINISTRADOR | AO44: CAMILA NOGUEIRA PAIVA CARDOSO | AP44: SOCIO ADMINISTRADOR | AQ44: 35 | AR44: 998968333 | AS44: MATHEUS NOGUEIRA PAIVA | AT44: SOCIO ADMINISTRADOR | AU44: 35 | AV44: 998236942 | AW44: 4110700-Incorporação de empreendimentos imobiliários\6463800-Outras sociedades de participação, exceto holdings\6810201-Compra e venda de imóveis próprios\6810202-Aluguel de imóveis próprios\7739099-Aluguel de outras máquinas e equipamentos comerciais e industriais não especificados anteriormente, sem operador\8292000-Envasamento e empacotamento sob contrato | AX44: 707280431.00-44 | AY44: N
A45: 04.019.475/0001-80 | B45: FARMA LOGISTICA E ARMAZENS GERAIS LTDA | D45: GRANDE | E45: 114453515 | F45: 26017609 | H45: 681 | I45: RISCO BAIXO | J45: ATIVA | K45: 5211701 | L45: Armazéns gerais - emissão de warrant | M45: 8/31/2000 | N45: 6 | O45: PORTUGAL | P45: 1.100 | Q45: ARMZ PARTE A 2 | R45: ITAQUI | S45: ITAPEVI | T45: SP | U45: 6696060 | V45: 11 | W45: 995739256 | X45: Celular | Y45: 11 | Z45: 976528623 | AA45: Celular | AB45: 11 | AC45: 991269633 | AD45: Celular | AE45: 11 | AF45: 47724200 | AG45: Fixo | AH45: PARALEGAL.CORPORATIVO@LUFT.COM.BR | AI45: MICHELI.MARQUES@LUFTEXPRESS.COM.BR | AK45: LUFT PARTICIPACOES S/A | AL45: SOCIO | AM45: 11 | AN45: 47724200 | AO45: LUCIANO LUFT | AP45: SOCIO | AQ45: 11 | AR45: 957441000 | AS45: ADEMAR ELOI LUFT | AT45: SOCIO | AU45: 66 | AV45: 981193286 | AW45: 3701100-Gestão de redes de esgoto\4930202-Transporte rodoviário de carga, exceto produtos perigosos e mudanças, intermunicipal, interestadual e internacional\5211799-Depósitos de mercadorias para terceiros, exceto armazéns gerais e guarda-móveis\5250804-Organização logística do transporte de carga\5250805-Operador de transporte multimodal - OTM\ | AX45: 373.120.115.114 | AY45: N
A46: 74.657.784/0001-61 | B46: CONFINA ALIMENTOS INDUSTRIAL LTDA | C46: CONFINA ALIMENTOS | D46: MÉDIA | E46: 112875539 | F46: 62001444 | G46: 62 | H46: 735 | I46: RISCO MUITO BAIXO | J46: ATIVA | K46: 1012101 | L46: Abate de aves | M46: 4/19/1994 | N46: 1 | O46: STELIO MACHADO LOUREIRO | P46: 220 | R46: STO ANTONIO | S46: POLONI | T46: SP | U46: 15160000 | V46: 17 | W46: 996025677 | X46: Celular | Y46: 17 | Z46: 38197221 | AA46: Fixo | AH46: JOSERICARDO@CONFINAALIMENTOS.COM.BR | AK46: WILSON SOLER | AL46: ADMINISTRADOR | AM46: 17 | AN46: 996091053 | AO46: FRIGORIFICO AVICOLA VOTUPORANGA LTDA | AP46: SOCIO | AQ46: 17 | AR46: 34059505 | AS46: FRANCISCO PIGNATARI | AT46: ADMINISTRADOR | AW46: 0154700-Criação de suínos\0155501-Criação de frangos para corte\0155505-Produção de ovos\1013901-Fabricação de produtos de carne\1013902-Preparação de subprodutos do abate\1066000-Fabricação de alimentos para animais\5211799-Depósitos de mercadorias para terceiros, exceto armazéns gerais e guarda-móveis\ | AX46: 547.003.640.110 | AY46: S
A47: 65.849.838/0001-08 | B47: PENSKE LOGISTICS DO BRASIL LTDA. | D47: GRANDE | E47: 111638228 | F47: 48664333 | G47: 101 | H47: 577 | I47: RISCO BAIXO | J47: ATIVA | K47: 4930202 | L47: Transporte rodoviário de carga, exceto produtos perigosos e mudanças, intermunicipal, interestadual e internacional | M47: 4/29/1991 | N47: 17 | O47: DAS NACOES UNIDAS 11541 | P47: 11541 | Q47: ANDAR 17CONJ172 | R47: BROOKLIN PAULISTA | S47: SAO PAULO | T47: SP | U47: 4578907 | V47: 11 | W47: 998706213 | X47: Celular | Y47: 81 | Z47: 971024235 | AA47: Celular | AB47: 11 | AC47: 964944508 | AD47: Celular | AE47: 11 | AF47: 47892739 | AG47: Fixo | AH47: PLSA.FISCAL@PENSKE.COM.BR | AI47: JULIANA.CARMO@PENSKE.COM | AJ47: PLSA.FISCAL@PENSKE.COM | AK47: PENSKE LOGISTICS LLC | AL47: SOCIO PESSOA JURIDICA DOMICILIADO NO EXTERIOR | AO47: PAULO AUGUSTO MACHADO VIEIRA SARTI | AP47: ADMINISTRADOR | AQ47: 11 | AR47: 979702857 | AS47: OMAR DE SOUZA PASSOS | AT47: ADMINISTRADOR | AU47: 19 | AV47: 997723721 | AW47: 5211701-Armazéns gerais - emissão de warrant\5211799-Depósitos de mercadorias para terceiros, exceto armazéns gerais e guarda-móveis\5212500-Carga e descarga\5229099-Outras atividades auxiliares dos transportes terrestres não especificadas anteriormente\5240199-Atividades auxiliares dos transportes aéreos, exceto operação dos aeroportos e campos de aterrissagem\5250804-Organização logística do transporte de carga\5250805-Operador de transporte multimodal - OTM\6202300-Desenvolvimento e licenciamento de programas de computador customizáveis\6463800-Outras sociedades de participação, exceto holdings\7020400-Atividades de consultoria em gestão empresarial, exceto consultoria técnica específica | AX47: 148.683.720.111 | AY47: N
A48: 10.687.862/0001-98 | B48: I. B. LOGISTICA E TRANSPORTES LTDA | D48: MÉDIA | E48: 109268905 | F48: 103360943 | G48: 242 | H48: 481 | I48: RISCO MÉDIO | J48: ATIVA | K48: 4930202 | L48: Transporte rodoviário de carga, exceto produtos perigosos e mudanças, intermunicipal, interestadual e internacional | M48: 3/12/2009 | N48: 4 | O48: VINTE E SEIS | P48: 1086 | R48: ALEXANDRITA | S48: ITURAMA | T48: MG | U48: 38280000 | V48: 17 | W48: 996533651 | X48: Celular | Y48: 34 | Z48: 999158057 | AA48: Celular | AB48: 17 | AC48: 996564625 | AD48: Celular | AH48: MARREGA.ESCRITORIO@NETSITE.COM.BR | AK48: ANTONIO CARLOS BOLDRIN | AL48: SOCIO ADMINISTRADOR | AM48: 34 | AN48: 996375451 | AO48: RICARDO ADILSON BOLDRIN | AP48: SOCIO ADMINISTRADOR | AQ48: 17 | AR48: 996750087 | AS48: FRANCISCO DONIZETI BOLDRIN | AT48: SOCIO ADMINISTRADOR | AU48: 34 | AV48: 999675057 | AW48: 0113000-Cultivo de cana-de-açúcar\0161001-Serviço de pulverização e controle de pragas agrícolas\0161003-Serviço de preparação de terreno, cultivo e colheita\3319800-Manutenção e reparação de equipamentos e produtos não especificados anteriormente\4930201-Transporte rodoviário de carga, exceto produtos perigosos e mudanças, municipal\7719599-Locação de outros meios de transporte não especificados anteriormente, sem condutor\7731400-Aluguel de máquinas e equipamentos agrícolas sem operador\ | AX48: 001113374.00-22 | AY48: N
A49: 10.818.793/0001-04 | B49: ABATEDORA AVICOLA SANTA VITORIA LTDA | C49: QUALITTI ALIMENTOS | D49: GRANDE | E49: 106303433 | F49: 1000000 | G49: 1 | H49: 933 | I49: RISCO MUITO BAIXO | J49: ATIVA | K49: 1012101 | L49: Abate de aves | M49: 5/13/2009 | N49: 4 | O49: GO 476 | Q49: KM 16 | R49: ZONA RURAL | S49: MORRINHOS | T49: GO | U49: 75650000 | V49: 64 | W49: 999268334 | X49: Celular | Y49: 64 | Z49: 999268257 | AA49: Celular | AB49: 64 | AC49: 999293953 | AD49: Celular | AE49: 64 | AF49: 34174000 | AG49: Fixo | AK49: CESAR ALTOMARI | AL49: SOCIO ADMINISTRADOR | AM49: 64 | AN49: 996421793 | AO49: SYLA ALTOMARI | AP49: ADMINISTRADOR | AQ49: 64 | AR49: 999830687 | AW49: 0111302-Cultivo de milho\0111399-Cultivo de outros cereais não especificados anteriormente\0115600-Cultivo de soja\0155501-Criação de frangos para corte\0155502-Produção de pintos de um dia\1012103-Frigorífico - abate de suínos\1013901-Fabricação de produtos de carne\1013902-Preparação de subprodutos do abate\1041400-Fabricação de óleos vegetais em bruto, exceto óleo de milho\1066000-Fabricação de alimentos para animais\4633802-Comércio atacadista de aves vivas e ovos\4634601-Comércio atacadista de carnes bovinas e suínas e derivados\4634602-Comércio atacadista de aves abatidas e derivados\4639701-Comércio atacadista de produtos alimentícios em geral\5211799-Depósitos de mercadorias para terceiros, exceto armazéns gerais e guarda-móveis\ | AX49: 10.455.984-5 | AY49: N
A50: 03.221.799/0001-34 | B50: MATADOURO E FRIGORIFICO PALADAR LTDA | C50: PALADAR | D50: MÉDIA | E50: 104290286 | F50: 24000000 | G50: 292 | H50: 742 | I50: RISCO MUITO BAIXO | J50: ATIVA | K50: 1013901 | L50: Fabricação de produtos de carne | M50: 5/28/1999 | N50: 3 | O50: BR 381 2 A | Q50: KM 265 | R50: LGA DO PAU | S50: JAGUARACU | T50: MG | U50: 35188000 | V50: 31 | W50: 999762714 | X50: Celular | Y50: 31 | Z50: 975165242 | AA50: Celular | AB50: 31 | AC50: 975226963 | AD50: Celular | AE50: 31 | AF50: 38452066 | AG50: Fixo | AH50: DORIZO@MAKROSISTEMAS.COM.BR | AK50: JOMAR SOUZA ANDRADE | AL50: SOCIO ADMINISTRADOR | AM50: 31 | AN50: 996735211 | AW50: 1013902-Preparação de subprodutos do abate\1066000-Fabricação de alimentos para animais\4631100-Comércio atacadista de leite e laticínios\4634601-Comércio atacadista de carnes bovinas e suínas e derivados\4634602-Comércio atacadista de aves abatidas e derivados\4635402-Comércio atacadista de cerveja, chope e refrigerante\4635499-Comércio atacadista de bebidas não especificadas anteriormente\4669999-Comércio atacadista de outras máquinas e equipamentos não especificados anteriormente, partes e peças\4673700-Comércio atacadista de material elétrico\4711302-Comércio varejista de mercadorias em geral, com predominância de produtos alimentícios - supermercados\4722901-Comércio varejista de carnes - açougues\4729699-Comércio varejista de produtos alimentícios em geral ou especializado em produtos alimentícios não especificados anteriormente\4789001-Comércio varejista de suvenires, bijuterias e artesanatos\5611203-Lanchonetes, casas de chá, de sucos e similares | AX50: 350049369.00-88 | AY50: N
A51: 96.825.575/0001-12 | B51: INTERMARITIMA PORTOS E LOGISTICA S/A | C51: INTER - I | D51: GRANDE | E51: 102308505 | F51: 19679184 | G51: 261 | H51: 899 | I51: RISCO MUITO BAIXO | J51: ATIVA | K51: 5231102 | L51: Atividades do Operador Portuário | M51: 9/3/1993 | N51: 15 | O51: ENGENHEIRO OSCAR PONTES | P51: 000099 | Q51: GALPAOPORTO DE SSA | R51: AGUA DE MENINOS | S51: SALVADOR | T51: BA | U51: 40460130 | V51: 71 | W51: 997289695 | X51: Celular | Y51: 71 | Z51: 996853137 | AA51: Celular | AB51: 71 | AC51: 996903455 | AD51: Celular | AE51: 71 | AF51: 38799717 | AG51: Fixo | AH51: RAILTON@INTERMARITIMA.COM.BR | AI51: ABEL@INTERMARITIMA.COM.BR | AJ51: ALAN.MELO@INTERMARITIMA.COM.BR | AK51: ROBERTO ZITELMANN DE OLIVA | AL51: DIRETOR | AM51: 71 | AN51: 991426214 | AO51: ROBERTO ZITELMANN DE OLIVA JUNIOR | AP51: PRESIDENTE | AQ51: 71 | AR51: 991157898 | AS51: HUMBERTO JOSE FARIAS CAMPOS FILHO | AT51: DIRETOR | AU51: 71 | AV51: 999523151 | AW51: 4930203-Transporte rodoviário de produtos perigosos\5211701-Armazéns gerais - emissão de warrant\5212500-Carga e descarga\5232000-Atividades de agenciamento marítimo | AX51: 038.924.310 | AY51: N

Sheet ADRIANA
A1: Carteira de Prospects — Vendedor 2
A2: Total de empresas: 47 | Porte: GRANDE | Fonte: Base de prospecção
A4: CNPJ | B4: Razão Social | C4: Nome Fantasia | D4: Porte | E4: Faturamento Presumido (R$) | F4: Capital Social (R$) | G4: Qtd. Funcionários | H4: Score | I4: Classificação de Risco | J4: Situação Cadastral | K4: CNAE | L4: Atividade Principal | M4: Data Abertura | N4: Qtd. Filiais | O4: Logradouro | P4: Nº | Q4: Complemento | R4: Bairro | S4: Cidade | T4: UF | U4: CEP | V4: DDD 1 | W4: Telefone 1 | X4: Tipo 1 | Y4: DDD 2 | Z4: Telefone 2 | AA4: Tipo 2 | AB4: DDD 3 | AC4: Telefone 3 | AD4: Tipo 3 | AE4: DDD 4 | AF4: Telefone 4 | AG4: Tipo 4 | AH4: E-mail 1 | AI4: E-mail 2 | AJ4: E-mail 3 | AK4: Sócio 1 | AL4: Cargo Sócio 1 | AM4: DDD Sócio 1 | AN4: Tel. Sócio 1 | AO4: Sócio 2 | AP4: Cargo Sócio 2 | AQ4: DDD Sócio 2 | AR4: Tel. Sócio 2 | AS4: Sócio 3 | AT4: Cargo Sócio 3 | AU4: DDD Sócio 3 | AV4: Tel. Sócio 3 | AW4: CNAEs Secundários | AX4: Inscrição Estadual | AY4: Flag DAU
A5: 61.752.739/0001-44 | B5: PRIETO ALIMENTOS LTDA EM RECUPERACAO JUDICIAL | D5: GRANDE | E5: 468405686 | F5: 3100000 | G5: 313 | H5: 410 | I5: RISCO MÉDIO | J5: ATIVA | K5: 1013901 | L5: Fabricação de produtos de carne | M5: 12/5/1972 | N5: 1 | O5: VEREADOR JOAQUIM PEREIRA BARBOSA | P5: 777 | R5: JORDANESIA (JORDANESIA) | S5: CAJAMAR | T5: SP | U5: 7776450 | V5: 16 | W5: 997669806 | X5: Celular | Y5: 11 | Z5: 950578821 | AA5: Celular | AB5: 19 | AC5: 981818143 | AD5: Celular | AE5: 11 | AF5: 48988106 | AG5: Fixo | AH5: PATRICIA.AVILA@PRIETOALIMENTOS.COM.BR | AI5: NATASHA@FRIGORIFICOPRIETO.COM.BR | AJ5: KEDMA@FRIGORIFICOPRIETO.COM.BR | AK5: MARCO AURELIO DA CRUZ VILLARINO PRIETO | AL5: DIRETOR | AM5: 11 | AN5: 996136190 | AO5: MARCELO DA CRUZ VILLARINO PRIETO | AP5: DIRETOR | AQ5: 19 | AR5: 996135780 | AW5: 4619200-Representantes comerciais e agentes do comércio de mercadorias em geral não especializado\4930202-Transporte rodoviário de carga, exceto produtos perigosos e mudanças, intermunicipal, interestadual e internacional\6821802-Corretagem no aluguel de imóveis\ | AX5: 241.003.423.118 | AY5: N
A6: 52.764.354/0001-06 | B6: TEC VIDRO INDUSTRIA, COMERCIO E SERVICOS TECNICOS S.A. | D6: GRANDE | E6: 431301757 | F6: 5120000 | G6: 19 | H6: 889 | I6: RISCO MUITO BAIXO | J6: ATIVA | K6: 4713002 | L6: Lojas de variedades, exceto lojas de departamentos ou magazines | M6: 7/28/1983 | N6: 1 | O6: VENUS | P6: 582 | Q6: SALA 01 | R6: AMERICAN PARK EMPRESARIAL NR | S6: INDAIATUBA | T6: SP | U6: 13347659 | V6: 11 | W6: 989838293 | X6: Celular | Y6: 11 | Z6: 991020112 | AA6: Celular | AB6: 11 | AC6: 975998936 | AD6: Celular | AE6: 19 | AF6: 39355454 | AG6: Fixo | AH6: TECVIDRO@TECVIDRO.COM.BR | AK6: GERMANO TOLEDO WEGBECHER | AL6: DIRETOR | AO6: VINICIUS NUNES BRAGA | AP6: DIRETOR | AQ6: 11 | AR6: 999661035 | AW6: 8211300-Serviços combinados de escritório e apoio administrativo\ | AX6: 110.941.280.116 | AY6: N
A7: 83.491.985/0001-22 | B7: SECCIONAL BRASIL SA | C7: SECCIONAL | D7: GRANDE | E7: 415840903 | F7: 6597456 | G7: 61 | H7: 913 | I7: RISCO MUITO BAIXO | J7: ATIVA | K7: 2511000 | L7: Fabricação de estruturas metálicas | M7: 7/27/1977 | N7: 0 | O7: JUSCELINO KUBITSCHEK DE OLIVEIRA | P7: 4225 | R7: CIDADE INDUSTRIAL | S7: CURITIBA | T7: PR | U7: 81270200 | V7: 41 | W7: 992694931 | X7: Celular | Y7: 41 | Z7: 33172270 | AA7: Fixo | AB7: 41 | AC7: 995260027 | AD7: Celular | AH7: INFORME@SECCIONAL.COM.BR | AI7: PAULA@SECCIONAL.COM.BR | AJ7: ANA@SECCIONAL.COM.BR | AK7: PAULO EMMANUEL DE ABREU JUNIOR | AL7: PRESIDENTE | AM7: 41 | AN7: 999734968 | AO7: PEDRO GUSTAVO ARAUJO DE ABREU | AP7: DIRETOR | AQ7: 41 | AR7: 999642860 | AS7: ANA CRISTINA ARAUJO DE ABREU MICHELENA | AT7: DIRETOR | AU7: 41 | AV7: 991549262 | AW7: 4292801-Montagem de estruturas metálicas\6462000-Holdings de instituições não financeiras\6810201-Compra e venda de imóveis próprios\6810202-Aluguel de imóveis próprios\7112000-Serviços de engenharia\7210000-Pesquisa e desenvolvimento experimental em ciências físicas e naturais\7739099-Aluguel de outras máquinas e equipamentos comerciais e industriais não especificados anteriormente, sem operador\7740300-Gestão de ativos intangíveis não financeiros | AX7: 10166115-61 | AY7: N
A8: 07.522.140/0001-79 | B8: NITSHORE ENGENHARIA E SERVICOS PORTUARIOS S.A. | D8: GRANDE | E8: 407301183 | F8: 31884406 | G8: 78 | H8: 701 | I8: RISCO MUITO BAIXO | J8: ATIVA | K8: 5231102 | L8: Atividades do Operador Portuário | M8: 8/1/2005 | N8: 1 | O8: FELICIANO SODRE | P8: 215 | Q8: 325 | R8: CENTRO | S8: NITEROI | T8: RJ | U8: 24030012 | V8: 21 | W8: 972202462 | X8: Celular | Y8: 21 | Z8: 999043580 | AA8: Celular | AB8: 21 | AC8: 995192149 | AD8: Celular | AE8: 21 | AF8: 21012250 | AG8: Fixo | AH8: MARIO.BARRETO@NITSHORE.COM.BR | AI8: ANDREA.MONTEIRO@NITSHORE.COM.BR | AJ8: COMPRAS@NITSHORE.COM.BR | AK8: GILSON GONCALVES RIBEIRO JUNIOR | AL8: CONSELHEIRO DE ADMINISTRACAO | AO8: WILSON ROBERTO COUTINHO | AP8: CONSELHEIRO DE ADMINISTRACAO | AW8: 3811400-Coleta de resíduos não perigosos\3812200-Coleta de resíduos perigosos\5211799-Depósitos de mercadorias para terceiros, exceto armazéns gerais e guarda-móveis\5212500-Carga e descarga\5239799-Atividades auxiliares dos transportes aquaviários não especificadas anteriormente\ | AX8: 77.980.326 | AY8: N
A9: 07.464.123/0001-22 | B9: MAFRIAL MATADOURO E FRIGORIFICO LTDA | D9: GRANDE | E9: 390411936 | F9: 200000 | G9: 23 | H9: 266 | I9: RISCO ALTO | J9: ATIVA | K9: 1011201 | L9: Frigorífico - abate de bovinos | M9: 6/10/2005 | N9: 0 | O9: SINVAL RODRIGUES COELHO | P9: 261 | R9: VILA ISA | S9: GOVERNADOR VALADARES | T9: MG | U9: 35044380 | V9: 33 | W9: 991237628 | X9: Celular | Y9: 33 | Z9: 991237508 | AA9: Celular | AB9: 33 | AC9: 991237737 | AD9: Celular | AE9: 33 | AF9: 32788587 | AG9: Fixo | AH9: CICERO.SILVA@MAFRIAL.COM.BR | AI9: JUSCELINO@MAFRIAL.COM.BR | AK9: JUSCELINO FARIA LOPES | AL9: SOCIO ADMINISTRADOR | AM9: 33 | AN9: 999897766 | AW9: 1012103-Frigorífico - abate de suínos\1013901-Fabricação de produtos de carne\1013902-Preparação de subprodutos do abate\4634601-Comércio atacadista de carnes bovinas e suínas e derivados\4722901-Comércio varejista de carnes - açougues\4723700-Comércio varejista de bebidas\4789099-Comércio varejista de outros produtos não especificados anteriormente\ | AX9: 277377294.00-07 | AY9: N
A10: 87.654.547/0001-99 | B10: COESUL-CONSTRUTORA EXTREMO SUL LTDA | D10: GRANDE | E10: 376784096 | F10: 7500000 | G10: 492 | H10: 924 | I10: RISCO MUITO BAIXO | J10: ATIVA | K10: 4930202 | L10: Transporte rodoviário de carga, exceto produtos perigosos e mudanças, intermunicipal, interestadual e internacional | M10: 8/10/1981 | N10: 2 | O10: FERNANDO FERRARI | P10: 5999 | R10: SARANDI | S10: PORTO ALEGRE | T10: RS | U10: 91140600 | V10: 51 | W10: 996384734 | X10: Celular | Y10: 51 | Z10: 997600812 | AA10: Celular | AB10: 51 | AC10: 997708396 | AD10: Celular | AE10: 51 | AF10: 33655533 | AG10: Fixo | AH10: RBOCK@COESUL.COM.BR | AI10: ALDO@COESUL.COM.BR | AJ10: ANGELO@COESUL.COM.BR | AK10: LUCI TERESINHA DA SILVA MOTTOLA | AL10: SOCIO | AO10: ROGERIO DA SILVA MOTTOLA | AP10: SOCIO | AQ10: 51 | AR10: 999555831 | AS10: LUCIANE DA SILVA MOTTOLA | AT10: SOCIO | AU10: 51 | AV10: 999557352 | AW10: 0810099-Extração e britamento de pedras e outros materiais para construção e beneficiamento associado\4110700-Incorporação de empreendimentos imobiliários\4211101-Construção de rodovias e ferrovias\4212000-Construção de obras de arte especiais\4213800-Obras de urbanização - ruas, praças e calçadas\4221902-Construção de estações e redes de distribuição de energia elétrica\4222701-Construção de redes de abastecimento de água, coleta de esgoto e construções correlatas, exceto obras de irrigação\4313400-Obras de terraplenagem\4930203-Transporte rodoviário de produtos perigosos\7112000-Serviços de engenharia | AX10: 165/0121510 | AY10: N
A11: 01.417.701/0001-93 | B11: FRICAL ALIMENTOS S/A | C11: FRICAL ALIMENTOS | D11: GRANDE | E11: 366516625 | F11: 5000000 | G11: 451 | H11: 819 | I11: RISCO MUITO BAIXO | J11: ATIVA | K11: 1011201 | L11: Frigorífico - abate de bovinos | M11: 9/10/1996 | N11: 2 | O11: CORONEL PEDRO MARTINS 137 | R11: CENTRO | S11: CARATINGA | T11: MG | U11: 35300970 | V11: 33 | W11: 998109406 | X11: Celular | Y11: 33 | Z11: 998111831 | AA11: Celular | AB11: 33 | AC11: 998104481 | AD11: Celular | AE11: 33 | AF11: 33227000 | AG11: Fixo | AH11: FRICAL@FRICALALIMENTOS.COM.BR | AI11: ALEXANDRE@FRICALALIMENTOS.COM.BR | AJ11: ANDERSONSALLES@FRICALALIMENTOS.COM.BR | AK11: ROGERIO MIRANDA SALIM | AL11: DIRETOR | AM11: 33 | AN11: 984070662 | AO11: ANTONIO SALIM NETO | AP11: PRESIDENTE | AQ11: 91 | AR11: 992822888 | AW11: 1012103-Frigorífico - abate de suínos\1013901-Fabricação de produtos de carne\1013902-Preparação de subprodutos do abate\4623102-Comércio atacadista de couros, lãs, peles e outros subprodutos não comestíveis de origem animal\4631100-Comércio atacadista de leite e laticínios\4633801-Comércio atacadista de frutas, verduras, raízes, tubérculos, hortaliças e legumes frescos\4634601-Comércio atacadista de carnes bovinas e suínas e derivados\4634602-Comércio atacadista de aves abatidas e derivados\4634603-Comércio atacadista de pescados e frutos do mar\4635401-Comércio atacadista de água mineral\4635402-Comércio atacadista de cerveja, chope e refrigerante\4635499-Comércio atacadista de bebidas não especificadas anteriormente\4637199-Comércio atacadista especializado em outros produtos alimentícios não especificados anteriormente\ | AX11: 134720720.00-15 | AY11: S
A12: 50.220.417/0001-38 | B12: ALUFER S A ESTRUTURAS METALICAS | D12: GRANDE | E12: 349271690 | F12: 16000000 | H12: 864 | I12: RISCO MUITO BAIXO | J12: ATIVA | K12: 2511000 | L12: Fabricação de estruturas metálicas | M12: 12/20/1962 | N12: 2 | O12: GENERAL FURTADO NASCIMENTO | P12: 684 | Q12: 7 AND CJS 71 73 74 | R12: ALTO DE PINHEIROS | S12: SAO PAULO | T12: SP | U12: 5465070 | V12: 11 | W12: 40241004 | X12: Fixo | AH12: ITU@ALUFER.COM.BR | AK12: ROBERTO PALENGA | AL12: DIRETOR | AM12: 11 | AN12: 972034308 | AO12: GUIDO ROMOLO GIOVANNI PALENGA | AP12: DIRETOR | AQ12: 11 | AR12: 978242059 | AS12: MARCIO QUILEZ FERREIRA | AT12: DIRETOR | AU12: 67 | AV12: 991283365 | AW12: 2521700-Fabricação de tanques, reservatórios metálicos e caldeiras para aquecimento central\ | AX12: 116.728.472.118 | AY12: N
A13: 02.092.233/0001-97 | B13: CONCAIS S/A | D13: GRANDE | E13: 333279123 | F13: 4520000 | H13: 927 | I13: RISCO MUITO BAIXO | J13: ATIVA | K13: 5231102 | L13: Atividades do Operador Portuário | M13: 9/4/1997 | N13: 2 | O13: GOMES DE CARVALHO | P13: 1306 | Q13: ANDAR 8 SALA 83 | R13: VILA OLIMPIA | S13: SAO PAULO | T13: SP | U13: 4547005 | V13: 11 | W13: 30488822 | X13: Fixo | AH13: INFORM@CONCAIS.COM.BR | AK13: LUIS ANTONIO FLORIANO | AL13: PRESIDENTE | AM13: 98 | AN13: 984951792 | AO13: LUIS GUSTAVO BATISTA | AP13: DIRETOR | AQ13: 13 | AR13: 997141463 | AX13: 148.301.001.112 | AY13: N
A14: 70.986.302/0001-66 | B14: FRIGORIFICO ATALAIA S/A | C14: ATALAIA ALIMENTOS | D14: GRANDE | E14: 325942078 | F14: 2087000 | G14: 417 | H14: 358 | I14: RISCO MÉDIO | J14: ATIVA | K14: 1012101 | L14: Abate de aves | M14: 3/29/1993 | N14: 4 | O14: DA FABRICA | P14: 10 | R14: R DE BAIXO | S14: PRADOS | T14: MG | U14: 36320000 | V14: 32 | W14: 999382664 | X14: Celular | Y14: 32 | Z14: 998135896 | AA14: Celular | AB14: 32 | AC14: 999747376 | AD14: Celular | AE14: 32 | AF14: 33536482 | AG14: Fixo | AH14: NFSERVICOS@ATALAIAALIMENTOS.IND.BR | AI14: MARCELO.FULLIN@ATALAIAALIMENTOS.IND.BR | AJ14: CLARISSE@ATALAIAALIMENTOS.IND.BR | AK14: MARCELO ANTONIO DAS CHAGAS | AL14: SOCIO ADMINISTRADOR | AM14: 32 | AN14: 999001430 | AO14: CLARISSE DE FATIMA FERREIRA CHAGAS | AP14: SOCIO ADMINISTRADOR | AQ14: 32 | AR14: 999005430 | AW14: 0155501-Criação de frangos para corte\0155502-Produção de pintos de um dia\0155503-Criação de outros galináceos, exceto para corte\0155504-Criação de aves, exceto galináceos\0163600-Atividades de pós-colheita\1013901-Fabricação de produtos de carne\1013902-Preparação de subprodutos do abate\1066000-Fabricação de alimentos para animais\1091101-Fabricação de produtos de panificação industrial\1094500-Fabricação de massas alimentícias\1096100-Fabricação de alimentos e pratos prontos\4623109-Comércio atacadista de alimentos para animais\4623199-Comércio atacadista de matérias-primas agrícolas não especificadas anteriormente\4633802-Comércio atacadista de aves vivas e ovos\4634601-Comércio atacadista de carnes bovinas e suínas e derivados\4634602-Comércio atacadista de aves abatidas e derivados\4634603-Comércio atacadista de pescados e frutos do mar\4634699-Comércio atacadista de carnes e derivados de outros animais\4637105-Comércio atacadista de massas alimentícias\4639701-Comércio atacadista de produtos alimentícios em geral\4729699-Comércio varejista de produtos alimentícios em geral ou especializado em produtos alimentícios não especificados anteriormente\5211701-Armazéns gerais - emissão de warrant\5211799-Depósitos de mercadorias para terceiros, exceto armazéns gerais e guarda-móveis\5212500-Carga e descarga\5250804-Organização logística do transporte de carga\6319400-Portais, provedores de conteúdo e outros serviços de informação na Internet\6463800-Outras sociedades de participação, exceto holdings\7120100-Testes e análises técnicas\8211300-Serviços combinados de escritório e apoio administrativo\8291100-Atividades de cobrança e informações cadastrais | AX14: 527839562.00-07 | AY14: N
A15: 22.651.194/0001-28 | B15: FUNDICAO SIDERAL LTDA | D15: GRANDE | E15: 303171782 | F15: 5000000 | G15: 331 | H15: 701 | I15: RISCO MUITO BAIXO | J15: ATIVA | K15: 2451200 | L15: Fundição de ferro e aço | M15: 3/12/1987 | N15: 1 | O15: MG-431 | P15: SN | Q15: KM 35 5 | R15: VILA TAVARES | S15: ITAUNA | T15: MG | U15: 35680143 | V15: 37 | W15: 998743144 | X15: Celular | Y15: 37 | Z15: 999544918 | AA15: Celular | AB15: 37 | AC15: 999316404 | AD15: Celular | AE15: 37 | AF15: 32494500 | AG15: Fixo | AH15: DANIELSOARES@FUNDICAOSIDERAL.COM.BR | AI15: LOGISTICA@FUNDICAOSIDERAL.COM.BR | AJ15: SUPRIMENTOS@FUNDICAOSIDERAL.COM.BR | AK15: JOSE MAURICIO ANDRADE SOARES | AL15: SOCIO ADMINISTRADOR | AM15: 37 | AN15: 988224736 | AO15: SIDERAL PARTICIPACOES LTDA | AP15: SOCIO | AQ15: 37 | AR15: 32494500 | AS15: DANIEL DE CASTRO ANDRADE SOARES | AT15: ADMINISTRADOR | AU15: 37 | AV15: 998047831 | AW15: 0115600-Cultivo de soja\0210101-Cultivo de eucalipto\2411300-Produção de ferro-gusa\2452100-Fundição de metais não ferrosos e suas ligas\2539001-Serviços de usinagem, torneiria e solda\3831999-Recuperação de materiais metálicos, exceto alumínio | AX15: 338533381.00-32 | AY15: N
A16: 05.367.368/0001-06 | B16: FM MODEL TRANSPORTES LTDA | C16: FM MODEL TRANSPORTES | D16: MÉDIA | E16: 286908483 | F16: 108045908 | G16: 123 | H16: 394 | I16: RISCO MÉDIO | J16: ATIVA | K16: 4930202 | L16: Transporte rodoviário de carga, exceto produtos perigosos e mudanças, intermunicipal, interestadual e internacional | M16: 10/25/2002 | N16: 0 | O16: BARAO DE JAGUARA, 707 | P16: 707 | Q16: SALA 151 | R16: CENTRO | S16: CAMPINAS | T16: SP | U16: 13015926 | V16: 19 | W16: 998670214 | X16: Celular | Y16: 11 | Z16: 952240369 | AA16: Celular | AB16: 11 | AC16: 40981740 | AD16: Fixo | AH16: EXPEDICAO@LHFABER.COM.BE | AK16: FERNANDO BORGES MODEL | AL16: SOCIO ADMINISTRADOR | AM16: 11 | AN16: 994010497 | AW16: 5250803-Agenciamento de cargas, exceto para o transporte marítimo\7732201-Aluguel de máquinas e equipamentos para construção sem operador, exceto andaimes | AX16: 387.251.936.115 | AY16: S
A17: 02.426.290/0001-65 | B17: BIOMEDICAL DISTRIBUTION MERCOSUR LTDA | C17: BOMI BRASIL | D17: GRANDE | E17: 280086450 | F17: 372833830 | H17: 643 | I17: RISCO BAIXO | J17: ATIVA | K17: 5211701 | L17: Armazéns gerais - emissão de warrant | M17: 3/10/1998 | N17: 8 | O17: PORTUGAL | P17: 1100 | Q17: C 26 PARTE | R17: ITAQUI | S17: ITAPEVI | T17: SP | U17: 6696060 | V17: 11 | W17: 985382511 | X17: Celular | Y17: 11 | Z17: 987860210 | AA17: Celular | AB17: 11 | AC17: 961850785 | AD17: Celular | AE17: 11 | AF17: 47748033 | AG17: Fixo | AH17: RECEBIMENTO.NFE@BOMIGROUP.COM | AK17: BOMI ITALIA SPA | AL17: SOCIO PESSOA JURIDICA DOMICILIADO NO EXTERIOR | AO17: TELMA NICOLETTI SANTORO | AP17: ADMINISTRADOR | AQ17: 15 | AR17: 997018800 | AS17: GILBERTO JOSE DOS SANTOS | AT17: ADMINISTRADOR | AU17: 11 | AV17: 943626786 | AW17: 4930201-Transporte rodoviário de carga, exceto produtos perigosos e mudanças, municipal\4930202-Transporte rodoviário de carga, exceto produtos perigosos e mudanças, intermunicipal, interestadual e internacional\4930203-Transporte rodoviário de produtos perigosos\5211799-Depósitos de mercadorias para terceiros, exceto armazéns gerais e guarda-móveis\5229099-Outras atividades auxiliares dos transportes terrestres não especificadas anteriormente\5250803-Agenciamento de cargas, exceto para o transporte marítimo\5250804-Organização logística do transporte de carga\5250805-Operador de transporte multimodal - OTM\7810800-Seleção e agenciamento de mão de obra\7820500-Locação de mão de obra temporária | AX17: 373.119.710.119 | AY17: N
A18: 05.107.871/0001-22 | B18: FRANGO NUTRIBEM LTDA. | D18: GRANDE | E18: 274615711 | F18: 15000000 | G18: 744 | H18: 903 | I18: RISCO MUITO BAIXO | J18: ATIVA | K18: 1012101 | L18: Abate de aves | M18: 6/18/2002 | N18: 1 | O18: SP 355 | Q18: KM DOZE E MEIO | S18: NOVA ALIANCA | T18: SP | U18: 15210000 | V18: 17 | W18: 997897637 | X18: Celular | Y18: 17 | Z18: 996554338 | AA18: Celular | AB18: 17 | AC18: 996770175 | AD18: Celular | AE18: 17 | AF18: 38117383 | AG18: Fixo | AH18: EMERSON@FRANGONUTRIBEM.COM.BR | AI18: ALINE@FRANGONUTRIBEM.COM.BR | AJ18: CAIO.BAZETTI@FRANGONUTRIBEM.COM.BR | AK18: CARLOS TOSHIHIRO MIZUSAKI | AL18: SOCIO ADMINISTRADOR | AO18: RICARDO GRANDIZOLI | AP18: SOCIO ADMINISTRADOR | AQ18: 17 | AR18: 996188769 | AS18: FABIO GRANDIZOLI | AT18: SOCIO ADMINISTRADOR | AU18: 17 | AV18: 992345995 | AW18: 0155501-Criação de frangos para corte\1013901-Fabricação de produtos de carne\1013902-Preparação de subprodutos do abate\1066000-Fabricação de alimentos para animais\4633803-Comércio atacadista de coelhos e outros pequenos animais vivos para alimentação\4634601-Comércio atacadista de carnes bovinas e suínas e derivados\4634602-Comércio atacadista de aves abatidas e derivados\4930202-Transporte rodoviário de carga, exceto produtos perigosos e mudanças, intermunicipal, interestadual e internacional | AX18: 476.054.276.110 | AY18: N
A19: 61.024.295/0001-20 | B19: ARFRIO S/A ARMAZENS GERAIS FRIGORIFICOS | D19: GRANDE | E19: 272828307 | F19: 80000000 | G19: 91 | H19: 861 | I19: RISCO MUITO BAIXO | J19: ATIVA | K19: 5211701 | L19: Armazéns gerais - emissão de warrant | M19: 4/11/1967 | N19: 13 | O19: JUSSARA | P19: 1001 | R19: JARDIM SANTA CECILIA | S19: BARUERI | T19: SP | U19: 06465070 | V19: 71 | W19: 999719190 | X19: Celular | Y19: 71 | Z19: 999886473 | AA19: Celular | AB19: 71 | AC19: 999763924 | AD19: Celular | AE19: 11 | AF19: 41954000 | AG19: Fixo | AH19: LCAMPOS@ARFRIO.COM.BR | AK19: MARCELO VASONE | AL19: DIRETOR | AM19: 11 | AN19: 982792242 | AO19: EDUARDO AMERICO DE ATHAIDE VASONE | AP19: PRESIDENTE | AQ19: 11 | AR19: 981061896 | AS19: RODOLFO VASONE | AT19: DIRETOR | AU19: 11 | AV19: 964189016 | AX19: 206.009.400.114 | AY19: N
A20: 51.979.359/0001-93 | B20: STOLTHAVEN SANTOS LTDA | D20: MÉDIA | E20: 264314429 | F20: 279083198 | G20: 123 | H20: 319 | I20: RISCO MÉDIO | J20: ATIVA | K20: 5211701 | L20: Armazéns gerais - emissão de warrant | M20: 11/3/1982 | N20: 1 | O20: AUGUSTO SCARABOTO | P20: 215 | Q20: 245 | R20: ALEMOA | S20: SANTOS | T20: SP | U20: 11095500 | V20: 13 | W20: 997238255 | X20: Celular | Y20: 13 | Z20: 997474318 | AA20: Celular | AB20: 13 | AC20: 996398680 | AD20: Celular | AE20: 13 | AF20: 32959003 | AG20: Fixo | AH20: SRIBAS@SNTG.COM | AK20: STOLTHAVEN TERMINALS BV | AL20: SOCIO PESSOA JURIDICA DOMICILIADO NO EXTERIOR | AO20: STOLT-NIELSEN BRASIL AFRETAMENTO LTDA. | AP20: SOCIO | AQ20: 11 | AR20: 38974999 | AS20: MARCELO TIACCI SCHMITT | AT20: ADMINISTRADOR | AU20: 11 | AV20: 983830729 | AX20: 633.190.383.111 | AY20: N
A21: 89.082.085/0001-08 | B21: RIO DO SUL SERVICO E TRANSPORTE LTDA | D21: GRANDE | E21: 253269455 | F21: 34000 | G21: 387 | H21: 653 | I21: RISCO BAIXO | J21: ATIVA | K21: 4930201 | L21: Transporte rodoviário de carga, exceto produtos perigosos e mudanças, municipal | M21: 12/6/1976 | N21: 5 | O21: EVARISTO LOPES | P21: 483 | R21: ERMO | S21: GUAIBA | T21: RS | U21: 92702700 | V21: 51 | W21: 997591437 | X21: Celular | Y21: 51 | Z21: 995824623 | AA21: Celular | AB21: 51 | AC21: 998693752 | AD21: Celular | AE21: 51 | AF21: 34801261 | AG21: Fixo | AH21: RIODOSUL.RS@GMAIL.COM | AI21: ACOGLIATTI@SULAMERICA.COM.BR | AJ21: ADELCO.MARINHO@SULAMERICA.COM.BR | AK21: PAULO ARRUDA DE OLIVEIRA | AL21: SOCIO ADMINISTRADOR | AM21: 51 | AN21: 999834441 | AO21: MARIA DE LOURDES HARLACHER GARCIA | AP21: SOCIO ADMINISTRADOR | AQ21: 51 | AR21: 993657457 | AS21: PAULO ROBERTO VIEIRA DE OLIVEIRA | AT21: ADMINISTRADOR | AU21: 51 | AV21: 998561409 | AW21: 0161099-Atividades de apoio à agricultura não especificadas anteriormente\0230600-Atividades de apoio à produção florestal\3319800-Manutenção e reparação de equipamentos e produtos não especificados anteriormente\3600601-Captação, tratamento e distribuição de água\3701100-Gestão de redes de esgoto\3702900-Atividades relacionadas a esgoto, exceto a gestão de redes\4120400-Construção de edifícios\4211101-Construção de rodovias e ferrovias\4213800-Obras de urbanização - ruas, praças e calçadas\4222701-Construção de redes de abastecimento de água, coleta de esgoto e construções correlatas, exceto obras de irrigação\4313400-Obras de terraplenagem\4399104-Serviços de operação e fornecimento de equipamentos para transporte e elevação de cargas e pessoas para uso em obras\4923002-Serviço de transporte de passageiros - locação de automóveis com motorista\4930202-Transporte rodoviário de carga, exceto produtos perigosos e mudanças, intermunicipal, interestadual e internacional\4930203-Transporte rodoviário de produtos perigosos\5212500-Carga e descarga\5250803-Agenciamento de cargas, exceto para o transporte marítimo\5250804-Organização logística do transporte de carga\5320202-Serviços de entrega rápida\7711000-Locação de automóveis sem condutor\7731400-Aluguel de máquinas e equipamentos agrícolas sem operador\7732201-Aluguel de máquinas e equipamentos para construção sem operador, exceto andaimes\7739099-Aluguel de outras máquinas e equipamentos comerciais e industriais não especificados anteriormente, sem operador\8130300-Atividades paisagísticas | AX21: 058/0023966 | AY21: N
A22: 07.702.969/0001-53 | B22: FUNDICAO REGALI BRASIL LTDA. | D22: MÉDIA | E22: 239896493 | F22: 13454064 | G22: 227 | H22: 412 | I22: RISCO MÉDIO | J22: ATIVA | K22: 2451200 | L22: Fundição de ferro e aço | M22: 10/20/2005 | N22: 0 | O22: DOUTOR JOSE FABIANO DE CHRISTO GURJAO | P22: 490 | R22: DISTRITO INDUSTRIAL II LUIZ TORRANI | S22: MOGI MIRIM | T22: SP | U22: 13803705 | V22: 19 | W22: 998427442 | X22: Celular | Y22: 19 | Z22: 998427450 | AA22: Celular | AB22: 19 | AC22: 998428895 | AD22: Celular | AE22: 19 | AF22: 38057460 | AG22: Fixo | AH22: FINANCEIRO@FUNDICAOREGALI.COM.BR | AI22: SIMONE@REGALIBRASIL.COM.BR | AJ22: CELSO@REGALIBRASIL.COM.BR | AK22: REGALI INTERNATIONAL SRL | AL22: SOCIO PESSOA JURIDICA DOMICILIADO NO EXTERIOR | AO22: MASSIMO REGALI | AP22: SOCIO ADMINISTRADOR | AQ22: 19 | AR22: 998427560 | AW22: 2941700-Fabricação de peças e acessórios para o sistema motor de veículos automotores\2942500-Fabricação de peças e acessórios para os sistemas de marcha e transmissão de veículos automotores\2943300-Fabricação de peças e acessórios para o sistema de freios de veículos automotores\2949299-Fabricação de outras peças e acessórios para veículos automotores não especificadas anteriormente | AX22: 456.064.276.113 | AY22: N
A23: 85.641.066/0001-13 | B23: FRIGORIFICO VERDI LTDA. | D23: MÉDIA | E23: 225389097 | F23: 4000000 | G23: 271 | H23: 941 | I23: RISCO MUITO BAIXO | J23: ATIVA | K23: 1011201 | L23: Frigorífico - abate de bovinos | M23: 12/30/1969 | N23: 3 | O23: ARI VERDI | P23: 410 | R23: CENTRO | S23: POUSO REDONDO | T23: SC | U23: 89172000 | V23: 47 | W23: 35458100 | X23: Fixo | Y23: 47 | Z23: 999330932 | AA23: Celular | AB23: 47 | AC23: 999330827 | AD23: Celular | AE23: 47 | AF23: 999330703 | AG23: Celular | AH23: JAQUELINE@FRIGORIFICOVERDI.COM.BR | AK23: ELFRIDA BICHELS VERDI | AL23: SOCIO ADMINISTRADOR | AO23: ARIANE BICHELS VERDI CRISTOFOLINI | AP23: SOCIO ADMINISTRADOR | AQ23: 47 | AR23: 999680470 | AS23: ARIEL HENRIQUE BICHELS VERDI | AT23: SOCIO ADMINISTRADOR | AW23: 1013901-Fabricação de produtos de carne\4623101-Comércio atacadista de animais vivos\4692300-Comércio atacadista de mercadorias em geral, com predominância de insumos agropecuários\4789099-Comércio varejista de outros produtos não especificados anteriormente\4930202-Transporte rodoviário de carga, exceto produtos perigosos e mudanças, intermunicipal, interestadual e internacional\ | AX23: 250160072 | AY23: N
A24: 07.750.075/0001-39 | B24: UNIAO AGROINDUSTRIAL LTDA | C24: UNIAO AVICOLA | D24: GRANDE | E24: 219633956 | F24: 51800000 | G24: 1315 | H24: 666 | I24: RISCO BAIXO | J24: ATIVA | K24: 1012101 | L24: Abate de aves | M24: 12/19/2005 | N24: 7 | O24: MT 160 KM 03 | Q24: MT 160 KM 3 | R24: ZONA RURAL | S24: NOVA MARILANDIA | T24: MT | U24: 78415000 | V24: 65 | W24: 33521219 | X24: Fixo | AH24: CONTABILIDADE@UNIAOAVICOLA.IND.BR | AI24: ADRIANA.ARAUJO@UNIAOAVICOLA.IND.BR | AJ24: ALEMAR.BORGES@UNIAOAVICOLA.IND.BR | AK24: JOSE APARECIDO DOS SANTOS | AL24: SOCIO | AM24: 65 | AN24: 984221806 | AO24: MARLI BECKER SANTOS | AP24: SOCIO ADMINISTRADOR | AQ24: 65 | AR24: 984795558 | AS24: MC EMPREENDIMENTOS & PARTICIPACOES LTDA | AT24: SOCIO | AU24: 65 | AV24: 33169050 | AW24: 0154700-Criação de suínos\0155501-Criação de frangos para corte\0163600-Atividades de pós-colheita\1013901-Fabricação de produtos de carne\1013902-Preparação de subprodutos do abate\1066000-Fabricação de alimentos para animais\1069400-Moagem e fabricação de produtos de origem vegetal não especificados anteriormente\1099699-Fabricação de outros produtos alimentícios não especificados anteriormente\1932200-Fabricação de biocombustíveis, exceto álcool\4623101-Comércio atacadista de animais vivos\4623109-Comércio atacadista de alimentos para animais\4623199-Comércio atacadista de matérias-primas agrícolas não especificadas anteriormente\4633801-Comércio atacadista de frutas, verduras, raízes, tubérculos, hortaliças e legumes frescos\4789004-Comércio varejista de animais vivos e de artigos e alimentos para animais de estimação\5211701-Armazéns gerais - emissão de warrant\6463800-Outras sociedades de participação, exceto holdings | AX24: 13.313.191-2 | AY24: S
A25: 49.243.124/0001-97 | B25: TRANSMORENO TRANSPORTE E LOGISTICA LTDA | D25: GRANDE | E25: 207812073 | F25: 1439000 | G25: 51 | H25: 586 | I25: RISCO BAIXO | J25: ATIVA | K25: 4930202 | L25: Transporte rodoviário de carga, exceto produtos perigosos e mudanças, intermunicipal, interestadual e internacional | M25: 4/6/1978 | N25: 0 | O25: VANDERLEI MORENO | P25: 13130 | R25: ROSEIRA DE SAO SEBASTIAO | S25: SAO JOSE DOS PINHAIS | T25: PR | U25: 83070245 | V25: 24 | W25: 999017539 | X25: Celular | Y25: 24 | Z25: 998572543 | AA25: Celular | AB25: 41 | AC25: 992258891 | AD25: Celular | AE25: 41 | AF25: 31347700 | AG25: Fixo | AH25: FISCAL@TRANSMORENO.COM.BR | AI25: SIDNEI.DANIOTI@TRANSMORENO.COM.BR | AJ25: THIAGO.MORENO@TRANSMORENO.COM.BR | AK25: GUILHERME DE ANDRADE FONSECA SAMPAIO | AL25: ADMINISTRADOR | AM25: 11 | AN25: 981209281 | AO25: RAMON PERES MARTINEZ GARCIA DE ALCARAZ | AP25: ADMINISTRADOR | AQ25: 15 | AR25: 981337577 | AS25: JSL S.A. | AT25: SOCIO | AU25: 11 | AV25: 23777000 | AW25: 4520001-Serviços de manutenção e reparação mecânica de veículos automotores\4520002-Serviços de lanternagem ou funilaria e pintura de veículos automotores\4520003-Serviços de manutenção e reparação elétrica de veículos automotores\4520004-Serviços de alinhamento e balanceamento de veículos automotores\4520005-Serviços de lavagem, lubrificação e polimento de veículos automotores\4520006-Serviços de borracharia para veículos automotores\4520007-Serviços de instalação, manutenção e reparação de acessórios para veículos automotores\4520008-Serviços de capotaria\4930201-Transporte rodoviário de carga, exceto produtos perigosos e mudanças, municipal\5211701-Armazéns gerais - emissão de warrant\5211799-Depósitos de mercadorias para terceiros, exceto armazéns gerais e guarda-móveis\5212500-Carga e descarga\5223100-Estacionamento de veículos\5250804-Organização logística do transporte de carga\6810202-Aluguel de imóveis próprios\6821802-Corretagem no aluguel de imóveis\7719599-Locação de outros meios de transporte não especificados anteriormente, sem condutor\ | AY25: N
A26: 06.132.739/0001-33 | B26: BURITI COMERCIO DE CARNES LTDA | C26: BURITI | D26: MÉDIA | E26: 203984723 | F26: 1200000 | G26: 327 | H26: 655 | I26: RISCO BAIXO | J26: ATIVA | K26: 1011201 | L26: Frigorífico - abate de bovinos | M26: 3/5/2004 | N26: 0 | O26: BURITI | Q26: CX POSTAL 101 | S26: AQUIDAUANA | T26: MS | U26: 79200000 | V26: 67 | W26: 992262000 | X26: Celular | Y26: 67 | Z26: 36861046 | AA26: Fixo | AH26: CONTROLADORIA@BURITICARNES.COM.BR | AI26: CONDADOS.OFC@IG.COM.BR | AK26: DANIEL CHRAMOSTA | AL26: SOCIO ADMINISTRADOR | AM26: 67 | AN26: 996302620 | AW26: 0151201-Criação de bovinos para corte\1011204-Frigorífico - abate de bufalinos\1013901-Fabricação de produtos de carne\1013902-Preparação de subprodutos do abate\4611700-Representantes comerciais e agentes do comércio de matérias-primas agrícolas e animais vivos\4623101-Comércio atacadista de animais vivos\4634601-Comércio atacadista de carnes bovinas e suínas e derivados\4634602-Comércio atacadista de aves abatidas e derivados\4722901-Comércio varejista de carnes - açougues\4729602-Comércio varejista de mercadorias em lojas de conveniência | AX26: 28.331.065-0 | AY26: S
A27: 00.220.615/0001-23 | B27: META COMERCIO DE PRODUTOS AGRICOLAS LTDA. | D27: MÉDIA | E27: 198592549 | F27: 3148629 | H27: 620 | I27: RISCO BAIXO | J27: ATIVA | K27: 4930202 | L27: Transporte rodoviário de carga, exceto produtos perigosos e mudanças, intermunicipal, interestadual e internacional | M27: 9/29/1994 | N27: 0 | O27: URUGUAI | P27: 1954 | Q27: APT 201 | R27: BOQUEIRAO | S27: PASSO FUNDO | T27: RS | U27: 99010112 | V27: 54 | W27: 999192664 | X27: Celular | Y27: 54 | Z27: 991055252 | AA27: Celular | AB27: 55 | AC27: 997222786 | AD27: Celular | AE27: 54 | AF27: 33141422 | AG27: Fixo | AH27: VLA.AMARANTE@GMAIL.COM | AI27: LORENA.LOPES@METAAGRICOLA.COM.BR | AJ27: CONTASAPAGAR@METAAGRICOLA.COM.BR | AK27: M. WAGNER LTDA | AL27: SOCIO | AM27: 54 | AN27: 991055252 | AO27: ROSO PARTICIPACOES LTDA. | AP27: SOCIO | AQ27: 54 | AR27: 33422420 | AS27: FELIPE DE MELLO GALVAN | AT27: SOCIO | AW27: 4511101-Comércio a varejo de automóveis, camionetas e utilitários novos\4520001-Serviços de manutenção e reparação mecânica de veículos automotores\4530702-Comércio por atacado de pneumáticos e câmaras-de-ar\4530703-Comércio a varejo de peças e acessórios novos para veículos automotores\4622200-Comércio atacadista de soja\4632001-Comércio atacadista de cereais e leguminosas beneficiados\4661300-Comércio atacadista de máquinas, aparelhos e equipamentos para uso agropecuário, partes e peças\4672900-Comércio atacadista de ferragens e ferramentas\4681805-Comércio atacadista de lubrificantes\4685100-Comércio atacadista de produtos siderúrgicos e metalúrgicos, exceto para construção\4689399-Comércio atacadista especializado em outros produtos intermediários não especificados anteriormente\4732600-Comércio varejista de lubrificantes\4789099-Comércio varejista de outros produtos não especificados anteriormente\5250801-Comissaria de despachos\6810201-Compra e venda de imóveis próprios\6810202-Aluguel de imóveis próprios\6822600-Gestão e administração da propriedade imobiliária\ | AX27: 091/0173257 | AY27: N
A28: 31.667.298/0001-11 | B28: TRANSHIP TRANSPORTES MARITIMOS LTDA | D28: MÉDIA | E28: 193404321 | F28: 51854169 | G28: 90 | H28: 766 | I28: RISCO MUITO BAIXO | J28: ATIVA | K28: 5011401 | L28: Transporte marítimo de cabotagem - Carga | M28: 11/9/1987 | N28: 4 | O28: MANUEL DUARTE | P28: 2291 | R28: GRADIM | S28: SAO GONCALO | T28: RJ | U28: 24430500 | V28: 21 | W28: 999872131 | X28: Celular | Y28: 21 | Z28: 996181169 | AA28: Celular | AB28: 21 | AC28: 967431924 | AD28: Celular | AE28: 21 | AF28: 22424242 | AG28: Fixo | AH28: LUIZ@TSTRANSHIP.COM.BR | AI28: ANTONIOCARLOS@TSTRANSHIP.COM.BR | AJ28: PAULO@TSTRANSHIP.COM.BR | AK28: QUATRO LUAS PARTICIPACOES LTDA | AL28: SOCIO | AM28: 21 | AN28: 22333611 | AO28: ELIZABETH CAPELETTI SARMENTO | AP28: SOCIO ADMINISTRADOR | AS28: DANIEL SARMENTO ALMEIDA | AT28: SOCIO | AU28: 21 | AV28: 999170216 | AW28: 4291000-Obras portuárias, marítimas e fluviais\4292802-Obras de montagem industrial\5012201-Transporte marítimo de longo curso - Carga\5021102-Transporte por navegação interior de carga, intermunicipal, interestadual e internacional, exceto travessia\5030103-Serviço de rebocadores e empurradores\5212500-Carga e descarga\5231102-Atividades do Operador Portuário\5250804-Organização logística do transporte de carga\5250805-Operador de transporte multimodal - OTM\6463800-Outras sociedades de participação, exceto holdings\6810202-Aluguel de imóveis próprios\7112000-Serviços de engenharia\7490102-Escafandria e mergulho\7719501-Locação de embarcações sem tripulação, exceto para finsrecreativos\7739099-Aluguel de outras máquinas e equipamentos comerciais e industriais não especificados anteriormente, sem operador\ | AX28: 83.485.191 | AY28: S
A29: 02.286.658/0001-37 | B29: GB TERMINAIS BRASIL S/A | D29: MÉDIA | E29: 189700722 | F29: 45821770 | G29: 9 | H29: 888 | I29: RISCO MUITO BAIXO | J29: ATIVA | K29: 5231102 | L29: Atividades do Operador Portuário | M29: 12/1/1997 | N29: 1 | O29: LAURO MULLER | P29: 00116 | Q29: SAL 3106 SAL 3201 SAL 3205 SAL 3206 SAL 3207 | R29: BOTAFOGO | S29: RIO DE JANEIRO | T29: RJ | U29: 22290160 | V29: 21 | W29: 967802788 | X29: Celular | Y29: 21 | Z29: 995276029 | AA29: Celular | AB29: 21 | AC29: 981486083 | AD29: Celular | AE29: 21 | AF29: 25863438 | AG29: Fixo | AH29: BELLIVANES@GMAIL.COM | AK29: ALUISIO JOSE MACEDO JUNIOR | AL29: DIRETOR | AM29: 11 | AN29: 978454566 | AW29: 5212500-Carga e descarga\5222200-Terminais rodoviários e ferroviários\5231101-Administração da infraestrutura portuária\5231103-Gestão de terminais aquaviários\5232000-Atividades de agenciamento marítimo\5250802-Atividades de despachantes aduaneiros\7739099-Aluguel de outras máquinas e equipamentos comerciais e industriais não especificados anteriormente, sem operador\ | AX29: 86.319.314 | AY29: N
A30: 09.452.900/0001-44 | B30: VIX TRANSPORTES DEDICADOS LTDA | C30: VIX TD | D30: GRANDE | E30: 182472782 | F30: 178000002 | G30: 437 | H30: 742 | I30: RISCO MUITO BAIXO | J30: ATIVA | K30: 4930202 | L30: Transporte rodoviário de carga, exceto produtos perigosos e mudanças, intermunicipal, interestadual e internacional | M30: 2/26/2008 | N30: 36 | O30: MARIO GURGEL 5030 | P30: 5030 | Q30: SETOR CENTRO ADM AB SALA 105 | R30: VILA CAPIXABA | S30: CARIACICA | T30: ES | U30: 29145901 | V30: 27 | W30: 21251420 | X30: Fixo | AK30: VIX LOGISTICA S/A | AL30: SOCIO | AM30: 27 | AN30: 21251421 | AO30: RODOLFO ALTOE FILHO | AP30: ADMINISTRADOR | AQ30: 28 | AR30: 999432325 | AS30: CIRO FERREIRA DA ROCHA | AT30: ADMINISTRADOR | AU30: 11 | AV30: 945967902 | AW30: 0161001-Serviço de pulverização e controle de pragas agrícolas\0161099-Atividades de apoio à agricultura não especificadas anteriormente\0210107-Extração de madeira em florestas plantadas\0230600-Atividades de apoio à produção florestal\0899199-Extração de outros minerais não metálicos não especificados anteriormente\0910600-Atividades de apoio à extração de petróleo e gás natural\0990402-Atividades de apoio à extração de minerais metálicos não ferrosos\0990403-Atividades de apoio à extração de minerais não metálicos\2330305-Preparação de massa de concreto e argamassa para construção\3314708-Manutenção e reparação de máquinas, equipamentos e aparelhos para transporte e elevação de cargas\3600602-Distribuição de água por caminhões\3811400-Coleta de resíduos não perigosos\3812200-Coleta de resíduos perigosos\4313400-Obras de terraplenagem\4319300-Serviços de preparação do terreno não especificados anteriormente\4399101-Administração de obras\4399104-Serviços de operação e fornecimento de equipamentos para transporte e elevação de cargas e pessoas para uso em obras\4511102-Comércio a varejo de automóveis, camionetas e utilitários usados\4520001-Serviços de manutenção e reparação mecânica de veículos automotores\4520002-Serviços de lanternagem ou funilaria e pintura de veículos automotores\4520005-Serviços de lavagem, lubrificação e polimento de veículos automotores\4921301-Transporte rodoviário coletivo de passageiros, com itinerário fixo, municipal\4921302-Transporte rodoviário coletivo de passageiros, com itinerário fixo, intermunicipal em região metropolitana\4922101-Transporte rodoviário coletivo de passageiros, com itinerário fixo, intermunicipal, exceto em região metropolitana\4922102-Transporte rodoviário coletivo de passageiros, com itinerário fixo, interestadual\4922103-Transporte rodoviário coletivo de passageiros, com itinerário fixo, internacional\4923002-Serviço de transporte de passageiros - locação de automóveis com motorista\4929901-Transporte rodoviário coletivo de passageiros, sob regime de fretamento, municipal\4929902-Transporte rodoviário coletivo de passageiros, sob regime de fretamento, intermunicipal, interestadual e internacional\4929903-Organização de excursões em veículos rodoviários próprios, municipal\4929904-Organização de excursões em veículos rodoviários próprios, intermunicipal, interestadual e internacional\4929999-Outros transportes rodoviários de passageiros não especificados anteriormente\4930201-Transporte rodoviário de carga, exceto produtos perigosos e mudanças, municipal\4930203-Transporte rodoviário de produtos perigosos\5030101-Navegação de apoio marítimo\5099899-Outros transportes aquaviários não especificados anteriormente\5212500-Carga e descarga\5221400-Concessionárias de rodovias, pontes, túneis e serviços relacionados\5223100-Estacionamento de veículos\5229002-Serviços de reboque de veículos\5229099-Outras atividades auxiliares dos transportes terrestres não especificadas anteriormente\5231102-Atividades do Operador Portuário\5240101-Operação dos aeroportos e campos de aterrissagem\5240199-Atividades auxiliares dos transportes aéreos, exceto operação dos aeroportos e campos de aterrissagem\5250803-Agenciamento de cargas, exceto para o transporte marítimo\5250804-Organização logística do transporte de carga\5250805-Operador de transporte multimodal - OTM\6462000-Holdings de instituições não financeiras\6463800-Outras sociedades de participação, exceto holdings\7020400-Atividades de consultoria em gestão empresarial, exceto consultoria técnica específica\7312200-Agenciamento de espaços para publicidade, exceto em veículos de comunicação\7490104-Atividades de intermediação e agenciamento de serviços e negócios em geral, exceto imobiliários\7711000-Locação de automóveis sem condutor\7719599-Locação de outros meios de transporte não especificados anteriormente, sem condutor\7731400-Aluguel de máquinas e equipamentos agrícolas sem operador\7732201-Aluguel de máquinas e equipamentos para construção sem operador, exceto andaimes\7739099-Aluguel de outras máquinas e equipamentos comerciais e industriais não especificados anteriormente, sem operador\7820500-Locação de mão de obra temporária\7830200-Fornecimento e gestão de recursos humanos para terceiros\8111700-Serviços combinados para apoio a edifícios, exceto condomínios prediais\8121400-Limpeza em prédios e em domicílios\8122200-Imunização e controle de pragas urbanas\8129000-Atividades de limpeza não especificadas anteriormente\8130300-Atividades paisagísticas\8211300-Serviços combinados de escritório e apoio administrativo\8219999-Preparação de documentos e serviços especializados de apoio administrativo não especificados anteriormente\8299799-Outras atividades de serviços prestados principalmente às empresas não especificadas anteriormente\8621601-UTI móvel\8621602-Serviços móveis de atendimento a urgências, exceto por UTI móvel\8622400-Serviços de remoção de pacientes, exceto os serviços móveis de atendimento a urgências | AX30: 082.547.03-3 | AY30: N
A31: 80.276.314/0001-50 | B31: FORTESOLO SERVICOS INTEGRADOS LTDA | C31: FORTESOLO | D31: GRANDE | E31: 175549216 | F31: 24616051 | G31: 121 | H31: 353 | I31: RISCO MÉDIO | J31: ATIVA | K31: 5211701 | L31: Armazéns gerais - emissão de warrant | M31: 9/23/1987 | N31: 6 | O31: AYRTON SENNA DA SILVA | P31: 7520 | R31: PARQUE SAO JOAO | S31: PARANAGUA | T31: PR | U31: 83212090 | V31: 41 | W31: 30240041 | X31: Fixo | AK31: DAVID PEREIRA DE JESUS | AL31: ADMINISTRADOR | AM31: 41 | AN31: 992011737 | AO31: FTS PARTICIPACOES SOCIETARIAS S.A. | AP31: SOCIO | AQ31: 41 | AR31: 31663400 | AW31: 1041400-Fabricação de óleos vegetais em bruto, exceto óleo de milho\2013402-Fabricação de adubos e fertilizantes, exceto organo-minerais\3319800-Manutenção e reparação de equipamentos e produtos não especificados anteriormente\4622200-Comércio atacadista de soja\4623103-Comércio atacadista de algodão\4623106-Comércio atacadista de sementes, flores, plantas e gramas\4623199-Comércio atacadista de matérias-primas agrícolas não especificadas anteriormente\4637103-Comércio atacadista de óleos e gorduras\4683400-Comércio atacadista de defensivos agrícolas, adubos, fertilizantes e corretivos do solo\5099899-Outros transportes aquaviários não especificados anteriormente\5212500-Carga e descarga\5223100-Estacionamento de veículos\5231102-Atividades do Operador Portuário\5250802-Atividades de despachantes aduaneiros\5250803-Agenciamento de cargas, exceto para o transporte marítimo\6810202-Aluguel de imóveis próprios\7739099-Aluguel de outras máquinas e equipamentos comerciais e industriais não especificados anteriormente, sem operador\8292000-Envasamento e empacotamento sob contrato | AX31: 90175503-54 | AY31: S
A32: 06.975.242/0001-87 | B32: LOG FRIO LOGISTICA LTDA. | C32: LOG FRIO LOGISTICA | D32: GRANDE | E32: 170614186 | F32: 53000000 | G32: 889 | H32: 702 | I32: RISCO MUITO BAIXO | J32: ATIVA | K32: 4930201 | L32: Transporte rodoviário de carga, exceto produtos perigosos e mudanças, municipal | M32: 8/11/2004 | N32: 7 | O32: JUSSARA | P32: 1635 | Q32: SALA L CAMARA 1 | R32: JARDIM SANTA CECILIA | S32: BARUERI | T32: SP | U32: 6465070 | V32: 11 | W32: 940125791 | X32: Celular | Y32: 11 | Z32: 941107193 | AA32: Celular | AB32: 11 | AC32: 975621200 | AD32: Celular | AE32: 11 | AF32: 21757107 | AG32: Fixo | AH32: CONTABILIDADE@LOGFRIO.COM.BR | AI32: MAURO@LOGFRIO.COM.BR | AJ32: FERREIRA@LOGFRIO.COM.BR | AK32: SUPERFRIO ARMAZENS GERAIS S.A. | AL32: SOCIO | AM32: 16 | AN32: 39021900 | AO32: CAMILA SCAPIM ARCARO | AP32: ADMINISTRADOR | AQ32: 19 | AR32: 992757408 | AS32: FRANCISCO CARLOS BORGES DE ASSIS MOURA | AT32: ADMINISTRADOR | AU32: 17 | AV32: 991297907 | AW32: 4930202-Transporte rodoviário de carga, exceto produtos perigosos e mudanças, intermunicipal, interestadual e internacional\5211799-Depósitos de mercadorias para terceiros, exceto armazéns gerais e guarda-móveis\5212500-Carga e descarga\ | AX32: 206.229.961.113 | AY32: N
A33: 29.355.260/0001-61 | B33: TRIUNFO LOGISTICA LTDA | C33: TRILOG | D33: GRANDE | E33: 162250226 | F33: 39000000 | G33: 974 | H33: 608 | I33: RISCO BAIXO | J33: ATIVA | K33: 5231102 | L33: Atividades do Operador Portuário | M33: 4/30/1985 | N33: 14 | O33: CIDADE LIMA | P33: 00086 | Q33: SAL 201 SAL 202 | R33: SANTO CRISTO | S33: RIO DE JANEIRO | T33: RJ | U33: 20220710 | V33: 21 | W33: 970261965 | X33: Celular | Y33: 21 | Z33: 972247348 | AA33: Celular | AB33: 21 | AC33: 997691639 | AD33: Celular | AE33: 21 | AF33: 21788800 | AG33: Fixo | AH33: COMUNICACAO@TRIUNFOLOGISTICA.COM.BR | AI33: THIAGO.RODRIGUES@TRIUNFOLOGISTICA.COM.BR | AJ33: ALEXANDRE.LIMA@TRIUNFOLOGISTICA.COM.BR | AK33: MARIA AMELIA FRANCO BASTOS | AL33: SOCIO ADMINISTRADOR | AM33: 21 | AN33: 998450622 | AO33: TATIANA RODRIGUES DO NASCIMENTO VIEIRA | AP33: SOCIO | AQ33: 21 | AR33: 997727088 | AS33: MARCOS ALEXANDRE DA SILVA | AT33: SOCIO | AU33: 21 | AV33: 999962502 | AW33: 5211701-Armazéns gerais - emissão de warrant\7739099-Aluguel de outras máquinas e equipamentos comerciais e industriais não especificados anteriormente, sem operador | AX33: 83.969.768 | AY33: S
A34: 73.325.722/0001-90 | B34: DAGNESE & CIA LTDA | C34: DAGNESE SOLUCOES METALICAS | D34: MÉDIA | E34: 160502556 | F34: 2350000 | G34: 322 | H34: 683 | I34: RISCO BAIXO | J34: ATIVA | K34: 2511000 | L34: Fabricação de estruturas metálicas | M34: 9/9/1993 | N34: 0 | O34: RS 324 | P34: 485 | Q34: KM 17 | R34: DISTRITO INDUSTRIAL | S34: NOVA BASSANO | T34: RS | U34: 95340000 | V34: 54 | W34: 999409085 | X34: Celular | Y34: 54 | Z34: 996378378 | AA34: Celular | AB34: 54 | AC34: 999185929 | AD34: Celular | AE34: 54 | AF34: 32733000 | AG34: Fixo | AH34: OTAVIO@DAGNESE.COM.BR | AI34: JULIO@DAGNESE.COM.BR | AJ34: VITOR@DAGNESE.COM.BR | AK34: ROMANO MARTINI | AL34: SOCIO ADMINISTRADOR | AM34: 54 | AN34: 991050911 | AO34: LUIS CLAUDIO DAGNESE | AP34: SOCIO ADMINISTRADOR | AQ34: 51 | AR34: 994940606 | AW34: 2512800-Fabricação de esquadrias de metal\2539001-Serviços de usinagem, torneiria e solda\3329599-Instalação de outros equipamentos não especificados anteriormente\4292801-Montagem de estruturas metálicas\4619200-Representantes comerciais e agentes do comércio de mercadorias em geral não especializado\4679604-Comércio atacadista especializado de materiais de construção não especificados anteriormente\6810202-Aluguel de imóveis próprios\7112000-Serviços de engenharia\7732201-Aluguel de máquinas e equipamentos para construção sem operador, exceto andaimes\ | AX34: 207/0004966 | AY34: S
A35: 82.134.073/0001-30 | B35: MORGANA ALIMENTOS LTDA | D35: MÉDIA | E35: 156572262 | F35: 48636000 | G35: 502 | H35: 775 | I35: RISCO MUITO BAIXO | J35: ATIVA | K35: 1012101 | L35: Abate de aves | M35: 8/8/1990 | N35: 5 | O35: OSNI KUHNEN | P35: 540 | R35: ALTO ARIRIU | S35: PALHOCA | T35: SC | U35: 88135609 | V35: 48 | W35: 996870511 | X35: Celular | Y35: 48 | Z35: 991117427 | AA35: Celular | AB35: 48 | AC35: 991575052 | AD35: Celular | AE35: 48 | AF35: 33421008 | AG35: Fixo | AH35: AMANDA@FRANGOSMORGANA.COM.BR | AI35: LAYS@FRANGOSMORGANA.COM.BR | AJ35: DEISIANE@FRANGOSMORGANA.COM.BR | AK35: MARCOS JOSE DA SILVA | AL35: SOCIO ADMINISTRADOR | AM35: 48 | AN35: 996324333 | AO35: BRUNO SILVA MARTINS DA SILVA | AP35: SOCIO ADMINISTRADOR | AQ35: 48 | AR35: 999959659 | AS35: AMANDA DUARTE BARRETO | AT35: SOCIO ADMINISTRADOR | AU35: 48 | AV35: 999624112 | AW35: 0151201-Criação de bovinos para corte\0154700-Criação de suínos\0155501-Criação de frangos para corte\0155502-Produção de pintos de um dia\0155505-Produção de ovos\1011201-Frigorífico - abate de bovinos\1012103-Frigorífico - abate de suínos\1066000-Fabricação de alimentos para animais\4623106-Comércio atacadista de sementes, flores, plantas e gramas\4623108-Comércio atacadista de matérias-primas agrícolas com atividade de fracionamento e acondicionamento associada\4632001-Comércio atacadista de cereais e leguminosas beneficiados\4683400-Comércio atacadista de defensivos agrícolas, adubos, fertilizantes e corretivos do solo\4712100-Comércio varejista de mercadorias em geral, com predominância de produtos alimentícios - minimercados, mercearias e armazéns\4722901-Comércio varejista de carnes - açougues\4729699-Comércio varejista de produtos alimentícios em geral ou especializado em produtos alimentícios não especificados anteriormente\5211799-Depósitos de mercadorias para terceiros, exceto armazéns gerais e guarda-móveis | AX35: 252090799 | AY35: N
A36: 07.063.949/0001-80 | B36: BARBIERI TRANSPORTES S/A | D36: GRANDE | E36: 150714292 | F36: 972000 | G36: 113 | H36: 853 | I36: RISCO MUITO BAIXO | J36: ATIVA | K36: 4930201 | L36: Transporte rodoviário de carga, exceto produtos perigosos e mudanças, municipal | M36: 10/18/2004 | N36: 10 | O36: OSLO | P36: 111-D | R36: PASSO DOS FORTES | S36: CHAPECO | T36: SC | U36: 89805110 | V36: 49 | W36: 999780233 | X36: Celular | Y36: 49 | Z36: 999681617 | AA36: Celular | AB36: 49 | AC36: 33214704 | AD36: Fixo | AH36: FISCAL@BLUETRANSPORTES.COM.BR | AK36: MARCOS ANTONIO BARBIERI | AL36: PRESIDENTE | AM36: 49 | AN36: 999876043 | AO36: ROVER JUNIOR SABADINI | AP36: DIRETOR | AQ36: 49 | AR36: 999686642 | AW36: 4930202-Transporte rodoviário de carga, exceto produtos perigosos e mudanças, intermunicipal, interestadual e internacional\5211799-Depósitos de mercadorias para terceiros, exceto armazéns gerais e guarda-móveis\6463800-Outras sociedades de participação, exceto holdings\7719599-Locação de outros meios de transporte não especificados anteriormente, sem condutor | AX36: 254871364 | AY36: N
A37: 47.598.719/0001-30 | B37: NAPPI INDUSTRIA DE METAIS LTDA | D37: MÉDIA | E37: 148486936 | F37: 100000 | G37: 161 | H37: 378 | I37: RISCO MÉDIO | J37: ATIVA | K37: 2452100 | L37: Fundição de metais não ferrosos e suas ligas | M37: 11/13/1981 | N37: 0 | O37: WASHINGTON LUIZ SN | Q37: KM 378 | R37: FAZ BOA ESPERANCA | S37: PINDORAMA | T37: SP | U37: 15830000 | V37: 17 | W37: 996278160 | X37: Celular | Y37: 17 | Z37: 997262519 | AA37: Celular | AH37: FISCAL@NAPPIMETAIS.COM | AI37: REGINALDO@JNAPPI.COM.BR | AK37: REGINALDO CLEBERTY NAPPI | AL37: TITULAR PESSOA FISICA RESIDENTE OU DOMICILIADO NO BRASIL | AW37: 2949299-Fabricação de outras peças e acessórios para veículos automotores não especificadas anteriormente\ | AX37: 529.004.852.113 | AY37: N
A38: 10.576.351/0001-07 | B38: DIX LOGISTICA S/A FALIDO | C38: DIX LOGISTICA | D38: GRANDE | E38: 143094858 | F38: 2310000 | G38: 39 | H38: 138 | I38: RISCO MUITO ALTO | J38: ATIVA | K38: 4930202 | L38: Transporte rodoviário de carga, exceto produtos perigosos e mudanças, intermunicipal, interestadual e internacional | M38: 1/13/2009 | N38: 6 | O38: NEO ALVES MARTINS | P38: 1334 | Q38: ANDAR 4 SALA 042 EDIF EXECUTIVE CENTER | R38: ZONA 03 | S38: MARINGA | T38: PR | U38: 87050110 | V38: 44 | W38: 999045818 | X38: Celular | Y38: 44 | Z38: 991020202 | AA38: Celular | AB38: 44 | AC38: 991653591 | AD38: Celular | AE38: 44 | AF38: 33540698 | AG38: Fixo | AH38: GERENCIA@DIXLOGISTICA.COM.BR | AI38: DIOJANES@DIXLOGISTICA.COM.BR | AK38: DIOJANES VIEIRA DA ANUNCIACAO | AL38: PRESIDENTE | AM38: 44 | AN38: 991020202 | AO38: ANA ELISSA LOPES GARCIA DA ANUNCIACAO | AP38: DIRETOR | AQ38: 44 | AR38: 991440131 | AW38: 4930201-Transporte rodoviário de carga, exceto produtos perigosos e mudanças, municipal\5250804-Organização logística do transporte de carga\7719599-Locação de outros meios de transporte não especificados anteriormente, sem condutor\ | AX38: 90610625-61 | AY38: S
A39: 36.376.804/0001-37 | B39: ARMANI TRANSPORTES S/A | D39: GRANDE | E39: 135460852 | F39: 3509378 | G39: 145 | H39: 880 | I39: RISCO MUITO BAIXO | J39: ATIVA | K39: 4930202 | L39: Transporte rodoviário de carga, exceto produtos perigosos e mudanças, intermunicipal, interestadual e internacional | M39: 8/13/1991 | N39: 12 | O39: BR 101 SN | Q39: KM 378 | R39: TOCAIA | S39: ICONHA | T39: ES | U39: 29280000 | V39: 28 | W39: 999747360 | X39: Celular | Y39: 28 | Z39: 35371103 | AA39: Fixo | AH39: FISCAL@ARMANITRANSPORTE.COM.BR | AI39: EDUARDO@ARMANITRANSPORTE.COM.BR | AJ39: PAULO@ARMANITRANSPORTE.COM.BR | AK39: FERNANDO ARMANI | AL39: PRESIDENTE | AM39: 28 | AN39: 981118118 | AO39: PAULO ARMANI | AP39: DIRETOR | AQ39: 28 | AR39: 999054344 | AW39: 4520001-Serviços de manutenção e reparação mecânica de veículos automotores\4930201-Transporte rodoviário de carga, exceto produtos perigosos e mudanças, municipal\4930203-Transporte rodoviário de produtos perigosos\5211799-Depósitos de mercadorias para terceiros, exceto armazéns gerais e guarda-móveis\5250804-Organização logística do transporte de carga\ | AX39: 081.489.70-6 | AY39: N
A40: 09.329.143/0001-16 | B40: ON TIME EXPRESS LOGISTICA E TRANSPORTES S.A. | D40: GRANDE | E40: 131924296 | F40: 15000000 | G40: 34 | H40: 731 | I40: RISCO MUITO BAIXO | J40: ATIVA | K40: 4930202 | L40: Transporte rodoviário de carga, exceto produtos perigosos e mudanças, intermunicipal, interestadual e internacional | M40: 11/16/2007 | N40: 6 | O40: MADEIRA | P40: 162 | Q40: SALA 803 | R40: ALPHAVILLE CENTRO INDUSTRIAL E EMPRESARIAL/ALPHAVILLE. | S40: BARUERI | T40: SP | U40: 6454010 | V40: 11 | W40: 963772806 | X40: Celular | Y40: 11 | Z40: 973634167 | AA40: Celular | AB40: 11 | AC40: 940226845 | AD40: Celular | AE40: 11 | AF40: 41932703 | AG40: Fixo | AH40: PORTARIAFISCAL@ONTIMELOGISTICA.COM.BR | AI40: RECEPCAO01@ONTIMELOGISTICA.COM.BR | AJ40: CONTROLADORIA01@ONTIMELOGISTICA.COM.BR | AK40: SERGIO MIOZZO ZUFFO | AL40: DIRETOR | AM40: 11 | AN40: 981961102 | AO40: ANTONIO LUIZ CODESPOTI TEIXEIRA DE FREITAS | AP40: DIRETOR | AQ40: 41 | AR40: 999681670 | AW40: 4930201-Transporte rodoviário de carga, exceto produtos perigosos e mudanças, municipal\5250803-Agenciamento de cargas, exceto para o transporte marítimo\5320201-Serviços de malote não realizados pelo Correio Nacional\5320202-Serviços de entrega rápida | AX40: 373.070.010.119 | AY40: N
A41: 78.881.414/0001-64 | B41: TRANSPORTES NATAL LTDA | D41: MÉDIA | E41: 125991332 | F41: 40643908 | G41: 290 | H41: 429 | I41: RISCO MÉDIO | J41: ATIVA | K41: 4930202 | L41: Transporte rodoviário de carga, exceto produtos perigosos e mudanças, intermunicipal, interestadual e internacional | M41: 8/13/1985 | N41: 8 | O41: LUIZ LAZZARIN | P41: 260 | Q41: RIO MARIA | R41: VILA FLORESTA II | S41: CRICIUMA | T41: SC | U41: 88817045 | V41: 48 | W41: 991016864 | X41: Celular | Y41: 48 | Z41: 991133956 | AA41: Celular | AB41: 48 | AC41: 991262526 | AD41: Celular | AE41: 48 | AF41: 34310600 | AG41: Fixo | AH41: DOCUMENTACAO1@TRANSNATAL.COM.BR | AI41: T.NATAL@TERRA.COM.BR | AK41: CELIO RENALDO NATAL | AL41: SOCIO ADMINISTRADOR | AM41: 48 | AN41: 999781741 | AO41: LEVATE HOLDING LTDA | AP41: SOCIO | AQ41: 48 | AR41: 30478150 | AW41: 4511104-Comércio por atacado de caminhões novos e usados\4930201-Transporte rodoviário de carga, exceto produtos perigosos e mudanças, municipal\5211701-Armazéns gerais - emissão de warrant\5212500-Carga e descarga | AX41: 251876950 | AY41: N
A42: 00.148.025/0002-18 | B42: LATASA INDUSTRIA E COMERCIO LTDA. | D42: MÉDIA | E42: 122103228 | F42: 55998000 | G42: 181 | H42: 329 | I42: RISCO MÉDIO | J42: ATIVA | K42: 2452100 | L42: Fundição de metais não ferrosos e suas ligas | M42: 12/5/1996 | N42: 4 | O42: JULIO DE PAULA CLARO | P42: 900 | R42: FEITAL | S42: PINDAMONHANGABA | T42: SP | U42: 12441400 | V42: 12 | W42: 991111756 | X42: Celular | Y42: 12 | Z42: 991111776 | AA42: Celular | AB42: 11 | AC42: 22221085 | AD42: Fixo | AH42: FISCAL@GRUPORECICLABR.COM.BR | AK42: JOSE ROBERTO MARTINEZ DO CANTO | AL42: ADMINISTRADOR | AM42: 11 | AN42: 999006196 | AO42: RECICLA BR S.A. | AP42: SOCIO | AQ42: 11 | AR42: 22221085 | AS42: JRC - CONSULTORIA, ASSESSORIA E PARTICIPACOES LTDA | AT42: SOCIO | AU42: 11 | AV42: 29090229 | AW42: 2441501-Produção de alumínio e suas ligas em formas primárias\3831901-Recuperação de sucatas de alumínio\3831999-Recuperação de materiais metálicos, exceto alumínio\ | AX42: 528.054.280.114 | AY42: S
A43: 70.992.359/0001-78 | B43: FRIDEL FRIGORIFICO INDUSTRIAL DEL REY LTDA | D43: MÉDIA | E43: 118104650 | F43: 4000000 | G43: 2 | H43: 634 | I43: RISCO BAIXO | J43: ATIVA | K43: 1011201 | L43: Frigorífico - abate de bovinos | M43: 4/2/1993 | N43: 1 | O43: DOUTOR ANTONIO CHAGAS DINIZ | P43: 555 | Q43: C SALA 02 | R43: CIDADE INDUSTRIAL | S43: CONTAGEM | T43: MG | U43: 32210160 | V43: 31 | W43: 21298500 | X43: Fixo | AH43: FISCAL@FRIDEL.COM.BR | AK43: FRICON PARTICIPACOES LTDA | AL43: SOCIO | AM43: 31 | AN43: 33634611 | AO43: ROBERTO FERRI AMARAL | AP43: SOCIO ADMINISTRADOR | AQ43: 31 | AR43: 984182828 | AS43: EDUARDO FERRI AMARAL | AT43: ADMINISTRADOR | AU43: 31 | AV43: 999495523 | AW43: 1013901-Fabricação de produtos de carne\1013902-Preparação de subprodutos do abate | AX43: 186833511.00-53 | AY43: N
A44: 01.344.733/0001-06 | B44: EXPRESSO RENOVACAO LTDA | C44: RENOVACAO LOGISTICA | D44: GRANDE | E44: 115739349 | F44: 250000 | G44: 384 | H44: 942 | I44: RISCO MUITO BAIXO | J44: ATIVA | K44: 4930202 | L44: Transporte rodoviário de carga, exceto produtos perigosos e mudanças, intermunicipal, interestadual e internacional | M44: 8/1/1996 | N44: 6 | O44: RUA SANGA FUNDA PORTAO | P44: 86 | Q44: CONDOMINIO LOGISTICO ACORIANOS UNIDADE 20 | R44: FLORESTA | S44: NOVA SANTA RITA | T44: RS | U44: 92480000 | V44: 51 | W44: 997978913 | X44: Celular | Y44: 41 | Z44: 992381879 | AA44: Celular | AB44: 51 | AC44: 992474986 | AD44: Celular | AE44: 51 | AF44: 30329500 | AG44: Fixo | AH44: CONTABILIDADE@RENOVACAOLOGISTICA.COM.BR | AI44: ADEMIR.MOURA@RENOVACAOLOGISTICA.COM.BR | AJ44: ALEX@RENOVACAOLOGISTICA.COM.BR | AK44: ADEMIR JOSE DE MOURA | AL44: TITULAR PESSOA FISICA RESIDENTE OU DOMICILIADO NO BRASIL | AM44: 51 | AN44: 992457154 | AW44: 4930201-Transporte rodoviário de carga, exceto produtos perigosos e mudanças, municipal\5211701-Armazéns gerais - emissão de warrant\5211799-Depósitos de mercadorias para terceiros, exceto armazéns gerais e guarda-móveis\5240199-Atividades auxiliares dos transportes aéreos, exceto operação dos aeroportos e campos de aterrissagem\6810202-Aluguel de imóveis próprios\7719599-Locação de outros meios de transporte não especificados anteriormente, sem condutor | AX44: 382/0022548 | AY44: N
A45: 76.513.324/0001-95 | B45: FRIGORIFICO BIZINELLI LTDA | D45: MÉDIA | E45: 113908558 | F45: 9215617 | G45: 11 | H45: 271 | I45: RISCO ALTO | J45: ATIVA | K45: 1013901 | L45: Fabricação de produtos de carne | M45: 8/28/1966 | N45: 1 | O45: MARIA BIZINELLI | P45: 530 | R45: CAMPO COMPRIDO | S45: CURITIBA | T45: PR | U45: 81210154 | V45: 41 | W45: 991298811 | X45: Celular | Y45: 41 | Z45: 992064479 | AA45: Celular | AB45: 41 | AC45: 991673904 | AD45: Celular | AE45: 41 | AF45: 32743838 | AG45: Fixo | AH45: ANGELOBIZINELLI@ONDA.COM.BR | AK45: LUIZ ROBERTO BIZINELLI | AL45: SOCIO ADMINISTRADOR | AO45: SERGIO LUIZ BIZINELLI | AP45: ADMINISTRADOR | AQ45: 41 | AR45: 996893516 | AS45: PAULA BAGGIO BIZINELLI | AT45: ADMINISTRADOR | AU45: 41 | AV45: 999884195 | AW45: 1012103-Frigorífico - abate de suínos\4634601-Comércio atacadista de carnes bovinas e suínas e derivados\4721103-Comércio varejista de laticínios e frios\4722901-Comércio varejista de carnes - açougues\4723700-Comércio varejista de bebidas\4930201-Transporte rodoviário de carga, exceto produtos perigosos e mudanças, municipal\4930202-Transporte rodoviário de carga, exceto produtos perigosos e mudanças, intermunicipal, interestadual e internacional\ | AX45: 10108955-09 | AY45: N
A46: 14.290.696/0001-42 | B46: FRISACRE FRIGORIFICO SANTO AFONSO DO ACRE LTDA | C46: FRISACRE | D46: MÉDIA | E46: 112836243 | F46: 40000000 | G46: 326 | H46: 833 | I46: RISCO MUITO BAIXO | J46: ATIVA | K46: 1011201 | L46: Frigorífico - abate de bovinos | M46: 11/14/1986 | N46: 6 | O46: BR-364 | Q46: KM 10 | R46: BELO JARDIM II | S46: RIO BRANCO | T46: AC | U46: 69908080 | V46: 68 | W46: 999020958 | X46: Celular | Y46: 68 | Z46: 21067358 | AA46: Fixo | AK46: JOAO GUILHERME YOSHIMATSU FELIX PEREIRA | AL46: SOCIO ADMINISTRADOR | AM46: 14 | AN46: 981566477 | AO46: MURILO LEITE | AP46: SOCIO ADMINISTRADOR | AQ46: 68 | AR46: 999851228 | AS46: ANA MARIA BRONCA FERREIRA PINTO | AT46: SOCIO | AU46: 68 | AV46: 999850080 | AW46: 0151201-Criação de bovinos para corte\1013901-Fabricação de produtos de carne\1013902-Preparação de subprodutos do abate\4623102-Comércio atacadista de couros, lãs, peles e outros subprodutos não comestíveis de origem animal\4634601-Comércio atacadista de carnes bovinas e suínas e derivados\4722901-Comércio varejista de carnes - açougues | AX46: 01.000.221/001-87 | AY46: S
A47: 14.781.303/0001-01 | B47: NAVEMESTRA SERVICOS DE NAVEGACAO LTDA. | D47: GRANDE | E47: 110871873 | F47: 137600098 | G47: 108 | H47: 486 | I47: RISCO MÉDIO | J47: ATIVA | K47: 5030101 | L47: Navegação de apoio marítimo | M47: 12/19/2011 | N47: 15 | O47: LAURO MULLER | P47: 00116 | Q47: SAL 2605 | R47: BOTAFOGO | S47: RIO DE JANEIRO | T47: RJ | U47: 22290160 | V47: 21 | W47: 971657016 | X47: Celular | Y47: 21 | Z47: 998286738 | AA47: Celular | AB47: 21 | AC47: 967017806 | AD47: Celular | AE47: 21 | AF47: 21382214 | AG47: Fixo | AH47: CONTATO@BRAVANTE.COM.BR | AI47: ROBERTA.RODRIGUES@BRAVANTE.COM.BR | AJ47: MARCOS.COSTA@SMIGUEL.COM.BR | AK47: MARCELINO JOSE LOBATO NASCIMENTO | AL47: ADMINISTRADOR | AM47: 21 | AN47: 993829287 | AO47: BRASBUNKER PARTICIPACOES S/A | AP47: SOCIO | AQ47: 21 | AR47: 30327543 | AW47: 3317101-Manutenção e reparação de embarcações e estruturas flutuantes\3319800-Manutenção e reparação de equipamentos e produtos não especificados anteriormente\3600601-Captação, tratamento e distribuição de água\3822000-Tratamento e disposição de resíduos perigosos\3900500-Descontaminação e outros serviços de gestão de resíduos\5011401-Transporte marítimo de cabotagem - Carga\5030103-Serviço de rebocadores e empurradores\5231103-Gestão de terminais aquaviários\6462000-Holdings de instituições não financeiras\7020400-Atividades de consultoria em gestão empresarial, exceto consultoria técnica específica\7490199-Outras atividades profissionais, científicas e técnicas não especificadas anteriormente\ | AX47: 86.735.423 | AY47: S
A48: 96.754.734/0001-35 | B48: UNIDAO TRANSPORTES E LOGISTICA LTDA | D48: GRANDE | E48: 109245401 | F48: 332000 | G48: 190 | H48: 680 | I48: RISCO BAIXO | J48: ATIVA | K48: 4930202 | L48: Transporte rodoviário de carga, exceto produtos perigosos e mudanças, intermunicipal, interestadual e internacional | M48: 5/2/1969 | N48: 8 | O48: NITEROI | P48: 1150 | Q48: CASA | R48: SCHARLAU | S48: SAO LEOPOLDO | T48: RS | U48: 93120030 | V48: 51 | W48: 999989599 | X48: Celular | Y48: 11 | Z48: 942634438 | AA48: Celular | AB48: 11 | AC48: 932460518 | AD48: Celular | AE48: 51 | AF48: 21185600 | AG48: Fixo | AH48: FISCAL@UNIDAO.COM | AI48: FERNANDO@UNIDAO.COM | AJ48: ARIEGI@UNIDAO.COM | AK48: ARCYLDA VERONA DE CESARO PARTICIPACOES SOCIETARIAS LTDA. | AL48: SOCIO | AM48: 51 | AN48: 996993730 | AO48: ELIANE DE CESARO LORENZ | AP48: SOCIO ADMINISTRADOR | AQ48: 51 | AR48: 999739130 | AS48: ADEMIR ANTONIO DORNELLES | AT48: ADMINISTRADOR | AW48: 4686902-Comércio atacadista de embalagens\4729602-Comércio varejista de mercadorias em lojas de conveniência\4731800-Comércio varejista de combustíveis para veículos automotores\4732600-Comércio varejista de lubrificantes\4789099-Comércio varejista de outros produtos não especificados anteriormente\4930201-Transporte rodoviário de carga, exceto produtos perigosos e mudanças, municipal\4930203-Transporte rodoviário de produtos perigosos\5211701-Armazéns gerais - emissão de warrant\5212500-Carga e descarga\5250803-Agenciamento de cargas, exceto para o transporte marítimo | AX48: 124/0036784 | AY48: S
A49: 53.237.962/0001-25 | B49: EMPRESA DE TRANSPORTES PAJUCARA LTDA | D49: GRANDE | E49: 105865231 | F49: 3000000 | G49: 305 | H49: 361 | I49: RISCO MÉDIO | J49: ATIVA | K49: 4930202 | L49: Transporte rodoviário de carga, exceto produtos perigosos e mudanças, intermunicipal, interestadual e internacional | M49: 2/10/1984 | N49: 15 | O49: PASCHOAL THOMEU | P49: 1.141 | Q49: GALPAOMODULOS 14 15 24E25 | R49: VILA NOVA BONSUCESSO | S49: GUARULHOS | T49: SP | U49: 7175090 | V49: 27 | W49: 995146414 | X49: Celular | Y49: 19 | Z49: 996374952 | AA49: Celular | AB49: 19 | AC49: 998466493 | AD49: Celular | AE49: 11 | AF49: 35856900 | AG49: Fixo | AH49: COMPRAS@PAJUNET.COM.BR | AI49: PAULO.SANTOS@PAJUNET.COM.BR | AJ49: RODRIGO.BIANCK@PAJUNET.COM.BR | AK49: ALTAMIR FILADELFI CABRAL | AL49: ADMINISTRADOR | AM49: 11 | AN49: 983240997 | AO49: CBR MOOCA PARTICIPACOES LTDA | AP49: SOCIO | AQ49: 11 | AR49: 33856900 | AS49: TERENA PARTICIPACOES LTDA | AT49: SOCIO | AU49: 11 | AV49: 33856900 | AW49: 4930201-Transporte rodoviário de carga, exceto produtos perigosos e mudanças, municipal\4930203-Transporte rodoviário de produtos perigosos\5211799-Depósitos de mercadorias para terceiros, exceto armazéns gerais e guarda-móveis\5212500-Carga e descarga\8219999-Preparação de documentos e serviços especializados de apoio administrativo não especificados anteriormente\ | AX49: 336.302.826.115 | AY49: N
A50: 49.363.468/0001-30 | B50: REFRIO ARMAZENS GERAIS LTDA. | C50: REFRIO | D50: GRANDE | E50: 102920345 | F50: 8300000 | H50: 596 | I50: RISCO BAIXO | J50: ATIVA | K50: 5211701 | L50: Armazéns gerais - emissão de warrant | M50: 9/22/1977 | N50: 6 | O50: REGIS BITTENCOURT | Q50: KM 293 5 SALA 03 | R50: POTUVERA | S50: ITAPECERICA DA SERRA | T50: SP | U50: 6882700 | V50: 11 | W50: 973295483 | X50: Celular | Y50: 11 | Z50: 970944072 | AA50: Celular | AB50: 11 | AC50: 944918912 | AD50: Celular | AE50: 11 | AF50: 47858555 | AG50: Fixo | AH50: JORGE@REFRIO.COM.BR | AI50: T.SOARES@REFRIO.COM.BR | AK50: REFRIO PARTICIPACOES E SERVICOS LTDA. | AL50: SOCIO | AM50: 11 | AN50: 46663122 | AO50: DANFLARE PARTICIPACOES LTDA | AP50: SOCIO | AS50: REINALDO ANTONIO NAHAS FILHO | AT50: ADMINISTRADOR | AU50: 11 | AV50: 998452530 | AW50: 4930201-Transporte rodoviário de carga, exceto produtos perigosos e mudanças, municipal\4930202-Transporte rodoviário de carga, exceto produtos perigosos e mudanças, intermunicipal, interestadual e internacional\5212500-Carga e descarga\5229099-Outras atividades auxiliares dos transportes terrestres não especificadas anteriormente\5250803-Agenciamento de cargas, exceto para o transporte marítimo\5250804-Organização logística do transporte de carga\7020400-Atividades de consultoria em gestão empresarial, exceto consultoria técnica específica\ | AX50: 370.051.229.111 | AY50: N
A51: 13.177.019/0001-50 | B51: NUTRIAL AGROINDUSTRIAS REUNIDAS S/A | C51: NUTRIAL | D51: GRANDE | E51: 101380062 | F51: 10837924 | H51: 714 | I51: RISCO MUITO BAIXO | J51: ATIVA | K51: 1011201 | L51: Frigorífico - abate de bovinos | M51: 7/26/1979 | N51: 5 | O51: VEREADOR JOAO CALAZANS | P51: 317 | Q51: C | R51: TREZE DE JULHO | S51: ARACAJU | T51: SE | U51: 49020030 | V51: 79 | W51: 33221878 | X51: Fixo | AH51: NUTRIAL@BOL.COM.BR | AI51: JA@FRIGONUTRIAL.COM.BR | AJ51: PATRICIA@FRIGONUTRIAL.COM.BR | AK51: JOAO VICTOR DE MELO BAIA | AL51: CONSELHEIRO DE ADMINISTRACAO | AM51: 82 | AN51: 981457271 | AO51: ADRYANA CAVALCANTE DA SILVA SANTANA | AP51: CONSELHEIRO DE ADMINISTRACAO | AQ51: 82 | AR51: 999193595 | AS51: ERIVAN RODRIGUES DE SANTANA | AT51: PRESIDENTE | AU51: 82 | AV51: 981570110 | AW51: 1011203-Frigorífico - abate de ovinos e caprinos\1012101-Abate de aves\1012102-Abate de pequenos animais\1012103-Frigorífico - abate de suínos\1013901-Fabricação de produtos de carne\1013902-Preparação de subprodutos do abate | AX51: 27.056.543-4 | AY51: N

Sheet GISLAINE
A1: Carteira de Prospects — Vendedor 3
A2: Total de empresas: 47 | Porte: GRANDE | Fonte: Base de prospecção
A4: CNPJ | B4: Razão Social | C4: Nome Fantasia | D4: Porte | E4: Faturamento Presumido (R$) | F4: Capital Social (R$) | G4: Qtd. Funcionários | H4: Score | I4: Classificação de Risco | J4: Situação Cadastral | K4: CNAE | L4: Atividade Principal | M4: Data Abertura | N4: Qtd. Filiais | O4: Logradouro | P4: Nº | Q4: Complemento | R4: Bairro | S4: Cidade | T4: UF | U4: CEP | V4: DDD 1 | W4: Telefone 1 | X4: Tipo 1 | Y4: DDD 2 | Z4: Telefone 2 | AA4: Tipo 2 | AB4: DDD 3 | AC4: Telefone 3 | AD4: Tipo 3 | AE4: DDD 4 | AF4: Telefone 4 | AG4: Tipo 4 | AH4: E-mail 1 | AI4: E-mail 2 | AJ4: E-mail 3 | AK4: Sócio 1 | AL4: Cargo Sócio 1 | AM4: DDD Sócio 1 | AN4: Tel. Sócio 1 | AO4: Sócio 2 | AP4: Cargo Sócio 2 | AQ4: DDD Sócio 2 | AR4: Tel. Sócio 2 | AS4: Sócio 3 | AT4: Cargo Sócio 3 | AU4: DDD Sócio 3 | AV4: Tel. Sócio 3 | AW4: CNAEs Secundários | AX4: Inscrição Estadual | AY4: Flag DAU
A5: 87.546.636/0001-11 | B5: FARINA S.A. COMPONENTES AUTOMOTIVOS | D5: GRANDE | E5: 466722850 | F5: 29200000 | G5: 338 | H5: 787 | I5: RISCO MUITO BAIXO | J5: ATIVA | K5: 2451200 | L5: Fundição de ferro e aço | M5: 8/4/1966 | N5: 1 | O5: CAVALHEIRO JOSE FARINA | P5: 215 | R5: SAO FRANCISCO | S5: BENTO GONCALVES | T5: RS | U5: 95703006 | V5: 51 | W5: 992684839 | X5: Celular | Y5: 54 | Z5: 991564102 | AA5: Celular | AB5: 54 | AC5: 991860472 | AD5: Celular | AE5: 54 | AF5: 21028600 | AG5: Fixo | AH5: CONTABILIDADE@FARINA.COM.BR | AI5: DENISE@FARINA.COM.BR | AK5: ANDRE DREHER GIOVANNINI | AL5: DIRETOR | AM5: 54 | AN5: 996876168 | AO5: ERNY DREHER ANTINOLFI | AP5: PRESIDENTE | AQ5: 54 | AR5: 991121820 | AW5: 2539001-Serviços de usinagem, torneiria e solda\2869100-Fabricação de máquinas e equipamentos para uso industrial específico não especificados anteriormente, peças e acessórios\2943300-Fabricação de peças e acessórios para o sistema de freios de veículos automotores\3314799-Manutenção e reparação de outras máquinas e equipamentos para usos industriais não especificados anteriormente\3511501-Geração de energia elétrica\ | AX5: 010/0000770 | AY5: N
A6: 59.275.289/0001-02 | B6: TRANSPORTADORA TURISTICA BENFICA SA EM RECUPERACAO JUDICIAL | C6: BENFICA | D6: GRANDE | E6: 431291822 | F6: 25800000 | G6: 58 | H6: 948 | I6: RISCO MUITO BAIXO | J6: ATIVA | K6: 4930202 | L6: Transporte rodoviário de carga, exceto produtos perigosos e mudanças, intermunicipal, interestadual e internacional | M6: 8/1/1966 | N6: 3 | O6: ARAGUAIA | P6: 381 | R6: SANTA MARIA | S6: SAO CAETANO DO SUL | T6: SP | U6: 9560580 | V6: 15 | W6: 996684497 | X6: Celular | Y6: 17 | Z6: 997511461 | AA6: Celular | AB6: 11 | AC6: 974228652 | AD6: Celular | AE6: 11 | AF6: 22012221 | AG6: Fixo | AH6: CONTABILIDADE@TTBENFICA.COM.BR | AI6: MAGALI.CHURAI@TTBENFICA.COM.BR | AJ6: FERNANDA.MOURO@TTBENFICA.COM.BR | AK6: CAIO FONTANA CORREA | AL6: DIRETOR | AM6: 11 | AN6: 996919506 | AW6: 4924800-Transporte escolar\4929902-Transporte rodoviário coletivo de passageiros, sob regime de fretamento, intermunicipal, interestadual e internacional\4929999-Outros transportes rodoviários de passageiros não especificados anteriormente\4930203-Transporte rodoviário de produtos perigosos\7711000-Locação de automóveis sem condutor\7719599-Locação de outros meios de transporte não especificados anteriormente, sem condutor | AX6: 636.000.804.110 | AY6: S
A7: 44.411.353/0001-50 | B7: CRAGEA - COMPANHIA REGIONAL DE ARMAZENS GERAIS E ENTREPOSTOS ADUANEIROS | C7: CRAGEA | D7: GRANDE | E7: 414401245 | F7: 29146386 | G7: 246 | H7: 844 | I7: RISCO MUITO BAIXO | J7: ATIVA | K7: 5211799 | L7: Depósitos de mercadorias para terceiros, exceto armazéns gerais e guarda-móveis | M7: 9/6/1973 | N7: 4 | O7: INDIO TIBIRICA | P7: 12000 | Q7: KM 58 | R7: PALMEIRAS DE SAO PAULO | S7: SUZANO | T7: SP | U7: 8630000 | V7: 11 | W7: 999919829 | X7: Celular | Y7: 11 | Z7: 972668459 | AA7: Celular | AB7: 11 | AC7: 994770482 | AD7: Celular | AE7: 11 | AF7: 26094357 | AG7: Fixo | AH7: FABIO.GALVAO@CRAGEA.COM.BR | AI7: JAILSON.SILVA@CRAGEA.COM.BR | AJ7: JEAN.FRANCA@CRAGEA.COM.BR | AK7: MAURILIO HIROMI YOSHITA | AL7: PRESIDENTE | AM7: 11 | AN7: 940819838 | AO7: MAURO SHIGUEMI YOSHITA | AP7: DIRETOR | AQ7: 11 | AR7: 999232160 | AS7: AKICO YOSHITA | AT7: DIRETOR | AX7: 672.016.576.119 | AY7: N
A8: 13.592.092/0001-98 | B8: COMPANHIA EMPORIO DE ARMAZENS GERAIS ALFANDEGADOS | D8: GRANDE | E8: 406984624 | F8: 29650000 | G8: 190 | H8: 884 | I8: RISCO MUITO BAIXO | J8: ATIVA | K8: 5211701 | L8: Armazéns gerais - emissão de warrant | M8: 6/27/1974 | N8: 1 | O8: LUIZ TARQUINIO | P8: 20 | R8: BOA VIAGEM | S8: SALVADOR | T8: BA | U8: 40414120 | V8: 71 | W8: 996693285 | X8: Celular | Y8: 71 | Z8: 996352546 | AA8: Celular | AB8: 71 | AC8: 996823145 | AD8: Celular | AE8: 71 | AF8: 31835192 | AG8: Fixo | AH8: FINANCEIRO@EADIEMPORIO.COM.BR | AK8: GLEIDE CELLI FREITAS LIMA | AL8: PRESIDENTE | AM8: 71 | AN8: 999269630 | AO8: CINTIA FREITAS LIMA MODESTO | AP8: DIRETOR | AQ8: 71 | AR8: 999562533 | AS8: ANTONIO FLORISVALDO TARZAN CARNEIRO LIMA FILHO | AT8: DIRETOR | AU8: 71 | AV8: 999627526 | AW8: 4930202-Transporte rodoviário de carga, exceto produtos perigosos e mudanças, intermunicipal, interestadual e internacional\ | AX8: 070.123.900 | AY8: S
A9: 58.317.751/0001-16 | B9: MOVECTA S.A. | C9: MOVECTA | D9: GRANDE | E9: 388003856 | F9: 69383521 | H9: 924 | I9: RISCO MUITO BAIXO | J9: ATIVA | K9: 5231102 | L9: Atividades do Operador Portuário | M9: 11/16/1987 | N9: 13 | O9: GUARARAPES | P9: 1909 | Q9: ANDAR 9 | R9: BROOKLIN PAULISTA | S9: SAO PAULO | T9: SP | U9: 04561004 | V9: 11 | W9: 30496570 | X9: Fixo | AH9: FISCAL@MOVECTA.COM.BR | AI9: JUAREZ.GONSALVES@LOCALFRIO.COM.BR | AJ9: MAURICIO.SANTOS@LOCALFRIO.COM.BR | AK9: ALCEU RODRIGUES VASONE | AL9: CONSELHEIRO DE ADMINISTRACAO | AM9: 11 | AN9: 984098888 | AO9: JOSE FLORENCIO RODRIGUES NETO | AP9: CONSELHEIRO DE ADMINISTRACAO | AQ9: 74 | AR9: 991917091 | AS9: NICOLAS BORTOLETO OLIVEIRA | AT9: DIRETOR | AU9: 11 | AV9: 972699696 | AW9: 4930201-Transporte rodoviário de carga, exceto produtos perigosos e mudanças, municipal\4930202-Transporte rodoviário de carga, exceto produtos perigosos e mudanças, intermunicipal, interestadual e internacional\4930203-Transporte rodoviário de produtos perigosos\5211701-Armazéns gerais - emissão de warrant\5250801-Comissaria de despachos\5250805-Operador de transporte multimodal - OTM | AX9: 103.859.954.110 | AY9: N
A10: 03.649.445/0001-95 | B10: CBL - COMPANHIA BRASILEIRA DE LOGISTICA S/A | D10: GRANDE | E10: 374003980 | F10: 80607832 | H10: 930 | I10: RISCO MUITO BAIXO | J10: ATIVA | K10: 5231102 | L10: Atividades do Operador Portuário | M10: 2/16/2000 | N10: 3 | O10: MANOEL RIBAS | P10: 966 | R10: MERCES | S10: CURITIBA | T10: PR | U10: 80810000 | V10: 41 | W10: 31567852 | X10: Fixo | AH10: CONTADOR@INTERALLI.COM.BR | AI10: GILMAR@CBLSA.COM.BR | AJ10: CBLSA@IG.COM.BR | AK10: FELIPE SLAVIERO FUMAGALLI | AL10: DIRETOR | AM10: 43 | AN10: 999741354 | AO10: FABRICIO SLAVIERO FUMAGALLI | AP10: DIRETOR | AQ10: 66 | AR10: 999540930 | AS10: CRISTIANO SLAVIERO FUMAGALLI | AT10: DIRETOR | AU10: 43 | AV10: 999579325 | AW10: 4663000-Comércio atacadista de máquinas e equipamentos para uso industrial, partes e peças\4940000-Transporte dutoviário\5211799-Depósitos de mercadorias para terceiros, exceto armazéns gerais e guarda-móveis\5232000-Atividades de agenciamento marítimo\5250801-Comissaria de despachos\5250805-Operador de transporte multimodal - OTM\6810201-Compra e venda de imóveis próprios\6810202-Aluguel de imóveis próprios\7739099-Aluguel de outras máquinas e equipamentos comerciais e industriais não especificados anteriormente, sem operador\ | AX10: 90203406-46 | AY10: N
A11: 02.973.358/0001-26 | B11: BH FOODS COMERCIO E INDUSTRIA LTDA | D11: GRANDE | E11: 364569606 | F11: 2000000 | G11: 359 | H11: 634 | I11: RISCO BAIXO | J11: ATIVA | K11: 1013901 | L11: Fabricação de produtos de carne | M11: 2/9/1999 | N11: 0 | O11: DO SOLDADO | P11: 730 | Q11: GALPAO5 | R11: PEROBAS | S11: CONTAGEM | T11: MG | U11: 32040027 | V11: 31 | W11: 21298500 | X11: Fixo | AH11: FISCAL@BHFOODS.COM.BR | AI11: EDUARDO@BHFOODS.COM.BR | AK11: FRICON PARTICIPACOES LTDA | AL11: SOCIO | AM11: 31 | AN11: 33634611 | AO11: EDUARDO FERRI AMARAL | AP11: SOCIO ADMINISTRADOR | AQ11: 31 | AR11: 999495523 | AS11: ROBERTO FERRI AMARAL | AT11: ADMINISTRADOR | AU11: 31 | AV11: 984182828 | AW11: 1011201-Frigorífico - abate de bovinos\1011203-Frigorífico - abate de ovinos e caprinos\1011204-Frigorífico - abate de bufalinos\1012101-Abate de aves\1012103-Frigorífico - abate de suínos\1013902-Preparação de subprodutos do abate\4634601-Comércio atacadista de carnes bovinas e suínas e derivados\4634602-Comércio atacadista de aves abatidas e derivados\4634603-Comércio atacadista de pescados e frutos do mar\4930201-Transporte rodoviário de carga, exceto produtos perigosos e mudanças, municipal\4930202-Transporte rodoviário de carga, exceto produtos perigosos e mudanças, intermunicipal, interestadual e internacional\5211799-Depósitos de mercadorias para terceiros, exceto armazéns gerais e guarda-móveis\5620101-Fornecimento de alimentos preparados preponderantemente para empresas\ | AX11: 186013086.00-02 | AY11: N
A12: 09.250.869/0001-69 | B12: FRIGORIFICO CARIACICA S.A. | C12: MAFRICAL | D12: GRANDE | E12: 348398647 | F12: 4980000 | G12: 341 | H12: 716 | I12: RISCO MUITO BAIXO | J12: ATIVA | K12: 1011201 | L12: Frigorífico - abate de bovinos | M12: 12/10/2007 | N12: 0 | O12: GOVERNADOR JOSE HENRIQUE SETTE | P12: 2660 | R12: PLANETA | S12: CARIACICA | T12: ES | U12: 29156775 | V12: 27 | W12: 999389538 | X12: Celular | Y12: 27 | Z12: 999361578 | AA12: Celular | AB12: 27 | AC12: 996041850 | AD12: Celular | AE12: 27 | AF12: 33963557 | AG12: Fixo | AH12: CONTABIL01@MAFRICAL.COM.BR | AI12: IRMAOSVAREJAO@UOL.COM.BR | AJ12: ALAN@MAFRICAL.COM.BR | AK12: EDMILSON SIQUEIRA VAREJAO SOBRINHO | AL12: PRESIDENTE | AM12: 27 | AN12: 981322602 | AO12: EDILSON DE SIQUEIRA VAREJAO JUNIOR | AP12: DIRETOR | AQ12: 27 | AR12: 993122196 | AW12: 1011203-Frigorífico - abate de ovinos e caprinos\1011204-Frigorífico - abate de bufalinos\1011205-Matadouro - abate de reses sob contrato, exceto abate de suínos\1012103-Frigorífico - abate de suínos\4634601-Comércio atacadista de carnes bovinas e suínas e derivados\4634602-Comércio atacadista de aves abatidas e derivados\4634699-Comércio atacadista de carnes e derivados de outros animais\ | AX12: 082.505.83-7 | AY12: N
A13: 82.714.783/0001-30 | B13: TRANSOESTE LOGISTICA LTDA | D13: GRANDE | E13: 330898615 | F13: 21680000 | G13: 745 | H13: 749 | I13: RISCO MUITO BAIXO | J13: ATIVA | K13: 4930202 | L13: Transporte rodoviário de carga, exceto produtos perigosos e mudanças, intermunicipal, interestadual e internacional | M13: 10/26/1990 | N13: 5 | O13: BR-163 | Q13: KM118 SALA02200M | R13: PARQUE INDUSTRIAL VETORASSO | S13: RONDONOPOLIS | T13: MT | U13: 78746055 | V13: 66 | W13: 981270425 | X13: Celular | Y13: 66 | Z13: 999120732 | AA13: Celular | AB13: 66 | AC13: 996337414 | AD13: Celular | AE13: 66 | AF13: 34112712 | AG13: Fixo | AH13: CONTADOR@TRANSOESTE.COM.BR | AI13: TRANSOESTE@TRANSOESTE.COM.BR | AJ13: ELIS@TRANSOESTE.COM.BR | AK13: JEAN CARLOS BARBOSA | AL13: SOCIO ADMINISTRADOR | AM13: 66 | AN13: 999847177 | AO13: MARCIO LUIZ BARBOSA | AP13: SOCIO ADMINISTRADOR | AS13: ODAIR JOSE BARBOSA | AT13: SOCIO ADMINISTRADOR | AU13: 66 | AV13: 996480154 | AW13: 4930203-Transporte rodoviário de produtos perigosos\ | AX13: 13.339.380-1 | AY13: N
A14: 30.683.536/0001-10 | B14: ZILLI ARMAZENS GERAIS S.A. | C14: TERCA | D14: GRANDE | E14: 317579169 | F14: 53068659 | G14: 270 | H14: 902 | I14: RISCO MUITO BAIXO | J14: ATIVA | K14: 5211701 | L14: Armazéns gerais - emissão de warrant | M14: 9/3/1986 | N14: 1 | O14: GOVERNADOR MARIO COVAS 1941 | P14: 1941 | Q14: KM 281 3 LOTE 2873 3013 | R14: PADRE MATHIAS | S14: CARIACICA | T14: ES | U14: 29158900 | V14: 27 | W14: 992288690 | X14: Celular | Y14: 27 | Z14: 999548607 | AA14: Celular | AB14: 27 | AC14: 999635764 | AD14: Celular | AE14: 27 | AF14: 33315000 | AG14: Fixo | AH14: DIRETORIA@TERCA.COM.BR | AI14: DIEGO@TERCA.COM.BR | AK14: OSVALDO ANTONIO PAGNUNSSAT ZILLI FILHO | AL14: DIRETOR | AO14: OSVALDO ANTONIO PAGNUNSSAT ZILLI | AP14: PRESIDENTE | AQ14: 62 | AR14: 984259022 | AW14: 5211799-Depósitos de mercadorias para terceiros, exceto armazéns gerais e guarda-móveis\5212500-Carga e descarga\5250801-Comissaria de despachos\5250804-Organização logística do transporte de carga\6463800-Outras sociedades de participação, exceto holdings\6810202-Aluguel de imóveis próprios\7739099-Aluguel de outras máquinas e equipamentos comerciais e industriais não especificados anteriormente, sem operador\ | AX14: 081.127.04-9 | AY14: S
A15: 04.461.341/0001-15 | B15: LIQUIPORT TERMINAL PORTUARIO S.A. | C15: LIQUIPORT | D15: GRANDE | E15: 297155674 | F15: 38195710 | G15: 16 | H15: 759 | I15: RISCO MUITO BAIXO | J15: ATIVA | K15: 5231102 | L15: Atividades do Operador Portuário | M15: 5/10/2001 | N15: 4 | O15: JOSE DAVID MOSCON | P15: 105 | R15: PAUL | S15: VILA VELHA | T15: ES | U15: 29115095 | V15: 27 | W15: 34222300 | X15: Fixo | AH15: ADMINISTRATIVO@LIQUIPORT.COM.BR | AI15: MLUIZ@LIQUIPORT.COM.BR | AJ15: HAROLDO@LIQUIPORT.COM.BR | AK15: EDUARDO AUGUSTO NUNES | AL15: DIRETOR | AM15: 21 | AN15: 967052786 | AW15: 5211701-Armazéns gerais - emissão de warrant\5212500-Carga e descarga | AX15: 082.558.53-1 | AY15: S
A16: 02.225.085/0001-31 | B16: FRIGORIFICO ELGOLLI LTDA | D16: MÉDIA | E16: 286571097 | F16: 820000 | G16: 319 | H16: 407 | I16: RISCO MÉDIO | J16: ATIVA | K16: 1011201 | L16: Frigorífico - abate de bovinos | M16: 10/22/1997 | N16: 3 | O16: KARL BAASCH | P16: 272 | R16: CENTRO | S16: TAIO | T16: SC | U16: 89190000 | V16: 47 | W16: 992434675 | X16: Celular | Y16: 47 | Z16: 991276855 | AA16: Celular | AB16: 47 | AC16: 992054059 | AD16: Celular | AE16: 47 | AF16: 35312866 | AG16: Fixo | AH16: TI@FRIGORIFICOELGOLLI.COM.BR | AK16: 10 HOLDING S.A. | AL16: SOCIO | AO16: EDUARDO ALBERTO ERN | AP16: ADMINISTRADOR | AQ16: 47 | AR16: 991212008 | AW16: 0151201-Criação de bovinos para corte\1012101-Abate de aves\1012103-Frigorífico - abate de suínos\1013901-Fabricação de produtos de carne\1013902-Preparação de subprodutos do abate\1043100-Fabricação de margarina e outras gorduras vegetais e de óleos não comestíveis de animais\4634601-Comércio atacadista de carnes bovinas e suínas e derivados\4634699-Comércio atacadista de carnes e derivados de outros animais\4722901-Comércio varejista de carnes - açougues\4930202-Transporte rodoviário de carga, exceto produtos perigosos e mudanças, intermunicipal, interestadual e internacional\5211799-Depósitos de mercadorias para terceiros, exceto armazéns gerais e guarda-móveis\ | AX16: 253589940 | AY16: N
A17: 83.834.101/0001-95 | B17: PALMASOLA S A MADEIRAS E AGRICULTURA | D17: GRANDE | E17: 279623796 | F17: 30123450 | G17: 400 | H17: 926 | I17: RISCO MUITO BAIXO | J17: ATIVA | K17: 4930202 | L17: Transporte rodoviário de carga, exceto produtos perigosos e mudanças, intermunicipal, interestadual e internacional | M17: 11/24/1955 | N17: 6 | O17: CRESTANI | P17: 515 | Q17: SERRARIA UM | R17: CENTRO | S17: PALMA SOLA | T17: SC | U17: 89985000 | V17: 49 | W17: 991357132 | X17: Celular | Y17: 49 | Z17: 991552651 | AA17: Celular | AB17: 49 | AC17: 991254612 | AD17: Celular | AE17: 49 | AF17: 36523000 | AG17: Fixo | AH17: EDEMAR@PALMASOLA.COM.BR | AI17: GABRIEL@PALMASOLA.COM.BR | AJ17: MARCELO@PALMASOLA.COM.BR | AK17: MARCELO VISSOTO | AL17: DIRETOR | AM17: 49 | AN17: 991278562 | AO17: LUIZ CARLOS REIS DE TOLEDO BARROS | AP17: DIRETOR | AQ17: 41 | AR17: 996898620 | AW17: 0111301-Cultivo de arroz\0111302-Cultivo de milho\0111303-Cultivo de trigo\0115600-Cultivo de soja\0151201-Criação de bovinos para corte\0210107-Extração de madeira em florestas plantadas\1610203-Serrarias com desdobramento de madeira em bruto\1610204-Serrarias sem desdobramento de madeira em bruto - Resseragem\1621800-Fabricação de madeira laminada e de chapas de madeira compensada, prensada e aglomerada\4622200-Comércio atacadista de soja\4623101-Comércio atacadista de animais vivos\4632001-Comércio atacadista de cereais e leguminosas beneficiados\4731800-Comércio varejista de combustíveis para veículos automotores\4732600-Comércio varejista de lubrificantes\4789099-Comércio varejista de outros produtos não especificados anteriormente\6810201-Compra e venda de imóveis próprios\6810202-Aluguel de imóveis próprios\6810203-Loteamento de imóveis próprios | AX17: 250163950 | AY17: N
A18: 04.660.028/0001-06 | B18: MECALUX DO BRASIL SISTEMAS DE ARMAZENAGEM LTDA. | D18: MÉDIA | E18: 274501222 | F18: 34983860 | G18: 172 | H18: 306 | I18: RISCO MÉDIO | J18: ATIVA | K18: 2511000 | L18: Fabricação de estruturas metálicas | M18: 8/23/2001 | N18: 0 | O18: FRANCISCO RIBERAS PAMPLIEGA | P18: 35 | Q18: GALPAO B | R18: JARDIM NOVA EUROPA | S18: HORTOLANDIA | T18: SP | U18: 13184891 | V18: 27 | W18: 996131898 | X18: Celular | Y18: 19 | Z18: 992314374 | AA18: Celular | AB18: 19 | AC18: 991129844 | AD18: Celular | AE18: 19 | AF18: 38096800 | AG18: Fixo | AH18: JOAO.FERREIRA@MECALUX.COM | AK18: MECALUX SERVIS SA | AL18: SOCIO PESSOA JURIDICA DOMICILIADO NO EXTERIOR | AO18: MECALUX S.A. | AP18: SOCIO PESSOA JURIDICA DOMICILIADO NO EXTERIOR | AS18: IVAN POBLET MENENDEZ | AT18: ADMINISTRADOR | AU18: 19 | AV18: 981131031 | AW18: 3102100-Fabricação de móveis com predominância de metal\3314708-Manutenção e reparação de máquinas, equipamentos e aparelhos para transporte e elevação de cargas\4292801-Montagem de estruturas metálicas\6204000-Consultoria em tecnologia da informação | AX18: 748.112.152.118 | AY18: N
A19: 67.671.222/0001-07 | B19: FRANGOESTE AVICULTURA LTDA | D19: GRANDE | E19: 267804942 | F19: 39000000 | G19: 712 | H19: 758 | I19: RISCO MUITO BAIXO | J19: ATIVA | K19: 1012101 | L19: Abate de aves | M19: 3/13/1992 | N19: 2 | O19: MAL RONDON SN | Q19: KM 159 | R19: BARRA FUNDA | S19: TIETE | T19: SP | U19: 18530000 | V19: 15 | W19: 997277429 | X19: Celular | Y19: 15 | Z19: 996565222 | AA19: Celular | AB19: 15 | AC19: 996914727 | AD19: Celular | AE19: 15 | AF19: 33639600 | AG19: Fixo | AH19: CARLOSALBERTO@FRANGOESTE.COM.BR | AI19: AGNALDO.GONCALVES@FRANGOESTE.COM.BR | AJ19: CRISTIANE.AMORIM@FRANGOESTE.COM.BR | AK19: ZANCHETTA ALIMENTOS LTDA | AL19: SOCIO | AM19: 15 | AN19: 33639600 | AO19: JOSE CARLOS ZANCHETTA | AP19: ADMINISTRADOR | AQ19: 15 | AR19: 991026532 | AS19: RENATA DOS SANTOS ZANCHETTA TEIXEIRA DE CAMARGO | AT19: ADMINISTRADOR | AU19: 19 | AV19: 996449061 | AW19: 1013901-Fabricação de produtos de carne\1013902-Preparação de subprodutos do abate\4634601-Comércio atacadista de carnes bovinas e suínas e derivados\4634602-Comércio atacadista de aves abatidas e derivados\4722901-Comércio varejista de carnes - açougues\5211799-Depósitos de mercadorias para terceiros, exceto armazéns gerais e guarda-móveis | AX19: 692.006.159.115 | AY19: N
A20: 11.671.820/0001-21 | B20: DOMART ALIMENTOS LTDA | C20: DOMART ALIMENTOS | D20: GRANDE | E20: 261397377 | F20: 36000000 | G20: 575 | H20: 767 | I20: RISCO MUITO BAIXO | J20: ATIVA | K20: 1012101 | L20: Abate de aves | M20: 3/3/2010 | N20: 2 | O20: JOAO BATISTA KLEIN SN | Q20: KM 2 | R20: SOIDO DE BAIXO | S20: MARECHAL FLORIANO | T20: ES | U20: 29255000 | V20: 27 | W20: 998360345 | X20: Celular | Y20: 27 | Z20: 997973099 | AA20: Celular | AB20: 27 | AC20: 999465210 | AD20: Celular | AE20: 27 | AF20: 32881325 | AG20: Fixo | AH20: COMPRAS@OIFRANGO.COM.BR | AI20: EDUARDO@OIFRANGO.COM.BR | AJ20: GUSTAVO@OIFRANGO.COM.BR | AK20: OSORIO SCHNEIDER | AL20: SOCIO | AM20: 27 | AN20: 996581325 | AO20: ODERLI SCHNEIDER | AP20: SOCIO ADMINISTRADOR | AQ20: 27 | AR20: 999711311 | AS20: ITAMAR KLEIN | AT20: SOCIO | AU20: 27 | AV20: 999977998 | AW20: 0155501-Criação de frangos para corte\0161099-Atividades de apoio à agricultura não especificadas anteriormente\1013901-Fabricação de produtos de carne\1013902-Preparação de subprodutos do abate\1066000-Fabricação de alimentos para animais\4633802-Comércio atacadista de aves vivas e ovos | AX20: 082.815.58-5 | AY20: N
A21: 17.283.362/0001-30 | B21: PRIME CATER COMERCIAL DE PRODUTOS ALIMENTICIOS S.A. | D21: GRANDE | E21: 252718365 | F21: 19754000 | G21: 212 | H21: 931 | I21: RISCO MUITO BAIXO | J21: ATIVA | K21: 1013901 | L21: Fabricação de produtos de carne | M21: 9/18/2012 | N21: 2 | O21: JOAQUIM SIMOES | P21: 350 | Q21: GALPAO I | R21: JD VERA CRUZ | S21: LOUVEIRA | T21: SP | U21: 13290000 | V21: 19 | W21: 31410369 | X21: Fixo | AH21: CONTAS-PAGAR@PMCT.COM.BR | AK21: MARCELO VAZ SHIMBO | AL21: DIRETOR | AM21: 11 | AN21: 996550481 | AO21: MARIA EUGENIA JUNIA CAMPACCI AMARAL ROCHA | AP21: CONSELHEIRO DE ADMINISTRACAO | AQ21: 11 | AR21: 998694242 | AS21: ANDRE OLIVEIRA PEROSA | AT21: CONSELHEIRO DE ADMINISTRACAO | AU21: 11 | AV21: 981445820 | AW21: 4634601-Comércio atacadista de carnes bovinas e suínas e derivados\4634699-Comércio atacadista de carnes e derivados de outros animais\4635499-Comércio atacadista de bebidas não especificadas anteriormente\4637199-Comércio atacadista especializado em outros produtos alimentícios não especificados anteriormente\4649499-Comércio atacadista de outros equipamentos e artigos de uso pessoal e doméstico não especificados anteriormente\4687701-Comércio atacadista de resíduos de papel e papelão\4712100-Comércio varejista de mercadorias em geral, com predominância de produtos alimentícios - minimercados, mercearias e armazéns\4722901-Comércio varejista de carnes - açougues\4723700-Comércio varejista de bebidas\4729699-Comércio varejista de produtos alimentícios em geral ou especializado em produtos alimentícios não especificados anteriormente\4759899-Comércio varejista de outros artigos de uso doméstico não especificados anteriormente\4761001-Comércio varejista de livros\4789099-Comércio varejista de outros produtos não especificados anteriormente\5212500-Carga e descarga\5620102-Serviços de alimentação para eventos e recepções - bufê\ | AX21: 421.024.463.119 | AY21: N
A22: 02.483.898/0001-21 | B22: FUNDICAO MORENO LTDA | D22: MÉDIA | E22: 235000945 | F22: 30000000 | G22: 274 | H22: 583 | I22: RISCO BAIXO | J22: ATIVA | K22: 2451200 | L22: Fundição de ferro e aço | M22: 4/23/1998 | N22: 0 | O22: ADAMO MELONI | P22: 1150 | Q22: CX POSTAL 530 | R22: SETOR INDUSTRIAL | S22: SERTAOZINHO | T22: SP | U22: 14175000 | V22: 16 | W22: 997029914 | X22: Celular | Y22: 16 | Z22: 997339223 | AA22: Celular | AB22: 16 | AC22: 996429635 | AD22: Celular | AE22: 16 | AF22: 39465000 | AG22: Fixo | AH22: JACQUELINE.OLIVEIRA@MORENO.IND.BR | AI22: FUNDICAOMORENO@MORENO.IND.BR | AJ22: DANIELA.HONORATO@MORENO.IND.BR | AK22: CLAUDIO RODOLFO SCHMIDT | AL22: ADMINISTRADOR | AM22: 11 | AN22: 989375551 | AO22: MORENO PARTICIPACOES E EQUIPAMENTOS INDUSTRIAIS LTDA | AP22: SOCIO | AQ22: 16 | AR22: 39465019 | AS22: LUIS GUSTAVO POSSOS | AT22: ADMINISTRADOR | AU22: 16 | AV22: 999929953 | AW22: 2862300-Fabricação de máquinas e equipamentos para as indústrias de alimentos, bebidas e fumo, peças e acessórios\2869100-Fabricação de máquinas e equipamentos para uso industrial específico não especificados anteriormente, peças e acessórios\3314799-Manutenção e reparação de outras máquinas e equipamentos para usos industriais não especificados anteriormente\7120100-Testes e análises técnicas | AX22: 664.064.334.112 | AY22: N
A23: 60.972.585/0001-33 | B23: TRANSREMOCAO TRANSPORTES PESADOS, REMOCOES TECNICAS E ARMAZENAMENTO LTDA. | D23: MÉDIA | E23: 224670294 | F23: 20000000 | G23: 160 | H23: 725 | I23: RISCO MUITO BAIXO | J23: ATIVA | K23: 4930202 | L23: Transporte rodoviário de carga, exceto produtos perigosos e mudanças, intermunicipal, interestadual e internacional | M23: 1/26/1970 | N23: 2 | O23: MAESTRO GABRIEL MIGLIORI | P23: 465 | R23: JARDIM PEREIRA LEITE | S23: SAO PAULO | T23: SP | U23: 2712140 | V23: 11 | W23: 940025007 | X23: Celular | Y23: 11 | Z23: 991702789 | AA23: Celular | AB23: 11 | AC23: 991414687 | AD23: Celular | AE23: 11 | AF23: 39339497 | AG23: Fixo | AH23: DIRETORIA1@TRANSREMOCAO.COM.BR | AI23: FINANCEIRO@TRANSREMOCAO.COM.BR | AJ23: FATURAMENTO@TRANSREMOCAO.COM.BR | AK23: PEDRO JOSE GAIA | AL23: SOCIO ADMINISTRADOR | AM23: 11 | AN23: 999325924 | AO23: ALEANDRA CUSTODIO GAIA | AP23: SOCIO-ADMINISTRADOR | AW23: 4930201-Transporte rodoviário de carga, exceto produtos perigosos e mudanças, municipal\5211799-Depósitos de mercadorias para terceiros, exceto armazéns gerais e guarda-móveis\5229099-Outras atividades auxiliares dos transportes terrestres não especificadas anteriormente\7112000-Serviços de engenharia | AX23: 108.265.110.112 | AY23: N
A24: 04.567.650/0001-74 | B24: LOCALIX SERVICOS AMBIENTAIS S.A. | C24: LOCALIX | D24: GRANDE | E24: 219249373 | F24: 35000000 | G24: 1039 | H24: 918 | I24: RISCO MUITO BAIXO | J24: ATIVA | K24: 4930202 | L24: Transporte rodoviário de carga, exceto produtos perigosos e mudanças, intermunicipal, interestadual e internacional | M24: 7/25/2001 | N24: 6 | O24: HALLEY | P24: 321 | R24: JARDIM RIACHO DAS PEDRAS | S24: CONTAGEM | T24: MG | U24: 32242270 | V24: 31 | W24: 998378905 | X24: Celular | Y24: 31 | Z24: 993760204 | AA24: Celular | AB24: 31 | AC24: 995732173 | AD24: Celular | AE24: 31 | AF24: 33332969 | AG24: Fixo | AH24: CONTABILIDADE@LOCALIX.COM.BR | AI24: BARBARA@LOCALIX.COM.BR | AJ24: BRUNO.MUNIZ@LOCALIX.COM.BR | AK24: MARCOS LEANDRO GUALBERTO LOPES | AL24: DIRETOR | AM24: 31 | AN24: 984475476 | AO24: DANIEL PRATES RIBEIRO | AP24: PRESIDENTE | AQ24: 38 | AR24: 997490029 | AW24: 2930101-Fabricação de cabines, carrocerias e reboques para caminhões\3811400-Coleta de resíduos não perigosos\3821100-Tratamento e disposição de resíduos não perigosos\3822000-Tratamento e disposição de resíduos perigosos\4213800-Obras de urbanização - ruas, praças e calçadas\4222701-Construção de redes de abastecimento de água, coleta de esgoto e construções correlatas, exceto obras de irrigação\4520001-Serviços de manutenção e reparação mecânica de veículos automotores\4520005-Serviços de lavagem, lubrificação e polimento de veículos automotores\4930201-Transporte rodoviário de carga, exceto produtos perigosos e mudanças, municipal\5222200-Terminais rodoviários e ferroviários\5239799-Atividades auxiliares dos transportes aquaviários não especificadas anteriormente\5240199-Atividades auxiliares dos transportes aéreos, exceto operação dos aeroportos e campos de aterrissagem\5250804-Organização logística do transporte de carga\7112000-Serviços de engenharia\7719599-Locação de outros meios de transporte não especificados anteriormente, sem condutor\7732201-Aluguel de máquinas e equipamentos para construção sem operador, exceto andaimes\8129000-Atividades de limpeza não especificadas anteriormente\8130300-Atividades paisagísticas | AX24: 186997700.00-61 | AY24: N
A25: 20.723.631/0001-46 | B25: TRANSPORTADORA FIGUEIREDO LTDA | D25: MÉDIA | E25: 205704913 | F25: 19125650 | G25: 33 | H25: 288 | I25: RISCO ALTO | J25: ATIVA | K25: 4930202 | L25: Transporte rodoviário de carga, exceto produtos perigosos e mudanças, intermunicipal, interestadual e internacional | M25: 1/11/1985 | N25: 5 | O25: JUSCELINO KUBITSCHEK DE OLIVEIRA | P25: 410 | R25: NS DO CARMO | S25: PARAOPEBA | T25: MG | U25: 35774000 | V25: 31 | W25: 910000000 | X25: Celular | Y25: 31 | Z25: 997712121 | AA25: Celular | AB25: 31 | AC25: 999153143 | AD25: Celular | AE25: 31 | AF25: 37144942 | AG25: Fixo | AH25: LUCIANO@TRANSPORTADORAFIGUEIREDO.COM.BR | AK25: MARCOS ANTONIO DE FIGUEIREDO | AL25: SOCIO | AM25: 31 | AN25: 999863877 | AO25: CELMA DA SILVA FIGUEIREDO | AP25: SOCIO | AQ25: 31 | AR25: 996340680 | AS25: LUCIANO DA SILVA FIGUEIREDO | AT25: ADMINISTRADOR | AU25: 31 | AV25: 998356791 | AW25: 4663000-Comércio atacadista de máquinas e equipamentos para uso industrial, partes e peças\4930201-Transporte rodoviário de carga, exceto produtos perigosos e mudanças, municipal\4930203-Transporte rodoviário de produtos perigosos\5211799-Depósitos de mercadorias para terceiros, exceto armazéns gerais e guarda-móveis\7020400-Atividades de consultoria em gestão empresarial, exceto consultoria técnica específica\7711000-Locação de automóveis sem condutor\7732201-Aluguel de máquinas e equipamentos para construção sem operador, exceto andaimes\8211300-Serviços combinados de escritório e apoio administrativo | AX25: 474644130.00-40 | AY25: N
A26: 20.177.671/0001-30 | B26: TRANSPORTES E CONSTRUCOES LTDA | C26: TCX | D26: GRANDE | E26: 203370926 | F26: 8000000 | G26: 92 | H26: 864 | I26: RISCO MUITO BAIXO | J26: ATIVA | K26: 4930202 | L26: Transporte rodoviário de carga, exceto produtos perigosos e mudanças, intermunicipal, interestadual e internacional | M26: 10/1/1984 | N26: 5 | O26: IMBIARA | P26: 260 | Q26: LOJA 04 | R26: CENTRO | S26: ARAXA | T26: MG | U26: 38183244 | V26: 34 | W26: 998112126 | X26: Celular | Y26: 34 | Z26: 999555145 | AA26: Celular | AB26: 34 | AC26: 998386061 | AD26: Celular | AE26: 34 | AF26: 36696524 | AG26: Fixo | AH26: COMPRAS.TRANSCOL@TERRA.COM.BR | AI26: AMANDA.VAZ@MINAX.COM.BR | AJ26: ANTONIO@MINAX.COM.BR | AK26: ANTONIO ASSIS ABDO | AL26: SOCIO ADMINISTRADOR | AM26: 34 | AN26: 991121104 | AO26: ANTONIO ASSIS ABDO JUNIOR | AP26: SOCIO ADMINISTRADOR | AQ26: 34 | AR26: 984015301 | AW26: 0990402-Atividades de apoio à extração de minerais metálicos não ferrosos\4299599-Outras obras de engenharia civil não especificadas anteriormente\4313400-Obras de terraplenagem\4929999-Outros transportes rodoviários de passageiros não especificados anteriormente\4930201-Transporte rodoviário de carga, exceto produtos perigosos e mudanças, municipal\4930203-Transporte rodoviário de produtos perigosos\5250803-Agenciamento de cargas, exceto para o transporte marítimo\7820500-Locação de mão de obra temporária | AX26: 040551063.00-38 | AY26: N
A27: 07.125.452/0001-49 | B27: INOVA AMBIENTAL ASSESSORIA E COMERCIO S/A | C27: INOVA AMBIENTAL | D27: GRANDE | E27: 198143198 | F27: 12200000 | G27: 889 | H27: 808 | I27: RISCO MUITO BAIXO | J27: ATIVA | K27: 4930202 | L27: Transporte rodoviário de carga, exceto produtos perigosos e mudanças, intermunicipal, interestadual e internacional | M27: 11/12/2004 | N27: 2 | O27: PROFESSOR HELENO CLAUDIO FRAGOSO | P27: 330 | R27: MOQUETA | S27: NOVA IGUACU | T27: RJ | U27: 26285015 | V27: 21 | W27: 976745669 | X27: Celular | Y27: 21 | Z27: 26648474 | AA27: Fixo | AH27: INOVA@INOVAAMBIENTAL.COM | AI27: EDUARDOTAVARES@INOVAAMBIENTAL.COM | AJ27: ALEXANDRE@INOVAAMBIENTAL.COM | AK27: CRISTIANO DE LIMA DAVID | AL27: DIRETOR | AM27: 21 | AN27: 999202204 | AO27: LAIZE DOS SANTOS PEREIRA | AP27: DIRETOR | AQ27: 21 | AR27: 981620975 | AW27: 3811400-Coleta de resíduos não perigosos\3812200-Coleta de resíduos perigosos\3821100-Tratamento e disposição de resíduos não perigosos\4222701-Construção de redes de abastecimento de água, coleta de esgoto e construções correlatas, exceto obras de irrigação\4321500-Instalação e manutenção elétrica\4330404-Serviços de pintura de edifícios em geral\4399103-Obras de alvenaria\4520001-Serviços de manutenção e reparação mecânica de veículos automotores\4923002-Serviço de transporte de passageiros - locação de automóveis com motorista\4930201-Transporte rodoviário de carga, exceto produtos perigosos e mudanças, municipal\4930203-Transporte rodoviário de produtos perigosos\5212500-Carga e descarga\7112000-Serviços de engenharia\7711000-Locação de automóveis sem condutor\7719599-Locação de outros meios de transporte não especificados anteriormente, sem condutor\7739099-Aluguel de outras máquinas e equipamentos comerciais e industriais não especificados anteriormente, sem operador\8111700-Serviços combinados para apoio a edifícios, exceto condomínios prediais\8129000-Atividades de limpeza não especificadas anteriormente\8130300-Atividades paisagísticas\ | AX27: 77.854.266 | AY27: S
A28: 81.075.137/0001-07 | B28: AGUIA SISTEMAS DE ARMAZENAGEM LTDA | D28: GRANDE | E28: 193264935 | F28: 66993040 | G28: 722 | H28: 813 | I28: RISCO MUITO BAIXO | J28: ATIVA | K28: 2511000 | L28: Fabricação de estruturas metálicas | M28: 11/24/1988 | N28: 5 | O28: SENADOR FLAVIO CARVALHO GUIMARAES | P28: 3505 | Q28: CXPST 1618 CEP 84071 980 | R28: BOA VISTA | S28: PONTA GROSSA | T28: PR | U28: 84072190 | V28: 42 | W28: 999196669 | X28: Celular | Y28: 41 | Z28: 991032518 | AA28: Celular | AB28: 51 | AC28: 998263782 | AD28: Celular | AE28: 44 | AF28: 32202666 | AG28: Fixo | AH28: NFERECEBIMENTO@AGUIASISTEMAS.COM.BR | AI28: CARLOS.WIECHETECK@AGUIASISTEMAS.COM | AJ28: DIOGO.AMARAL@AGUIASISTEMAS.COM | AK28: FERDINANDO SCHEFFER JUNIOR | AL28: DIRETOR | AM28: 42 | AN28: 984244793 | AO28: ROGERIO SCHEFFER | AP28: PRESIDENTE | AQ28: 42 | AR28: 999933333 | AS28: JOAO FRANCISCO MIRANDA RIBAS | AT28: DIRETOR | AU28: 42 | AV28: 991151132 | AW28: 1610203-Serrarias com desdobramento de madeira em bruto\1623400-Fabricação de artefatos de tanoaria e de embalagens de madeira\1629301-Fabricação de artefatos diversos de madeira, exceto móveis\2330302-Fabricação de artefatos de cimento para uso na construção\2330305-Preparação de massa de concreto e argamassa para construção\2822402-Fabricação de máquinas, equipamentos e aparelhos para transporte e elevação de cargas, peças e acessórios\3314708-Manutenção e reparação de máquinas, equipamentos e aparelhos para transporte e elevação de cargas\4292801-Montagem de estruturas metálicas\4744099-Comércio varejista de materiais de construção em geral\6202300-Desenvolvimento e licenciamento de programas de computador customizáveis\6209100-Suporte técnico, manutenção e outros serviços em tecnologia da informação\7020400-Atividades de consultoria em gestão empresarial, exceto consultoria técnica específica\7112000-Serviços de engenharia\7739099-Aluguel de outras máquinas e equipamentos comerciais e industriais não especificados anteriormente, sem operador\8211300-Serviços combinados de escritório e apoio administrativo\8599604-Treinamento em desenvolvimento profissional e gerencial | AX28: 20104146-55 | AY28: N
A29: 05.075.152/0001-77 | B29: MUNDIAL LOGISTICA INTEGRADA LTDA | D29: GRANDE | E29: 188165279 | F29: 1040000 | G29: 399 | H29: 485 | I29: RISCO MÉDIO | J29: ATIVA | K29: 5211701 | L29: Armazéns gerais - emissão de warrant | M29: 4/4/2002 | N29: 2 | O29: VELHA GUARULHOS-SAO MIGUEL | P29: 1971 | R29: JARDIM ARAPONGAS | S29: GUARULHOS | T29: SP | U29: 7210250 | V29: 11 | W29: 932362140 | X29: Celular | Y29: 11 | Z29: 947032721 | AA29: Celular | AB29: 11 | AC29: 976973510 | AD29: Celular | AE29: 11 | AF29: 23492185 | AG29: Fixo | AH29: FISCAL.SP@MUNDIALLOGISTICS.COM.BR | AI29: ALEXANDRE.FERREIRA@MUNDIALLOGISTICS.COM.BR | AJ29: FINANCEIRO@MUNDIALWEB.COM.BR | AK29: PAULA CRISTINA ARMANI | AL29: SOCIO ADMINISTRADOR | AM29: 11 | AN29: 983565559 | AO29: M ONE SOLUCOES PARA O PONTO DE VENDA LTDA | AP29: SOCIO | AQ29: 11 | AR29: 23492185 | AS29: FERNANDO PASSOS | AT29: SOCIO-ADMINISTRADOR | AU29: 11 | AV29: 999023095 | AW29: 4930201-Transporte rodoviário de carga, exceto produtos perigosos e mudanças, municipal\4930202-Transporte rodoviário de carga, exceto produtos perigosos e mudanças, intermunicipal, interestadual e internacional\4930203-Transporte rodoviário de produtos perigosos\5211799-Depósitos de mercadorias para terceiros, exceto armazéns gerais e guarda-móveis\5240199-Atividades auxiliares dos transportes aéreos, exceto operação dos aeroportos e campos de aterrissagem\5250804-Organização logística do transporte de carga\5250805-Operador de transporte multimodal - OTM\8292000-Envasamento e empacotamento sob contrato | AX29: 336.693.230.111 | AY29: N
A30: 04.364.144/0001-88 | B30: LABORDE SERVICOS MARITIMOS LTDA. | D30: MÉDIA | E30: 181267521 | F30: 98630647 | H30: 87 | I30: RISCO MUITO ALTO | J30: ATIVA | K30: 5030101 | L30: Navegação de apoio marítimo | M30: 3/28/2001 | N30: 1 | O30: SAO CRISTOVAO | P30: 5 | Q30: SALA506 | R30: SAO CRISTOVAO | S30: RIO DE JANEIRO | T30: RJ | U30: 20940000 | V30: 21 | W30: 38494500 | X30: Fixo | AH30: JANUARIOEMMERICK@HOTMAIL.COM | AI30: CARLOSMANO@LABORDE.COM.BR | AK30: LABORDE MARINE INTERNATIONAL, LLC | AL30: SOCIO PESSOA JURIDICA DOMICILIADO NO EXTERIOR | AO30: PHOENIX NAVEGACAO LTDA | AP30: SOCIO | AQ30: 21 | AR30: 38494500 | AS30: THOMAS ANTHONY LUSCO | AT30: ADMINISTRADOR | AW30: 0910600-Atividades de apoio à extração de petróleo e gás natural\3317101-Manutenção e reparação de embarcações e estruturas flutuantes\5239799-Atividades auxiliares dos transportes aquaviários não especificadas anteriormente\7719501-Locação de embarcações sem tripulação, exceto para finsrecreativos\7739001-Aluguel de máquinas e equipamentos para extração de minérios e petróleo, sem operador\ | AX30: 77.227.733 | AY30: S
A31: 36.858.520/0001-87 | B31: GRAVIA ESQUALITY INDUSTRIA METALURGICA LTDA - EM RECUPERACAO JUDICIAL | D31: MÉDIA | E31: 174291702 | F31: 33430000 | G31: 58 | H31: 49 | I31: RISCO MUITO ALTO | J31: ATIVA | K31: 2512800 | L31: Fabricação de esquadrias de metal | M31: 6/11/1991 | N31: 0 | O31: VP 2E | Q31: QUADRA03 MODULO 07 A | R31: DISTRITO AGROINDUSTRIAL DE ANAPOLIS | S31: ANAPOLIS | T31: GO | U31: 75132050 | V31: 62 | W31: 33108810 | X31: Fixo | AH31: MARCIA.ARAUJO@GRAVIA.IND.BR | AI31: TAYNARA.ANDRADE@GRAVIA.IND.BR | AK31: JOSE DA SILVA GRAVIA | AL31: SOCIO ADMINISTRADOR | AW31: 2539001-Serviços de usinagem, torneiria e solda\4321500-Instalação e manutenção elétrica\4613300-Representantes comerciais e agentes do comércio de madeira, material de construção e ferragens\4669999-Comércio atacadista de outras máquinas e equipamentos não especificados anteriormente, partes e peças\4672900-Comércio atacadista de ferragens e ferramentas\4673700-Comércio atacadista de material elétrico\4742300-Comércio varejista de material elétrico\4744001-Comércio varejista de ferragens e ferramentas\4789099-Comércio varejista de outros produtos não especificados anteriormente\7112000-Serviços de engenharia | AX31: 10.230.693-1 | AY31: S
A32: 51.485.274/0001-59 | B32: EMPRESA DE TRANSPORTES COVRE LTDA | D32: GRANDE | E32: 169379310 | F32: 8000000 | G32: 331 | H32: 470 | I32: RISCO MÉDIO | J32: ATIVA | K32: 4930202 | L32: Transporte rodoviário de carga, exceto produtos perigosos e mudanças, intermunicipal, interestadual e internacional | M32: 8/7/1969 | N32: 6 | O32: ANHANGUERA | P32: SN | Q32: KM 147 5 | R32: JARDIM NOVA LIMEIRA | S32: LIMEIRA | T32: SP | U32: 13486199 | V32: 19 | W32: 971449857 | X32: Celular | Y32: 19 | Z32: 996434035 | AA32: Celular | AB32: 19 | AC32: 996980432 | AD32: Celular | AE32: 19 | AF32: 34514688 | AG32: Fixo | AH32: NFE.ADM@COVRE.COM.BR | AI32: MELISSA.COVRE@COVRE.COM.BR | AJ32: ADRIANO.DIAS@COVRE.COM.BR | AK32: ANTONIO APARECIDO COVRE | AL32: ADMINISTRADOR | AM32: 13 | AN32: 991332985 | AO32: JOAO COVRE FILHO | AP32: ADMINISTRADOR | AQ32: 13 | AR32: 991222902 | AS32: EDISON COVRE | AT32: ADMINISTRADOR | AW32: 4930203-Transporte rodoviário de produtos perigosos\5211701-Armazéns gerais - emissão de warrant\5211799-Depósitos de mercadorias para terceiros, exceto armazéns gerais e guarda-móveis\5250804-Organização logística do transporte de carga\8211300-Serviços combinados de escritório e apoio administrativo\ | AX32: 417.002.539.118 | AY32: N
A33: 83.177.170/0001-73 | B33: FRIGORIFICO GESSNER LTDA | D33: MÉDIA | E33: 161618293 | F33: 1660000 | G33: 295 | H33: 978 | I33: RISCO MUITO BAIXO | J33: ATIVA | K33: 1011201 | L33: Frigorífico - abate de bovinos | M33: 4/13/1976 | N33: 1 | O33: FRITZ LORENZ | P33: 3520 | Q33: ST IND | S33: TIMBO | T33: SC | U33: 89120000 | V33: 47 | W33: 999093997 | X33: Celular | Y33: 47 | Z33: 992373817 | AA33: Celular | AB33: 47 | AC33: 992868915 | AD33: Celular | AE33: 47 | AF33: 32811500 | AG33: Fixo | AH33: ROGERIO@FRIGORIFICOGESSNER.COM.BR | AK33: CONRAD GESSNER | AL33: SOCIO-ADMINISTRADOR | AM33: 47 | AN33: 999737055 | AW33: 1011205-Matadouro - abate de reses sob contrato, exceto abate de suínos\1013901-Fabricação de produtos de carne\1013902-Preparação de subprodutos do abate\1052000-Fabricação de laticínios\1099699-Fabricação de outros produtos alimentícios não especificados anteriormente\4631100-Comércio atacadista de leite e laticínios\4634699-Comércio atacadista de carnes e derivados de outros animais\4639701-Comércio atacadista de produtos alimentícios em geral\4689399-Comércio atacadista especializado em outros produtos intermediários não especificados anteriormente\4721103-Comércio varejista de laticínios e frios\4722901-Comércio varejista de carnes - açougues\4729699-Comércio varejista de produtos alimentícios em geral ou especializado em produtos alimentícios não especificados anteriormente\4930201-Transporte rodoviário de carga, exceto produtos perigosos e mudanças, municipal\4930202-Transporte rodoviário de carga, exceto produtos perigosos e mudanças, intermunicipal, interestadual e internacional | AX33: 250436086 | AY33: N
A34: 05.388.226/0001-25 | B34: APM TERMINALS PECEM OPERACOES PORTUARIAS LTDA | C34: APM TERMINALS PECEM | D34: MÉDIA | E34: 160132283 | F34: 51217940 | G34: 502 | H34: 448 | I34: RISCO MÉDIO | J34: ATIVA | K34: 5231102 | L34: Atividades do Operador Portuário | M34: 11/5/2002 | N34: 3 | O34: MARCOS MACEDO | P34: 1255 | Q34: AP 1301 | R34: ALDEOTA | S34: FORTALEZA | T34: CE | U34: 60150190 | V34: 85 | W34: 981180337 | X34: Celular | Y34: 85 | Z34: 981754404 | AA34: Celular | AB34: 85 | AC34: 981830904 | AD34: Celular | AE34: 85 | AF34: 33722718 | AG34: Fixo | AH34: MARCIALINNA@GMAIL.COM | AK34: UNILINK TRANSPORTES INTEGRADOS LTDA | AL34: SOCIO | AM34: 85 | AN34: 32310075 | AO34: APM TERMINALS BV | AP34: SOCIO PESSOA JURIDICA DOMICILIADO NO EXTERIOR | AS34: ANDRE LUIS GONZAGA OURIVES | AT34: ADMINISTRADOR | AU34: 13 | AV34: 981481889 | AW34: 4930201-Transporte rodoviário de carga, exceto produtos perigosos e mudanças, municipal\5212500-Carga e descarga\5231101-Administração da infraestrutura portuária\7739099-Aluguel de outras máquinas e equipamentos comerciais e industriais não especificados anteriormente, sem operador | AX34: 06.674197-1 | AY34: N
A35: 40.924.102/0001-18 | B35: KATOEN NATIE DO BRASIL LTDA | D35: GRANDE | E35: 155388526 | F35: 49801300 | G35: 358 | H35: 435 | I35: RISCO MÉDIO | J35: ATIVA | K35: 5211701 | L35: Armazéns gerais - emissão de warrant | M35: 9/10/1991 | N35: 5 | O35: VIENA | P35: 419 | Q35: PARTE | R35: CASCATA | S35: PAULINIA | T35: SP | U35: 13146055 | V35: 19 | W35: 996859338 | X35: Celular | Y35: 19 | Z35: 998251382 | AA35: Celular | AB35: 19 | AC35: 999849520 | AD35: Celular | AE35: 19 | AF35: 21161506 | AG35: Fixo | AH35: FISCAL@KATOENNATIE.COM.BR | AI35: KATHERINE.DIMAIO@KATOENNATIE.COM.BR | AJ35: INFORMATICA@KATOENNATIE.COM.BR | AK35: DISTRILOG EMPREENDIMENTOS, COMERCIO E IMPORTACAO LTDA | AL35: SOCIO | AM35: 19 | AN35: 21161500 | AO35: KATOEN NATIE LOGISTICA LTDA | AP35: SOCIO | AQ35: 19 | AR35: 21161500 | AS35: MARCAL LUIZ FEITOSA FERRARI | AT35: SOCIO ADMINISTRADOR | AU35: 19 | AV35: 992060740 | AW35: 3314722-Manutenção e reparação de máquinas e aparelhos para a indústria do plástico\3839499-Recuperação de materiais não especificados anteriormente\4930201-Transporte rodoviário de carga, exceto produtos perigosos e mudanças, municipal\4930202-Transporte rodoviário de carga, exceto produtos perigosos e mudanças, intermunicipal, interestadual e internacional\5212500-Carga e descarga\5250804-Organização logística do transporte de carga\5250805-Operador de transporte multimodal - OTM\6810202-Aluguel de imóveis próprios\7739099-Aluguel de outras máquinas e equipamentos comerciais e industriais não especificados anteriormente, sem operador\7830200-Fornecimento e gestão de recursos humanos para terceiros\8292000-Envasamento e empacotamento sob contrato\ | AX35: 513.437.141.114 | AY35: N
A36: 04.732.762/0001-33 | B36: SVD TRANSPORTES RODOVIARIOS S/A | C36: SVD TRANSPORTES | D36: GRANDE | E36: 150572118 | F36: 3000000 | G36: 166 | H36: 664 | I36: RISCO BAIXO | J36: ATIVA | K36: 4930202 | L36: Transporte rodoviário de carga, exceto produtos perigosos e mudanças, intermunicipal, interestadual e internacional | M36: 10/17/2001 | N36: 10 | O36: LODOVICO KAMINSKI | P36: 880 | R36: AUGUSTA | S36: CURITIBA | T36: PR | U36: 81265310 | V36: 41 | W36: 996020699 | X36: Celular | Y36: 41 | Z36: 33733330 | AA36: Fixo | AH36: TESOURARIA@GRUPOSVD.COM.BR | AI36: VALERIO@SVDTRANSPORTES.COM.BR | AJ36: FABRICIO.ROSSATO@GRUPOSVD.COM.BR | AK36: ROBERTO EVERALDO TRINDADE | AL36: DIRETOR | AM36: 41 | AN36: 991273577 | AO36: FABRICIO DE ASSIS ROSSATO | AP36: DIRETOR | AQ36: 41 | AR36: 999449973 | AS36: FABIANA ROSSATO TRINDADE | AT36: DIRETOR | AU36: 41 | AV36: 988598799 | AW36: 4731800-Comércio varejista de combustíveis para veículos automotores\4930201-Transporte rodoviário de carga, exceto produtos perigosos e mudanças, municipal\5211701-Armazéns gerais - emissão de warrant\5223100-Estacionamento de veículos\5250803-Agenciamento de cargas, exceto para o transporte marítimo\7711000-Locação de automóveis sem condutor\7820500-Locação de mão de obra temporária\8111700-Serviços combinados para apoio a edifícios, exceto condomínios prediais | AX36: 90246629-07 | AY36: N
A37: 07.298.131/0001-46 | B37: CYA VERDE LOGISTICA LTDA | C37: CIA VERDE | D37: GRANDE | E37: 147662784 | F37: 114472185 | G37: 476 | H37: 500 | I37: RISCO MÉDIO | J37: ATIVA | K37: 4930202 | L37: Transporte rodoviário de carga, exceto produtos perigosos e mudanças, intermunicipal, interestadual e internacional | M37: 3/29/2005 | N37: 13 | O37: JOAO FREDERICO FOERSTER | P37: 87 | R37: PINHEIRINHO | S37: CURITIBA | T37: PR | U37: 81150340 | V37: 41 | W37: 987868376 | X37: Celular | Y37: 41 | Z37: 991569448 | AA37: Celular | AB37: 41 | AC37: 31334050 | AD37: Fixo | AH37: FINACEIRO@TRANSVIAVERDE.COM.BR | AI37: NFE@CIAVERDELOG.COM.BR | AK37: ELISEU PRADO | AL37: SOCIO ADMINISTRADOR | AM37: 41 | AN37: 999751250 | AO37: MICHELE CAROLINE PRADO RUDEK | AP37: SOCIO ADMINISTRADOR | AQ37: 41 | AR37: 991493322 | AW37: 4930201-Transporte rodoviário de carga, exceto produtos perigosos e mudanças, municipal\5211701-Armazéns gerais - emissão de warrant\5212500-Carga e descarga\7711000-Locação de automóveis sem condutor | AX37: 90391018-63 | AY37: S
A38: 04.431.781/0001-20 | B38: PLAYVENDER INTERNATIONAL LTDA | D38: GRANDE | E38: 137795492 | F38: 9127255 | H38: 257 | I38: RISCO ALTO | J38: ATIVA | K38: 1013901 | L38: Fabricação de produtos de carne | M38: 5/10/2001 | N38: 0 | O38: ZOELO SOLA | P38: 1100 | Q38: AREAS B1 B2 E B3 | R38: TRIANGULO | S38: TRES RIOS | T38: RJ | U38: 25820180 | V38: 24 | W38: 998719244 | X38: Celular | Y38: 24 | Z38: 998853321 | AA38: Celular | AB38: 24 | AC38: 999029232 | AD38: Celular | AE38: 24 | AF38: 22518118 | AG38: Fixo | AH38: EDUARDO@FINTERNATIONAL.COM.BR | AI38: BRUNA.ALMEIDA@FINTERNATIONAL.COM.BR | AJ38: CHRISTIANBUNEL@FINTERNATIONAL.COM.BR | AK38: AGROPECUARIA E PARTICIPACOES NOVA CAMPOS LTDA | AL38: SOCIO | AO38: CLAUDIO RENATO DA NOVA CAMPOS | AP38: ADMINISTRADOR | AQ38: 21 | AR38: 977319791 | AW38: 2869100-Fabricação de máquinas e equipamentos para uso industrial específico não especificados anteriormente, peças e acessórios\4623106-Comércio atacadista de sementes, flores, plantas e gramas\4623199-Comércio atacadista de matérias-primas agrícolas não especificadas anteriormente\4632001-Comércio atacadista de cereais e leguminosas beneficiados\4634603-Comércio atacadista de pescados e frutos do mar\4635401-Comércio atacadista de água mineral\4635402-Comércio atacadista de cerveja, chope e refrigerante\4635403-Comércio atacadista de bebidas com atividade de fracionamento e acondicionamento associada\4635499-Comércio atacadista de bebidas não especificadas anteriormente\4637199-Comércio atacadista especializado em outros produtos alimentícios não especificados anteriormente\4639701-Comércio atacadista de produtos alimentícios em geral\4644301-Comércio atacadista de medicamentos e drogas de uso humano\4645101-Comércio atacadista de instrumentos e materiais para uso médico, cirúrgico, hospitalar e de laboratórios\4646001-Comércio atacadista de cosméticos e produtos de perfumaria\4646002-Comércio atacadista de produtos de higiene pessoal\4649401-Comércio atacadista de equipamentos elétricos de uso pessoal e doméstico\4663000-Comércio atacadista de máquinas e equipamentos para uso industrial, partes e peças\4684299-Comércio atacadista de outros produtos químicos e petroquímicos não especificados anteriormente\4789005-Comércio varejista de produtos saneantes domissanitários\5232000-Atividades de agenciamento marítimo\5250801-Comissaria de despachos\5250803-Agenciamento de cargas, exceto para o transporte marítimo\6463800-Outras sociedades de participação, exceto holdings\7490104-Atividades de intermediação e agenciamento de serviços e negócios em geral, exceto imobiliários\7739099-Aluguel de outras máquinas e equipamentos comerciais e industriais não especificados anteriormente, sem operador\ | AX38: 75.474.407 | AY38: N
A39: 87.548.038/0001-81 | B39: ANDERLE-TRANSPORTES LTDA | C39: ANDERLE TRANSPORTES | D39: MÉDIA | E39: 135430871 | F39: 2000000 | G39: 60 | H39: 901 | I39: RISCO MUITO BAIXO | J39: ATIVA | K39: 4930202 | L39: Transporte rodoviário de carga, exceto produtos perigosos e mudanças, intermunicipal, interestadual e internacional | M39: 11/7/1972 | N39: 8 | O39: ANGELINA BARBERINA TOMASI FRACALOSSI | P39: 25 | R39: SAO VALENTIN | S39: BENTO GONCALVES | T39: RS | U39: 95709410 | V39: 54 | W39: 991130702 | X39: Celular | Y39: 54 | Z39: 999040958 | AA39: Celular | AB39: 54 | AC39: 991581200 | AD39: Celular | AE39: 54 | AF39: 25212173 | AG39: Fixo | AH39: ANDERLE@ANDERLETRANSPORTES.COM.BR | AI39: ANDE@ITALNET.COM.BR | AK39: CELSO ANDERLE | AL39: SOCIO ADMINISTRADOR | AM39: 54 | AN39: 984092662 | AO39: CESAR ANDERLE | AP39: SOCIO ADMINISTRADOR | AQ39: 54 | AR39: 991956391 | AW39: 4930201-Transporte rodoviário de carga, exceto produtos perigosos e mudanças, municipal\5250803-Agenciamento de cargas, exceto para o transporte marítimo | AX39: 010/0045111 | AY39: N
A40: 03.523.549/0001-59 | B40: TRANSBEN TRANSPORTES LTDA | D40: GRANDE | E40: 131750883 | F40: 24494762 | G40: 31 | H40: 733 | I40: RISCO MUITO BAIXO | J40: ATIVA | K40: 4930202 | L40: Transporte rodoviário de carga, exceto produtos perigosos e mudanças, intermunicipal, interestadual e internacional | M40: 11/23/1999 | N40: 11 | O40: PRIMEIRO DE MAIO | P40: 900 | Q40: GALPAOA | R40: PRIMEIRO DE MAIO | S40: BRUSQUE | T40: SC | U40: 88353202 | V40: 47 | W40: 991918454 | X40: Celular | Y40: 42 | Z40: 991196441 | AA40: Celular | AB40: 47 | AC40: 992264386 | AD40: Celular | AE40: 47 | AF40: 33500937 | AG40: Fixo | AH40: MARLI.JESUS@TRANSBEN.COM.BR | AI40: FINANCEIRO@TRANSBEN.COM.BR | AJ40: ADRIANO@TRANSBEN.COM.BR | AK40: ADRIANO JOSE BENVENUTTI | AL40: SOCIO ADMINISTRADOR | AM40: 47 | AN40: 999933591 | AO40: JOSE BENVENUTTI | AP40: SOCIO ADMINISTRADOR | AQ40: 47 | AR40: 997738257 | AS40: ANDREA APARECIDA BENVENUTTI HANG | AT40: SOCIO | AW40: 4520005-Serviços de lavagem, lubrificação e polimento de veículos automotores\4923002-Serviço de transporte de passageiros - locação de automóveis com motorista\4930201-Transporte rodoviário de carga, exceto produtos perigosos e mudanças, municipal\4930203-Transporte rodoviário de produtos perigosos\5211799-Depósitos de mercadorias para terceiros, exceto armazéns gerais e guarda-móveis\5212500-Carga e descarga\5223100-Estacionamento de veículos\5229099-Outras atividades auxiliares dos transportes terrestres não especificadas anteriormente\5250803-Agenciamento de cargas, exceto para o transporte marítimo\5250805-Operador de transporte multimodal - OTM\7490104-Atividades de intermediação e agenciamento de serviços e negócios em geral, exceto imobiliários\7711000-Locação de automóveis sem condutor\7719599-Locação de outros meios de transporte não especificados anteriormente, sem condutor\8129000-Atividades de limpeza não especificadas anteriormente | AX40: 253974747 | AY40: N
A41: 76.667.682/0001-52 | B41: BUDEL TRANSPORTES LTDA | D41: GRANDE | E41: 125806988 | F41: 12855000 | G41: 415 | H41: 662 | I41: RISCO BAIXO | J41: ATIVA | K41: 4930202 | L41: Transporte rodoviário de carga, exceto produtos perigosos e mudanças, intermunicipal, interestadual e internacional | M41: 2/23/1983 | N41: 18 | O41: BENJAMIM CLAUDINO BARBOSA | P41: 13275 | Q41: LOTE FUNDOS | R41: ZACARIAS | S41: SAO JOSE DOS PINHAIS | T41: PR | U41: 83025323 | V41: 41 | W41: 999775171 | X41: Celular | Y41: 41 | Z41: 32566452 | AA41: Fixo | AH41: ANDERSON@BUDEL.COM.BR | AI41: JEANE@BUDEL.COM.BR | AJ41: ANDRESSA.CRUZ@BUDEL.COM.BR | AK41: MAC ADMINISTRACAO LTDA. | AL41: SOCIO | AM41: 41 | AN41: 999342524 | AO41: MARCUS VINICIUS BUDEL | AP41: SOCIO ADMINISTRADOR | AQ41: 41 | AR41: 999570531 | AS41: CAMILA BUDEL | AT41: SOCIO | AU41: 41 | AV41: 999355354 | AW41: 4313400-Obras de terraplenagem\4511101-Comércio a varejo de automóveis, camionetas e utilitários novos\4511102-Comércio a varejo de automóveis, camionetas e utilitários usados\4923002-Serviço de transporte de passageiros - locação de automóveis com motorista\4929901-Transporte rodoviário coletivo de passageiros, sob regime de fretamento, municipal\4929902-Transporte rodoviário coletivo de passageiros, sob regime de fretamento, intermunicipal, interestadual e internacional\4930201-Transporte rodoviário de carga, exceto produtos perigosos e mudanças, municipal\4930203-Transporte rodoviário de produtos perigosos\5223100-Estacionamento de veículos\7711000-Locação de automóveis sem condutor\7719599-Locação de outros meios de transporte não especificados anteriormente, sem condutor\7731400-Aluguel de máquinas e equipamentos agrícolas sem operador | AX41: 11200435-16 | AY41: S
A42: 53.611.828/0001-42 | B42: POLIVIAS S/A TRANSPORTES E SERVICOS | D42: GRANDE | E42: 122032463 | F42: 4800000 | G42: 13 | H42: 783 | I42: RISCO MUITO BAIXO | J42: ATIVA | K42: 4930202 | L42: Transporte rodoviário de carga, exceto produtos perigosos e mudanças, intermunicipal, interestadual e internacional | M42: 7/12/1984 | N42: 17 | O42: MOEMA | P42: 87 | Q42: BLOCO A CONJ143 | R42: MOEMA | S42: SAO PAULO | T42: SP | U42: 4077020 | V42: 11 | W42: 982819768 | X42: Celular | Y42: 11 | Z42: 982819753 | AA42: Celular | AB42: 11 | AC42: 991357346 | AD42: Celular | AE42: 11 | AF42: 50535188 | AG42: Fixo | AK42: CASSIO CIAMPOLINI SAMPAIO BARROS | AL42: PRESIDENTE | AM42: 11 | AN42: 996552318 | AO42: CELIA MARIA NEGRAES SAMPAIO BARROS | AP42: DIRETOR | AQ42: 11 | AR42: 982819805 | AW42: 3314708-Manutenção e reparação de máquinas, equipamentos e aparelhos para transporte e elevação de cargas\4911600-Transporte ferroviário de carga\5021102-Transporte por navegação interior de carga, intermunicipal, interestadual e internacional, exceto travessia\5211799-Depósitos de mercadorias para terceiros, exceto armazéns gerais e guarda-móveis\5212500-Carga e descarga\5229099-Outras atividades auxiliares dos transportes terrestres não especificadas anteriormente\5232000-Atividades de agenciamento marítimo\5250802-Atividades de despachantes aduaneiros\5250803-Agenciamento de cargas, exceto para o transporte marítimo\5250804-Organização logística do transporte de carga\6463800-Outras sociedades de participação, exceto holdings\7711000-Locação de automóveis sem condutor\7719599-Locação de outros meios de transporte não especificados anteriormente, sem condutor\7739099-Aluguel de outras máquinas e equipamentos comerciais e industriais não especificados anteriormente, sem operador | AX42: 111.117.917.118 | AY42: N
A43: 71.040.653/0001-42 | B43: CNAGA - ARMAZENS GERAIS ALFANDEGADOS LTDA | D43: MÉDIA | E43: 116514050 | F43: 34415160 | G43: 111 | H43: 682 | I43: RISCO BAIXO | J43: ATIVA | K43: 5211701 | L43: Armazéns gerais - emissão de warrant | M43: 4/10/1968 | N43: 2 | O43: DAS NACOES UNIDAS | P43: 22452 | R43: VILA ALMEIDA | S43: SAO PAULO | T43: SP | U43: 4795000 | V43: 11 | W43: 999606662 | X43: Celular | Y43: 11 | Z43: 996330690 | AA43: Celular | AB43: 11 | AC43: 996295994 | AD43: Celular | AE43: 11 | AF43: 55451966 | AG43: Fixo | AH43: FISCAL@CNAGA.COM.BR | AI43: AMERICO@CNAGA.COM.BR | AJ43: ANGELINA@CNAGA.COM.BR | AK43: JOSE AMERICO RIBEIRO DOS SANTOS | AL43: SOCIO ADMINISTRADOR | AM43: 11 | AN43: 956294289 | AO43: ANGELINA RIBEIRO DOS SANTOS | AP43: SOCIO | AQ43: 11 | AR43: 942689387 | AS43: AMERICO RIBEIRO DOS SANTOS NETO | AT43: SOCIO ADMINISTRADOR | AX43: 109.851.964.119 | AY43: N
A44: 57.317.133/0001-03 | B44: DV3 SOLUCOES LOGISTICAS LTDA | C44: DV3 SOLUCOES LOGISTICAS | D44: GRANDE | E44: 115077399 | F44: 2500000 | G44: 79 | H44: 898 | I44: RISCO MUITO BAIXO | J44: ATIVA | K44: 4930202 | L44: Transporte rodoviário de carga, exceto produtos perigosos e mudanças, intermunicipal, interestadual e internacional | M44: 4/13/1987 | N44: 10 | O44: FARJALA MOISES | P44: 735 | R44: PARQUE RESIDENCIAL CANDIDO PORTINARI | S44: RIBEIRAO PRETO | T44: SP | U44: 14093524 | V44: 34 | W44: 997657500 | X44: Celular | Y44: 11 | Z44: 996729164 | AA44: Celular | AB44: 11 | AC44: 992518011 | AD44: Celular | AE44: 14 | AF44: 32451755 | AG44: Fixo | AH44: COLLETO@DV3SOLUCOES.COM | AI44: MARIANA@JADLOCADORA.COM.BR | AK44: MOISES PAULO SOARES DE CAMPOS | AL44: SOCIO ADMINISTRADOR | AM44: 11 | AN44: 999992754 | AO44: ANDERSON MARCHI DAVO | AP44: SOCIO ADMINISTRADOR | AQ44: 11 | AR44: 999113340 | AS44: MARLENE DE FATIMA MARCHI DAVO | AT44: SOCIO | AW44: 4930201-Transporte rodoviário de carga, exceto produtos perigosos e mudanças, municipal\4930203-Transporte rodoviário de produtos perigosos\4930204-Transporte rodoviário de mudanças\5211799-Depósitos de mercadorias para terceiros, exceto armazéns gerais e guarda-móveis\5212500-Carga e descarga\5240199-Atividades auxiliares dos transportes aéreos, exceto operação dos aeroportos e campos de aterrissagem\5250803-Agenciamento de cargas, exceto para o transporte marítimo\5250804-Organização logística do transporte de carga\5320201-Serviços de malote não realizados pelo Correio Nacional\5320202-Serviços de entrega rápida\7711000-Locação de automóveis sem condutor\7719599-Locação de outros meios de transporte não especificados anteriormente, sem condutor | AX44: 797.175.925.111 | AY44: N
A45: 10.535.766/0001-24 | B45: UNIMETAL TAUBATE INDUSTRIA COMERCIO E EMPREENDIMENTOS LTDA | D45: MÉDIA | E45: 113488796 | F45: 51120215 | G45: 1 | H45: 788 | I45: RISCO MUITO BAIXO | J45: ATIVA | K45: 1921700 | L45: Fabricação de produtos do refino de petróleo | M45: 11/18/2008 | N45: 1 | O45: CMS-470 | P45: SN | Q45: SETOR B | R45: ITAPAVUSSU | S45: COSMOPOLIS | T45: SP | U45: 13151352 | V45: 12 | W45: 981712771 | X45: Celular | Y45: 15 | Z45: 32357500 | AA45: Fixo | AH45: A.CURBAGE@BRASILCARBONOS.COM.BR | AI45: R.ASSUMPCAO@BRASILCARBONOS.COM.BR | AK45: LUIS GUILHERME STELLA LIMA | AL45: DIRETOR | AM45: 15 | AN45: 988222474 | AO45: MAURICIO TUMOLO FILHO | AP45: ADMINISTRADOR | AQ45: 11 | AR45: 966303030 | AS45: UNIMETAL INDUSTRIA COMERCIO E EMPREENDIMENTOS LTDA | AT45: SOCIO | AU45: 15 | AV45: 32357541 | AW45: 4930202-Transporte rodoviário de carga, exceto produtos perigosos e mudanças, intermunicipal, interestadual e internacional\5212500-Carga e descarga | AX45: 276.031.274.113 | AY45: N
A46: 55.065.981/0001-47 | B46: EMPRESA DE TRANSPORTES RODOJACTO LTDA | C46: RODOJACTO | D46: MÉDIA | E46: 112772225 | F46: 47185000 | G46: 109 | H46: 700 | I46: RISCO BAIXO | J46: ATIVA | K46: 4930202 | L46: Transporte rodoviário de carga, exceto produtos perigosos e mudanças, intermunicipal, interestadual e internacional | M46: 12/12/1969 | N46: 2 | O46: SP 294 COMANDANTE JOAO RIBEIRO DE BARROS | Q46: KM 476 SN | R46: ZONA RURAL | S46: ORIENTE | T46: SP | U46: 17570000 | V46: 14 | W46: 997976222 | X46: Celular | Y46: 14 | Z46: 996720189 | AA46: Celular | AB46: 14 | AC46: 997244752 | AD46: Celular | AE46: 14 | AF46: 34052314 | AG46: Fixo | AH46: ROBSON.LUCAS@RODOJACTO.COM.BR | AI46: PAULO.OLIVA@RODOJACTO.COM.BR | AJ46: ANDRE.OLIVA@RODOJACTO.COM.BR | AK46: JORGE NISHIMURA | AL46: SOCIO-ADMINISTRADOR | AM46: 14 | AN46: 981159458 | AO46: LYO NISHIMURA | AP46: SOCIO-ADMINISTRADOR | AQ46: 11 | AR46: 974451397 | AS46: UJI COMERCIO E PARTICIPACOES LIMITADA | AT46: SOCIO | AU46: 11 | AV46: 32093171 | AX46: 489.008.161.110 | AY46: N
A47: 13.294.850/0001-91 | B47: J.A COMERCIO DE GENEROS ALIMENTICIOS E SERVICOS LTDA | D47: MÉDIA | E47: 110142622 | F47: 9020085 | G47: 162 | H47: 574 | I47: RISCO BAIXO | J47: ATIVA | K47: 1013901 | L47: Fabricação de produtos de carne | M47: 2/18/2011 | N47: 1 | O47: JOAO AMATO | P47: 2735 | R47: CHACARA LAGOA BRANCA | S47: CAMPO LIMPO PAULISTA | T47: SP | U47: 13231620 | V47: 11 | W47: 937043889 | X47: Celular | Y47: 11 | Z47: 942241131 | AA47: Celular | AB47: 11 | AC47: 942378961 | AD47: Celular | AE47: 11 | AF47: 29236321 | AG47: Fixo | AH47: GERENTEADMINISTRATIVO@JALIMENTOS.COM.BR | AI47: BIRA@JAALIMENTOS.COM.BR | AK47: TUPANANGIL TRICAI MAGALHAES | AL47: SOCIO-ADMINISTRADOR | AM47: 11 | AN47: 937043889 | AW47: 4617600-Representantes comerciais e agentes do comércio de produtos alimentícios, bebidas e fumo\4634601-Comércio atacadista de carnes bovinas e suínas e derivados\4639701-Comércio atacadista de produtos alimentícios em geral\4684201-Comércio atacadista de resinas e elastômeros\4686902-Comércio atacadista de embalagens\4722901-Comércio varejista de carnes - açougues\4930201-Transporte rodoviário de carga, exceto produtos perigosos e mudanças, municipal\4930202-Transporte rodoviário de carga, exceto produtos perigosos e mudanças, intermunicipal, interestadual e internacional\5211799-Depósitos de mercadorias para terceiros, exceto armazéns gerais e guarda-móveis\8211300-Serviços combinados de escritório e apoio administrativo | AX47: 245.075.776.118 | AY47: N
A48: 47.400.817/0001-10 | B48: ATIMAKY ESQUADRIAS METALICAS LTDA | D48: MÉDIA | E48: 107948308 | F48: 9348499 | G48: 124 | H48: 925 | I48: RISCO MUITO BAIXO | J48: ATIVA | K48: 2512800 | L48: Fabricação de esquadrias de metal | M48: 1/13/1976 | N48: 1 | O48: DOS MAMOEIROS | P48: 99 | R48: LOTEAMENTO QUINTA DAS FRUTAS | S48: TAUBATE | T48: SP | U48: 12092520 | V48: 12 | W48: 981096111 | X48: Celular | Y48: 12 | Z48: 981092444 | AA48: Celular | AB48: 12 | AC48: 981920809 | AD48: Celular | AE48: 12 | AF48: 36813366 | AG48: Fixo | AH48: CONTABILIDADE@ATIMAKY.COM | AI48: ALEXANDER@ATIMAKY.COM.BR | AJ48: COMPLETELINE@ATIMAKY.COM.BR | AK48: TATEO TAKAHASHI | AL48: SOCIO ADMINISTRADOR | AM48: 12 | AN48: 974080020 | AO48: ALEXANDER TATEO SHODO TAKAHASHI | AP48: SOCIO | AQ48: 12 | AR48: 996249230 | AS48: ILTON TAKESHI SHODO TAKAHASHI | AT48: SOCIO | AU48: 11 | AV48: 999752513 | AW48: 2511000-Fabricação de estruturas metálicas\2949299-Fabricação de outras peças e acessórios para veículos automotores não especificadas anteriormente\4292801-Montagem de estruturas metálicas\4330402-Instalação de portas, janelas, tetos, divisórias e armários embutidos de qualquer material\8211300-Serviços combinados de escritório e apoio administrativo\ | AX48: 688.458.021.111 | AY48: N
A49: 54.423.934/0001-65 | B49: ARANAO TRANSPORTES RODOVIARIOS LTDA | D49: MÉDIA | E49: 105779289 | F49: 2000000 | G49: 236 | H49: 638 | I49: RISCO BAIXO | J49: ATIVA | K49: 4930202 | L49: Transporte rodoviário de carga, exceto produtos perigosos e mudanças, intermunicipal, interestadual e internacional | M49: 4/28/1985 | N49: 8 | O49: BR-116 | Q49: KM 15 | R49: PEDRAS | S49: FORTALEZA | T49: CE | U49: 60874502 | V49: 14 | W49: 991314025 | X49: Celular | Y49: 14 | Z49: 991510509 | AA49: Celular | AB49: 14 | AC49: 981012000 | AD49: Celular | AE49: 14 | AF49: 34223355 | AG49: Fixo | AH49: CELIO@ARANAOTRANSPORTES.COM.BR | AK49: ARANAO HOLDING PARTICIPACOES LTDA | AL49: SOCIO | AM49: 14 | AN49: 33069074 | AO49: FABIO AGAPITO ARANAO | AP49: SOCIO ADMINISTRADOR | AQ49: 14 | AR49: 997844808 | AS49: ALEXANDRE AGAPITO ARANAO | AT49: SOCIO ADMINISTRADOR | AU49: 14 | AV49: 991279857 | AW49: 4520005-Serviços de lavagem, lubrificação e polimento de veículos automotores\4930201-Transporte rodoviário de carga, exceto produtos perigosos e mudanças, municipal\5211799-Depósitos de mercadorias para terceiros, exceto armazéns gerais e guarda-móveis\5212500-Carga e descarga\5223100-Estacionamento de veículos\7711000-Locação de automóveis sem condutor\7739099-Aluguel de outras máquinas e equipamentos comerciais e industriais não especificados anteriormente, sem operador\ | AX49: 438.051.413.114 | AY49: N
